Workbook
Name ESTACOES: _xlfn.anchorarray('Cadastro Estacoes'!$AZ$1)
Name ItemCadastrado: CadastroItens[ITEM]
Name PROJETO: _xlfn.anchorarray('Cadastro Estacoes'!$BA$1)
Name TAB_FALHA: Tabela_FALHA[FALHA]
Name TAB_ITEM: Tabela_ITEM[ITEM]
Name TAB_MOTIVO: Tabela_MOTIVO[MOTIVO]
Name ItemCadastrado: CadastroItens[ITEM]
Name TAB_FALHA: Tabela_FALHA[FALHA]
Name TAB_ITEM: Tabela_ITEM[ITEM]
Name TAB_MOTIVO: Tabela_MOTIVO[MOTIVO]
Name ItemCadastrado: CadastroItens[ITEM]
Name TAB_FALHA: Tabela_FALHA[FALHA]
Name TAB_ITEM: Tabela_ITEM[ITEM]
Name TAB_MOTIVO: Tabela_MOTIVO[MOTIVO]
Name ItemCadastrado: CadastroItens[ITEM]
Name TAB_FALHA: Tabela_FALHA[FALHA]
Name TAB_ITEM: Tabela_ITEM[ITEM]
Name TAB_MOTIVO: Tabela_MOTIVO[MOTIVO]
Name ItemCadastrado: CadastroItens[ITEM]
Name TAB_FALHA: Tabela_FALHA[FALHA]
Name TAB_ITEM: Tabela_ITEM[ITEM]
Name TAB_MOTIVO: Tabela_MOTIVO[MOTIVO]
Name ItemCadastrado: CadastroItens[ITEM]
Name TAB_FALHA: Tabela_FALHA[FALHA]
Name TAB_ITEM: Tabela_ITEM[ITEM]
Name TAB_MOTIVO: Tabela_MOTIVO[MOTIVO]
Name TAB_FALHA: Tabela_FALHA[FALHA]
Name TAB_ITEM: Tabela_ITEM[ITEM]
Name TAB_MOTIVO: Tabela_MOTIVO[MOTIVO]
Name TAB_FALHA: Tabela_FALHA[FALHA]
Name TAB_ITEM: Tabela_ITEM[ITEM]
Name TAB_MOTIVO: Tabela_MOTIVO[MOTIVO]
Name TAB_FALHA: Tabela_FALHA[FALHA]
Name TAB_ITEM: Tabela_ITEM[ITEM]
Name TAB_MOTIVO: Tabela_MOTIVO[MOTIVO]
Name TAB_FALHA: Tabela_FALHA[FALHA]
Name TAB_ITEM: Tabela_ITEM[ITEM]
Name TAB_MOTIVO: Tabela_MOTIVO[MOTIVO]
Name TAB_FALHA: Tabela_FALHA[FALHA]
Name TAB_ITEM: Tabela_ITEM[ITEM]
Name TAB_MOTIVO: Tabela_MOTIVO[MOTIVO]
Name TAB_FALHA: Tabela_FALHA[FALHA]
Name TAB_ITEM: Tabela_ITEM[ITEM]
Name TAB_MOTIVO: Tabela_MOTIVO[MOTIVO]
Name TAB_FALHA: Tabela_FALHA[FALHA]
Name TAB_ITEM: Tabela_ITEM[ITEM]
Name TAB_MOTIVO: Tabela_MOTIVO[MOTIVO]
Name TAB_FALHA: Tabela_FALHA[FALHA]
Name TAB_ITEM: Tabela_ITEM[ITEM]
Name TAB_MOTIVO: Tabela_MOTIVO[MOTIVO]
Name TAB_FALHA: Tabela_FALHA[FALHA]
Name TAB_ITEM: Tabela_ITEM[ITEM]
Name TAB_MOTIVO: Tabela_MOTIVO[MOTIVO]
Name resp: RespStatusEstacoes!$A$1:$A$21

Sheet RespStatusEstacoes
A1: LFF | B1: Luiz Fernando Campos Furlan | C1: fernando@hidromares.com.br | E1: CO
A2: RS | B2: Rodrigo Saggiomo | C2: rodrigo@hidromares.com.br | E2: Qualidade
A3: ADC | B3: Alexandre De Caroli | C3: alexandre@hidromares.com.br | E3: DT
A4: GCA | B4: Gabriel Paschoal | C4: gabriel@hidromares.com.br | E4: DC
A5: FMS | B5: Francisco Moreira Silvério | C5: francisco@hidromares.com.br | E5: CO
A6: LSP | B6: Lucas Pagano | C6: lucas@hidromares.com.br | E6: O
A7: FPM | B7: Felipe Porfírio Marques | C7: felipe.marques@hidromares.com.br | E7: O
A8: EMD | B8: Eliezer Matias Lima dos Santos Dias | C8: eliezer@hidromares.com.br | E8: T
A9: EJC | B9: Edmar de Jesus Cardoso | C9: edmar@hidromares.com.br | E9: O
A10: DSS | B10: Diego de Sena Santos | C10: diego@hidromares.com.br | E10: A
A11: RO | B11: Renato Oliveira | C11: renato@hidromares.com.br | E11: O
A12: VCP | B12: Vanessa | C12: vanessa@hidromares.com.br | E12: O
... A20: LHC | B20: Luiz Henrique dos Santos Cruz | C20: luiz.cruz@hidromares.com.br | E20: A
A23: Feito | B23: Alta
A24: A fazer | B24: Média
A25: Fazendo | B25: Baixa

Sheet Planilha1
A2: {=_xlws.FILTER(Pendencias!A:Q,Pendencias!L:L="ADC","")} -> #NAME?

Sheet Pendencias Feitas Backup
A2: P0008 | B2: HMCSNB22 | C2: Levar e instalar RNS para nivelamento | D2: 1 | E2: 43434 | F2: =IF(Tabela18[[#This Row],[Estações]]="HMOFICINA","VMS",IFERROR(VLOOKUP(B2,'Cadastro Estacoes'!$A$2:$Z$201,26,0),"")) -> #ERROR! | G2: Feito | I2: RN | J2: 1 | K2: EMD | L2: ESS | M2: 43410 | N2: C | O2: 43410 | P2: =IFERROR(VLOOKUP(B2,'Cadastro Estacoes'!$A:$B,2,0),"") -> SISMO®CSN
A3: P0021 | B3: HMPDMDOLFIM08 | C3: Realizar um dia de lançamento de derivadores | D3: 2 | E3: 11/10/2019 | F3: =IF(Tabela18[[#This Row],[Estações]]="HMOFICINA","VMS",IFERROR(VLOOKUP(B3,'Cadastro Estacoes'!$A$2:$Z$201,26,0),"")) -> #ERROR! | G3: Feito | H3: Separar um dia do campo apenas para isso | I3: 2 derivadores; 2 GPS reservas | K3: LSP | L3: FMS | M3: 30/04/2019 | N3: C | O3: 43956 | P3: =IFERROR(VLOOKUP(B3,'Cadastro Estacoes'!$A:$B,2,0),"") -> SISMO®VALEPDM
A4: P0024 | B4: HMPSEPIER | C4: Colocar tampa no furo do alçapão do tubulão | D4: 2 | E4: 20/03/2020 | F4: =IF(Tabela18[[#This Row],[Estações]]="HMOFICINA","VMS",IFERROR(VLOOKUP(B4,'Cadastro Estacoes'!$A$2:$Z$201,26,0),"")) -> #ERROR! | G4: Feito | H4: esta pendeencia está atrelada à P0671 | K4: EMD | L4: EJC | M4: 17/01/2020 | N4: C | O4: 44206 | P4: =IFERROR(VLOOKUP(B4,'Cadastro Estacoes'!$A:$B,2,0),"") -> SISMO®PSE
A5: P0025 | B5: HMTJMONTANHA | C5: Realizar um dia de lançamento de derivadores | D5: 1 | E5: 31/03/2020 | F5: =IF(Tabela18[[#This Row],[Estações]]="HMOFICINA","VMS",IFERROR(VLOOKUP(B5,'Cadastro Estacoes'!$A$2:$Z$201,26,0),"")) -> #ERROR! | G5: Feito | H5: Separar um dia do campo apenas para isso | I5: 2 derivadores; 2 GPS reservas | L5: FMS | M5: 30/04/2019 | N5: C | P5: =IFERROR(VLOOKUP(B5,'Cadastro Estacoes'!$A:$B,2,0),"") -> SISMO®TAPAJOS
A6: P0029 | B6: HMTJTORRE1 | C6: Instalar abracadeira de inox para prender tubo do young na madeira | D6: 0 | E6: 24/05/2020 | F6: =IF(Tabela18[[#This Row],[Estações]]="HMOFICINA","VMS",IFERROR(VLOOKUP(B6,'Cadastro Estacoes'!$A$2:$Z$201,26,0),"")) -> #ERROR! | G6: Feito | H6: Abraçadeira de inox 64-83 é pequena | K6: CCL | L6: ESS | M6: 13/05/2019 | N6: C | O6: 44110 | P6: =IFERROR(VLOOKUP(B6,'Cadastro Estacoes'!$A:$B,2,0),"") -> SISMO®TAPAJOS
A7: P0055 | B7: HMQIGUARAS | C7: Trocar a régua de maré | D7: 3 | E7: 29/10/2019 | F7: =IF(Tabela18[[#This Row],[Estações]]="HMOFICINA","VMS",IFERROR(VLOOKUP(B7,'Cadastro Estacoes'!$A$2:$Z$201,26,0),"")) -> #ERROR! | G7: Feito | H7: Estão faltando 4 lances de régua | K7: FPM | L7: VCP | M7: 30/07/2019 | N7: C | O7: 43767 | P7: =IFERROR(VLOOKUP(B7,'Cadastro Estacoes'!$A:$B,2,0),"") -> SISMO®QUIRIRI
A8: P0059 | B8: HMPSEPIER | C8: Fazer lançamentos de CastAway próximo ao sensor CT, 4 antes e 4 após a limpeza no sensor, com intervalos de 5 minutos entre os lançamentos | D8: 1 | E8: Permanente | F8: =IF(Tabela18[[#This Row],[Estações]]="HMOFICINA","VMS",IFERROR(VLOOKUP(B8,'Cadastro Estacoes'!$A$2:$Z$201,26,0),"")) -> #ERROR! | G8: Feito | I8: CastAway | K8: EMD | L8: VCP | M8: 30/07/2019 | N8: C | O8: 43900 | P8: =IFERROR(VLOOKUP(B8,'Cadastro Estacoes'!$A:$B,2,0),"") -> SISMO®PSE
A9: P0108 | B9: HMPPMIRA | C9: fazer suporte para caixa de bateria | D9: 1 | E9: 20/10/2019 | F9: =IF(Tabela18[[#This Row],[Estações]]="HMOFICINA","VMS",IFERROR(VLOOKUP(B9,'Cadastro Estacoes'!$A$2:$Z$201,26,0),"")) -> #ERROR! | G9: Feito | H9: está sobreposta sobre as baterias dos eqp. praticagem | I9: parafusos/buchas/arroelas/porcas | K9: FPM | L9: JBM | M9: 16/09/2019 | N9: O | O9: 16/09/2019 | P9: =IFERROR(VLOOKUP(B9,'Cadastro Estacoes'!$A:$B,2,0),"") -> SISMO®PARANAGUAPILOTS
A10: P0109 | B10: HMCAPIER | C10: Fazer uma regua de mare para substituir a danificada | D10: 0 | E10: 20/10/2019 | F10: =IF(Tabela18[[#This Row],[Estações]]="HMOFICINA","VMS",IFERROR(VLOOKUP(B10,'Cadastro Estacoes'!$A$2:$Z$201,26,0),"")) -> #ERROR! | G10: Feito | K10: FPM | L10: JBM | M10: 16/09/2019 | N10: O | O10: 16/09/2019 | P10: =IFERROR(VLOOKUP(B10,'Cadastro Estacoes'!$A:$B,2,0),"") -> SISMO®CATTALINI
A11: P0112 | B11: HMPDMDOLFIM15 | C11: Levar Cracha Vale | D11: 0 | E11: Permanente | F11: =IF(Tabela18[[#This Row],[Estações]]="HMOFICINA","VMS",IFERROR(VLOOKUP(B11,'Cadastro Estacoes'!$A$2:$Z$201,26,0),"")) -> #ERROR! | G11: Feito | I11: Crachá | K11: LSP | L11: LSP | M11: 16/09/2019 | N11: C | O11: 29/11/2019 | P11: =IFERROR(VLOOKUP(B11,'Cadastro Estacoes'!$A:$B,2,0),"") -> SISMO®VALEPDM
A12: P0113 | B12: HMPDMDOLFIM08 | C12: Adaptar APR para manobra a ser realizada. | D12: 0 | E12: Permanente | F12: =IF(Tabela18[[#This Row],[Estações]]="HMOFICINA","VMS",IFERROR(VLOOKUP(B12,'Cadastro Estacoes'!$A$2:$Z$201,26,0),"")) -> #ERROR! | G12: Feito | I12: APR preenchida | K12: LSP | L12: LSP | M12: 16/09/2019 | N12: O | O12: 24/01/2020 | P12: =IFERROR(VLOOKUP(B12,'Cadastro Estacoes'!$A:$B,2,0),"") -> SISMO®VALEPDM
A13: P0114 | B13: HMPDMDOLFIM08 | C13: Levar Cracha Vale | D13: 0 | E13: Permanente | F13: =IF(Tabela18[[#This Row],[Estações]]="HMOFICINA","VMS",IFERROR(VLOOKUP(B13,'Cadastro Estacoes'!$A$2:$Z$201,26,0),"")) -> #ERROR! | G13: Feito | I13: Crachá | K13: LSP | L13: LSP | M13: 16/09/2019 | N13: C | O13: 01/03/2020 | P13: =IFERROR(VLOOKUP(B13,'Cadastro Estacoes'!$A:$B,2,0),"") -> SISMO®VALEPDM
A14: P0115 | B14: HMPDMDOLFIM15 | C14: Adaptar APR para manobra a ser realizada. | D14: 0 | E14: Permanente | F14: =IF(Tabela18[[#This Row],[Estações]]="HMOFICINA","VMS",IFERROR(VLOOKUP(B14,'Cadastro Estacoes'!$A$2:$Z$201,26,0),"")) -> #ERROR! | G14: Feito | I14: APR preenchida | K14: LSP | L14: LSP | M14: 16/09/2019 | N14: O | O14: 23/03/2020 | P14: =IFERROR(VLOOKUP(B14,'Cadastro Estacoes'!$A:$B,2,0),"") -> SISMO®VALEPDM
A15: P0116 | B15: HMPDMPIER01 | C15: Adaptar APR para manobra a ser realizada. | D15: 0 | E15: Permanente | F15: =IF(Tabela18[[#This Row],[Estações]]="HMOFICINA","VMS",IFERROR(VLOOKUP(B15,'Cadastro Estacoes'!$A$2:$Z$201,26,0),"")) -> #ERROR! | G15: Feito | I15: APR preenchida | K15: LSP | L15: LSP | M15: 16/09/2019 | N15: O | O15: 23/03/2020 | P15: =IFERROR(VLOOKUP(B15,'Cadastro Estacoes'!$A:$B,2,0),"") -> SISMO®VALEPDM
A16: P0117 | B16: HMPDMPIER03 | C16: Adaptar APR para manobra a ser realizada. | D16: 0 | E16: Permanente | F16: =IF(Tabela18[[#This Row],[Estações]]="HMOFICINA","VMS",IFERROR(VLOOKUP(B16,'Cadastro Estacoes'!$A$2:$Z$201,26,0),"")) -> #ERROR! | G16: Feito | I16: APR preenchida | K16: LSP | L16: LSP | M16: 16/09/2019 | N16: O | O16: 14/04/2020 | P16: =IFERROR(VLOOKUP(B16,'Cadastro Estacoes'!$A:$B,2,0),"") -> SISMO®VALEPDM
A17: P0118 | B17: HMPDMPIER01 | C17: Levar Cracha Vale | D17: 0 | E17: Permanente | F17: =IF(Tabela18[[#This Row],[Estações]]="HMOFICINA","VMS",IFERROR(VLOOKUP(B17,'Cadastro Estacoes'!$A$2:$Z$201,26,0),"")) -> #ERROR! | G17: Feito | I17: Crachá | K17: LSP | L17: LSP | M17: 16/09/2019 | N17: C | O17: 14/04/2020 | P17: =IFERROR(VLOOKUP(B17,'Cadastro Estacoes'!$A:$B,2,0),"") -> SISMO®VALEPDM
A18: P0119 | B18: HMPDMPIER03 | C18: Levar Cracha Vale | D18: 0 | E18: Permanente | F18: =IF(Tabela18[[#This Row],[Estações]]="HMOFICINA","VMS",IFERROR(VLOOKUP(B18,'Cadastro Estacoes'!$A$2:$Z$201,26,0),"")) -> #ERROR! | G18: Feito | I18: Crachá | K18: LSP | L18: LSP | M18: 16/09/2019 | N18: C | O18: 19/05/2020 | P18: =IFERROR(VLOOKUP(B18,'Cadastro Estacoes'!$A:$B,2,0),"") -> SISMO®VALEPDM
A19: P0120 | B19: HMCAPIER | C19: Levar nova régua para substituir a danificada | D19: 1 | E19: 20/10/2019 | F19: =IF(Tabela18[[#This Row],[Estações]]="HMOFICINA","VMS",IFERROR(VLOOKUP(B19,'Cadastro Estacoes'!$A$2:$Z$201,26,0),"")) -> #ERROR! | G19: Feito | H19: Lembrar da força da maré | I19: regua de maré | K19: FPM | L19: MAS | M19: 16/09/2019 | N19: C | O19: 19/05/2020 | P19: =IFERROR(VLOOKUP(B19,'Cadastro Estacoes'!$A:$B,2,0),"") -> SISMO®CATTALINI
A20: P0122 | B20: HMCAPIER | C20: Alterar catracas que estão fixando o equipamento na pilastra (pegador de uma quebrou) | D20: 0 | E20: 20/10/2019 | F20: =IF(Tabela18[[#This Row],[Estações]]="HMOFICINA","VMS",IFERROR(VLOOKUP(B20,'Cadastro Estacoes'!$A$2:$Z$201,26,0),"")) -> #ERROR! | G20: Feito | H20: substituir as DUAS | I20: DUAS catracas | K20: FPM | L20: MAS | M20: 16/09/2019 | N20: C | O20: 19/05/2020 | P20: =IFERROR(VLOOKUP(B20,'Cadastro Estacoes'!$A:$B,2,0),"") -> SISMO®CATTALINI
A21: P0123 | B21: HMPPMIRA | C21: p/ acessar caixa de equipamento levar chave do cadeado | D21: 0 | E21: 20/10/2019 | F21: =IF(Tabela18[[#This Row],[Estações]]="HMOFICINA","VMS",IFERROR(VLOOKUP(B21,'Cadastro Estacoes'!$A$2:$Z$201,26,0),"")) -> #ERROR! | G21: Feito | H21: caixa do equipamento foi movida para fora da 'casinha' e caixa da bateria está na casaria de fibra da patricagem | I21: chave que está no almo | K21: FPM | L21: MAS | M21: 16/09/2019 | N21: C | O21: 24/06/2020 | P21: =IFERROR(VLOOKUP(B21,'Cadastro Estacoes'!$A:$B,2,0),"") -> SISMO®PARANAGUAPILOTS
A22: P0146 | B22: HMLIB02 | C22: Lançar derivadores | D22: 1 | E22: 25/10/2019 | F22: =IF(Tabela18[[#This Row],[Estações]]="HMOFICINA","VMS",IFERROR(VLOOKUP(B22,'Cadastro Estacoes'!$A$2:$Z$201,26,0),"")) -> #ERROR! | G22: Feito | I22: derivador, gps reserva, ficha de derivadores | K22: EJC | L22: DMP | M22: 25/09/2019 | N22: C | O22: 13/07/2020 | P22: =IFERROR(VLOOKUP(B22,'Cadastro Estacoes'!$A:$B,2,0),"") -> SISMO®LIBRA/MULTI
A23: P0169 | B23: SEM ESTACAO | C23: Alinhar estrutura SSO | D23: 0 | E23: 01/10/2019 | F23: =IF(Tabela18[[#This Row],[Estações]]="HMOFICINA","VMS",IFERROR(VLOOKUP(B23,'Cadastro Estacoes'!$A$2:$Z$201,26,0),"")) -> #ERROR! | G23: Feito | H23: Reunião com Saraiva | K23: DSS | L23: ADC | M23: 26/09/2019 | N23: O | O23: 14/07/2020 | P23: =IFERROR(VLOOKUP(B23,'Cadastro Estacoes'!$A:$B,2,0),"") -> SEM PROJETO
A24: P0187 | B24: SEM ESTACAO | C24: Integrar sensor InnertialLabs | D24: 2 | E24: 05/10/2019 | F24: =IF(Tabela18[[#This Row],[Estações]]="HMOFICINA","VMS",IFERROR(VLOOKUP(B24,'Cadastro Estacoes'!$A$2:$Z$201,26,0),"")) -> #ERROR! | G24: Feito | H24: Aguardando o fabricante enviar o programa para Modificar dados binários | J24: 5 | K24: DSS | L24: LFF | M24: 30/09/2019 | N24: O | O24: 44279 | P24: =IFERROR(VLOOKUP(B24,'Cadastro Estacoes'!$A:$B,2,0),"") -> SEM PROJETO
A25: P0262 | B25: SEM ESTACAO | C25: Cadastrar toda equipe campo nos programas de milhagem | D25: 3 | E25: 11/10/2019 | F25: =IF(Tabela18[[#This Row],[Estações]]="HMOFICINA","VMS",IFERROR(VLOOKUP(B25,'Cadastro Estacoes'!$A$2:$Z$201,26,0),"")) -> #ERROR! | G25: Feito | J25: 1 | K25: DSS | L25: FMS | M25: 03/10/2019 | N25: O | O25: 14/07/2020 | P25: =IFERROR(VLOOKUP(B25,'Cadastro Estacoes'!$A:$B,2,0),"") -> SEM PROJETO
A26: P0327 | B26: HMPCMOLHE | C26: Pedir a abertura do cadeado da porta de acesso ao molhe | D26: 0 | E26: Permanente | F26: =IF(Tabela18[[#This Row],[Estações]]="HMOFICINA","VMS",IFERROR(VLOOKUP(B26,'Cadastro Estacoes'!$A$2:$Z$201,26,0),"")) -> #ERROR! | G26: Feito | H26: Falar com o Sérgio pra pegar a chave na Suzano Celulose com o operador de painel | K26: POF | L26: RO | M26: 14/10/2019 | N26: O | O26: 14/07/2020 | P26: =IFERROR(VLOOKUP(B26,'Cadastro Estacoes'!$A:$B,2,0),"") -> SISMO®PORTOCEL
A27: P0355 | B27: SEM ESTACAO | C27: Fazer procedimento de como fazer cabo GILL | D27: 2 | E27: 31/10/2019 | F27: =IF(Tabela18[[#This Row],[Estações]]="HMOFICINA","VMS",IFERROR(VLOOKUP(B27,'Cadastro Estacoes'!$A$2:$Z$201,26,0),"")) -> #ERROR! | G27: Feito | H27: Procedimento padrão (Verificar com Diego) | K27: DSS | L27: LFF | M27: 15/10/2019 | N27: O | O27: 29/07/2020 | P27: =IFERROR(VLOOKUP(B27,'Cadastro Estacoes'!$A:$B,2,0),"") -> SEM PROJETO
A28: P0368 | B28: HMBTCPBA | C28: Integrar Gill GMX no CR 300 | D28: 0 | E28: 31/03/2020 | F28: =IF(Tabela18[[#This Row],[Estações]]="HMOFICINA","VMS",IFERROR(VLOOKUP(B28,'Cadastro Estacoes'!$A$2:$Z$201,26,0),"")) -> #ERROR! | G28: Feito | H28: Aguardar chegada do sensor | I28: 1 anemomentro, 1 CR 300 | K28: CCL | L28: FMS | M28: 15/10/2019 | N28: O | O28: 07/08/2020 | P28: =IFERROR(VLOOKUP(B28,'Cadastro Estacoes'!$A:$B,2,0),"") -> SISMO®BTS
A29: P0416 | B29: HMSPTEBAR | C29: Arrancar prensacabo do eletroduto para passar cabo da estação | D29: 0 | E29: 31/01/2020 | F29: =IF(Tabela18[[#This Row],[Estações]]="HMOFICINA","VMS",IFERROR(VLOOKUP(B29,'Cadastro Estacoes'!$A$2:$Z$201,26,0),"")) -> #ERROR! | G29: Feito | H29: Prensacabo esta muito preso la, rosca ja esta se desfazendo | I29: Esmiril | K29: EMD | L29: LSP | M29: 28/10/2019 | N29: C | O29: 07/08/2020 | P29: =IFERROR(VLOOKUP(B29,'Cadastro Estacoes'!$A:$B,2,0),"") -> SISMO®SPPILOTS
A30: P0440 | B30: HMPSEPIER | C30: Lançar derivador na região de medição do SL | D30: 2 | E30: Permanente | F30: =IF(Tabela18[[#This Row],[Estações]]="HMOFICINA","VMS",IFERROR(VLOOKUP(B30,'Cadastro Estacoes'!$A$2:$Z$201,26,0),"")) -> #ERROR! | G30: Feito | H30: Vanessa mandou no grupo local ideal para lancamento | I30: derivador e gps | J30: 1 | K30: EMD | L30: VCP | M30: 02/11/2019 | N30: C | O30: 17/08/2020 | P30: =IFERROR(VLOOKUP(B30,'Cadastro Estacoes'!$A:$B,2,0),"") -> SISMO®PSE
A31: P0471 | B31: HMPCBOIA | C31: Levar cadeado CR50 quando for retirar o DCPS da água | D31: 1 | E31: Permanente | F31: =IF(Tabela18[[#This Row],[Estações]]="HMOFICINA","VMS",IFERROR(VLOOKUP(B31,'Cadastro Estacoes'!$A$2:$Z$201,26,0),"")) -> #ERROR! | G31: Feito | H31: Levar alicate corta cadeado | I31: Alicate corta cadeado | K31: POF | L31: RO | M31: 12/11/2019 | N31: C | O31: 17/08/2020 | P31: =IFERROR(VLOOKUP(B31,'Cadastro Estacoes'!$A:$B,2,0),"") -> SISMO®PORTOCEL
A32: P0510 | B32: SEM ESTACAO | C32: Revisar discos e partilhas da saveiro cabine simples | D32: 0 | E32: 25/11/2019 | F32: =IF(Tabela18[[#This Row],[Estações]]="HMOFICINA","VMS",IFERROR(VLOOKUP(B32,'Cadastro Estacoes'!$A$2:$Z$201,26,0),"")) -> #ERROR! | G32: Feito | H32: avaliar necessidade de trocar | J32: 1 | K32: DSS | L32: ESS | M32: 21/11/2019 | N32: O | O32: 21/08/2020 | P32: =IFERROR(VLOOKUP(B32,'Cadastro Estacoes'!$A:$B,2,0),"") -> SEM PROJETO
A33: P0513 | B33: SEM ESTACAO | C33: Avaliar sensores fabricados no Brasil - Nível (radar) -> Mafetech | D33: 0 | E33: 10/01/2020 | F33: =IF(Tabela18[[#This Row],[Estações]]="HMOFICINA","VMS",IFERROR(VLOOKUP(B33,'Cadastro Estacoes'!$A$2:$Z$201,26,0),"")) -> #ERROR! | G33: Feito | H33: Puxar o tema e passar para Desenvolvimento. Gustavo Henrique <vendas4@mafetech.com.br>; 19/12: enviado email solicitando infos | K33: DSS | L33: ADC | M33: 26/11/2019 | N33: O | O33: 21/08/2020 | P33: =IFERROR(VLOOKUP(B33,'Cadastro Estacoes'!$A:$B,2,0),"") -> SEM PROJETO
A34: P0524 | B34: HMTJUNITAPAJOS | C34: Substituir e fixar melhor cabo SL | D34: 0 | E34: 31/03/2020 | F34: =IF(Tabela18[[#This Row],[Estações]]="HMOFICINA","VMS",IFERROR(VLOOKUP(B34,'Cadastro Estacoes'!$A$2:$Z$201,26,0),"")) -> #ERROR! | G34: Feito | H34: Cabo com mau contato - necessário substituir e fixar melhor | I34: Cabo | K34: CCL | L34: DMP | M34: 29/11/2019 | N34: C | O34: 21/08/2020 | P34: =IFERROR(VLOOKUP(B34,'Cadastro Estacoes'!$A:$B,2,0),"") -> SISMO®TAPAJOS
A35: P0524 | B35: HMTJUNITAPAJOS | C35: Caixa de bateria com prensa-cabo para cima | D35: 0 | E35: 31/03/2020 | F35: =IF(Tabela18[[#This Row],[Estações]]="HMOFICINA","VMS",IFERROR(VLOOKUP(B35,'Cadastro Estacoes'!$A$2:$Z$201,26,0),"")) -> #ERROR! | G35: Feito | H35: Levar cabo de painel para poder virar a caixa | K35: CCL | L35: DMP | M35: 29/11/2019 | N35: C | O35: 44286 | P35: =IFERROR(VLOOKUP(B35,'Cadastro Estacoes'!$A:$B,2,0),"") -> SISMO®TAPAJOS
A36: P0542 | B36: HMSPTEBAR | C36: Verificar modem 548 | D36: 0 | E36: 29/02/2020 | F36: =IF(Tabela18[[#This Row],[Estações]]="HMOFICINA","VMS",IFERROR(VLOOKUP(B36,'Cadastro Estacoes'!$A$2:$Z$201,26,0),"")) -> #ERROR! | G36: Feito | H36: Modem caiu e não voltou mais | I36: Modem e chip | J36: 1 | K36: EMD | L36: ESS | M36: 04/12/2019 | N36: C | O36: 01/09/2020 | P36: =IFERROR(VLOOKUP(B36,'Cadastro Estacoes'!$A:$B,2,0),"") -> SISMO®SPPILOTS
A37: P0547 | B37: SEM ESTACAO | C37: Ativar pacote SonWave no XR 1500 E 5450 | D37: 0 | E37: 31/03/2020 | F37: =IF(Tabela18[[#This Row],[Estações]]="HMOFICINA","VMS",IFERROR(VLOOKUP(B37,'Cadastro Estacoes'!$A$2:$Z$201,26,0),"")) -> #ERROR! | G37: Feito | H37: Seguir instruções do e-mail após retorno do ADCP | K37: DSS | L37: FMS | M37: 04/12/2019 | N37: O | O37: 01/09/2020 | P37: =IFERROR(VLOOKUP(B37,'Cadastro Estacoes'!$A:$B,2,0),"") -> SEM PROJETO
A38: P0566 | B38: SEM ESTACAO | C38: Configurar Rastreadores | D38: 0 | E38: 31/12/2019 | F38: =IF(Tabela18[[#This Row],[Estações]]="HMOFICINA","VMS",IFERROR(VLOOKUP(B38,'Cadastro Estacoes'!$A$2:$Z$201,26,0),"")) -> #ERROR! | G38: Feito | K38: DSS | L38: LSP | M38: 09/12/2019 | N38: O | O38: 01/09/2020 | P38: =IFERROR(VLOOKUP(B38,'Cadastro Estacoes'!$A:$B,2,0),"") -> SEM PROJETO
A39: P0568 | B39: HMCAPIER | C39: Marcar novos RNs e pintá-los | D39: 0 | E39: 01/03/2020 | F39: =IF(Tabela18[[#This Row],[Estações]]="HMOFICINA","VMS",IFERROR(VLOOKUP(B39,'Cadastro Estacoes'!$A$2:$Z$201,26,0),"")) -> #ERROR! | G39: Feito | H39: dos antigos foram localizados somente dois - precisa marcar novos RNs | I39: marcas de RN + chumbador + pinta para pintura | J39: 2 | K39: FPM | L39: MAS | M39: 13/12/2019 | N39: C | O39: 11/09/2020 | P39: =IFERROR(VLOOKUP(B39,'Cadastro Estacoes'!$A:$B,2,0),"") -> SISMO®CATTALINI
A40: P0594 | B40: HMLIPIER | C40: Instalar Régua e Fazer Nivelamento | D40: 0 | E40: 20/02/2020 | F40: =IF(Tabela18[[#This Row],[Estações]]="HMOFICINA","VMS",IFERROR(VLOOKUP(B40,'Cadastro Estacoes'!$A$2:$Z$201,26,0),"")) -> #ERROR! | G40: Feito | H40: Atrelada a pendência P0673, deixar separado no almoxarifado e idenficado. | I40: Régua e demais materias para instalção da Régua; nível, mira | K40: EJC | L40: VCP | M40: 18/12/2019 | N40: C | O40: 24/09/2020 | P40: =IFERROR(VLOOKUP(B40,'Cadastro Estacoes'!$A:$B,2,0),"") -> SISMO®LIBRA/MULTI
A41: P0609 | B41: SEM ESTACAO | C41: Estudar controle de itens -> Instalados, Em campo, Em estoque | D41: 0 | E41: 02/01/2020 | F41: =IF(Tabela18[[#This Row],[Estações]]="HMOFICINA","VMS",IFERROR(VLOOKUP(B41,'Cadastro Estacoes'!$A$2:$Z$201,26,0),"")) -> #ERROR! | G41: Feito | H41: Discutir próxima reunião VCP/RMC | K41: DSS | L41: ADC | M41: 26/12/2019 | N41: O | O41: 06/10/2020 | P41: =IFERROR(VLOOKUP(B41,'Cadastro Estacoes'!$A:$B,2,0),"") -> SEM PROJETO
A42: P0629 | B42: HMLIPIER | C42: Substituição do cabo ADCP ou Fazer Mufla no local | D42: 0 | E42: 30/03/2020 | F42: =IF(Tabela18[[#This Row],[Estações]]="HMOFICINA","VMS",IFERROR(VLOOKUP(B42,'Cadastro Estacoes'!$A$2:$Z$201,26,0),"")) -> #ERROR! | G42: Feito | H42: Cabo ADCP está quase se rompendo na junção com a mufla, foi realizado um remendo paliativo com Fita isolante liquida e Sylver Tape. | K42: EJC | L42: EJC | M42: 26/02/2020 | N42: C | O42: 06/10/2020 | P42: =IFERROR(VLOOKUP(B42,'Cadastro Estacoes'!$A:$B,2,0),"") -> SISMO®LIBRA/MULTI
A43: P0665 | B43: HMTEPIER | C43: Separar 7 réguas de maré para fixar na estrutura (LEVAR EMENDA) | D43: 1 | E43: 31/01/2020 | F43: =IF(Tabela18[[#This Row],[Estações]]="HMOFICINA","VMS",IFERROR(VLOOKUP(B43,'Cadastro Estacoes'!$A$2:$Z$201,26,0),"")) -> #ERROR! | G43: Feito | K43: POF | L43: DSS | M43: 10/01/2020 | N43: O | O43: 06/10/2020 | P43: =IFERROR(VLOOKUP(B43,'Cadastro Estacoes'!$A:$B,2,0),"") -> SISMO®TEBIG
A44: P0666 | B44: HMTEPIER | C44: Separar RNS e chumbadores para nivelamento | D44: 1 | E44: 31/01/2020 | F44: =IF(Tabela18[[#This Row],[Estações]]="HMOFICINA","VMS",IFERROR(VLOOKUP(B44,'Cadastro Estacoes'!$A$2:$Z$201,26,0),"")) -> #ERROR! | G44: Feito | H44: Verificar quantidade com FMS ou LFF. | K44: POF | L44: DSS | M44: 10/01/2020 | N44: O | O44: 06/10/2020 | P44: =IFERROR(VLOOKUP(B44,'Cadastro Estacoes'!$A:$B,2,0),"") -> SISMO®TEBIG
A45: P0671 | B45: HMQIGUARAS | C45: Criar tampa para o furo do alçapão do tubulão | D45: 3 | E45: 14/02/2020 | F45: =IF(Tabela18[[#This Row],[Estações]]="HMOFICINA","VMS",IFERROR(VLOOKUP(B45,'Cadastro Estacoes'!$A$2:$Z$201,26,0),"")) -> #ERROR! | G45: Feito | H45: Medida da tampa 26x26 cm. Deve ser colada com tubolite no local. | K45: FPM | L45: EJC | M45: 17/01/2020 | N45: O | O45: 06/10/2020 | P45: =IFERROR(VLOOKUP(B45,'Cadastro Estacoes'!$A:$B,2,0),"") -> SISMO®QUIRIRI
A46: P0672 | B46: HMTJTORRE1 | C46: Fazer ou comprar abracadeira para prender tubo do young na madeira | D46: 1 | E46: 14/02/2020 | F46: =IF(Tabela18[[#This Row],[Estações]]="HMOFICINA","VMS",IFERROR(VLOOKUP(B46,'Cadastro Estacoes'!$A$2:$Z$201,26,0),"")) -> #ERROR! | G46: Feito | H46: Atrelada a pendência P0029, deixar separado no almoxarifado e idenficado. | K46: CCL | L46: DSS | M46: 13/01/2020 | N46: O | O46: 06/10/2020 | P46: =IFERROR(VLOOKUP(B46,'Cadastro Estacoes'!$A:$B,2,0),"") -> SISMO®TAPAJOS
A47: P0676 | B47: HMQIGUARAS | C47: Fazer reguá de maré | D47: 1 | E47: 14/02/2020 | F47: =IF(Tabela18[[#This Row],[Estações]]="HMOFICINA","VMS",IFERROR(VLOOKUP(B47,'Cadastro Estacoes'!$A$2:$Z$201,26,0),"")) -> #ERROR! | G47: Feito | H47: Atrelada a pendência P0055, deixar separado no almoxarifado e idenficado. | K47: FPM | L47: DSS | M47: 13/01/2020 | N47: O | O47: 06/10/2020 | P47: =IFERROR(VLOOKUP(B47,'Cadastro Estacoes'!$A:$B,2,0),"") -> SISMO®QUIRIRI
A48: P0678 | B48: HMCAPIER | C48: Fazer reguá de maré (pendencia igual a 109) | D48: 1 | E48: 14/02/2020 | F48: =IF(Tabela18[[#This Row],[Estações]]="HMOFICINA","VMS",IFERROR(VLOOKUP(B48,'Cadastro Estacoes'!$A$2:$Z$201,26,0),"")) -> #ERROR! | G48: Feito | H48: Atrelada a pendência P0120, deixar separado no almoxarifado e idenficado. | K48: FPM | L48: DSS | M48: 13/01/2020 | N48: O | O48: 13/10/2020 | P48: =IFERROR(VLOOKUP(B48,'Cadastro Estacoes'!$A:$B,2,0),"") -> SISMO®CATTALINI
A49: P0691 | B49: HMCSNPIER | C49: Trocar abraçadeiras enferrujadas do tubo do maregrafo | D49: 0 | E49: 13/02/2020 | F49: =IF(Tabela18[[#This Row],[Estações]]="HMOFICINA","VMS",IFERROR(VLOOKUP(B49,'Cadastro Estacoes'!$A$2:$Z$201,26,0),"")) -> #ERROR! | G49: Feito | H49: abraçadeiras com bastante ferrugem | I49: abraçadeira | J49: 1 | K49: EMD | L49: ESS | M49: 17/01/2020 | N49: C | O49: 13/10/2020 | P49: =IFERROR(VLOOKUP(B49,'Cadastro Estacoes'!$A:$B,2,0),"") -> SISMO®CSN
A50: P0697 | B50: HMQISOURE | C50: Pintura do guarda corpo da estação | D50: 2 | E50: 20/03/2020 | F50: =IF(Tabela18[[#This Row],[Estações]]="HMOFICINA","VMS",IFERROR(VLOOKUP(B50,'Cadastro Estacoes'!$A$2:$Z$201,26,0),"")) -> #ERROR! | G50: Feito | H50: Lixar e pintar de preto o guarda corpo da estação | I50: Lixa, escova de aço, pincel e tinta preta | K50: FPM | L50: EJC | M50: 17/01/2020 | N50: C | O50: 13/10/2020 | P50: =IFERROR(VLOOKUP(B50,'Cadastro Estacoes'!$A:$B,2,0),"") -> SISMO®QUIRIRI
A51: P0698 | B51: HMQISOURE | C51: Melhorar fixação da antena aranha | D51: 0 | E51: 20/01/2020 | F51: =IF(Tabela18[[#This Row],[Estações]]="HMOFICINA","VMS",IFERROR(VLOOKUP(B51,'Cadastro Estacoes'!$A$2:$Z$201,26,0),"")) -> #ERROR! | G51: Feito | H51: Antena fixada com abraçadeira tipo U e tairape. Verificar por fotos o material a ser utilizado. | K51: FPM | L51: EJC | M51: 17/01/2020 | N51: C | O51: 27/10/2020 | P51: =IFERROR(VLOOKUP(B51,'Cadastro Estacoes'!$A:$B,2,0),"") -> SISMO®QUIRIRI
A52: P0700 | B52: HMQIGUARAS | C52: Reforma da varanda da boia. | D52: 2 | E52: 20/03/2020 | F52: =IF(Tabela18[[#This Row],[Estações]]="HMOFICINA","VMS",IFERROR(VLOOKUP(B52,'Cadastro Estacoes'!$A$2:$Z$201,26,0),"")) -> #ERROR! | G52: Feito | H52: Precisa de um dia inteiro para essa tarefa, sugiro que seja realizada por Abimael | I52: Escova de aço, lixa, pincel e tinta | K52: FPM | L52: EJC | M52: 17/01/2020 | N52: C | O52: 29/10/2020 | P52: =IFERROR(VLOOKUP(B52,'Cadastro Estacoes'!$A:$B,2,0),"") -> SISMO®QUIRIRI
A53: P0701 | B53: HMQIGUARAS | C53: Reformar escada utilizada para acessar a boia | D53: 2 | E53: 20/03/2020 | F53: =IF(Tabela18[[#This Row],[Estações]]="HMOFICINA","VMS",IFERROR(VLOOKUP(B53,'Cadastro Estacoes'!$A$2:$Z$201,26,0),"")) -> #ERROR! | G53: Feito | H53: Sugiro que seja realizada por Abimael | K53: FPM | L53: EJC | M53: 17/01/2020 | N53: C | O53: 29/10/2020 | P53: =IFERROR(VLOOKUP(B53,'Cadastro Estacoes'!$A:$B,2,0),"") -> SISMO®QUIRIRI
A54: P0702 | B54: HMQIGUARAS | C54: Substituir adesivo da caixa ambiental | D54: 2 | E54: 20/04/2020 | F54: =IF(Tabela18[[#This Row],[Estações]]="HMOFICINA","VMS",IFERROR(VLOOKUP(B54,'Cadastro Estacoes'!$A$2:$Z$201,26,0),"")) -> #ERROR! | G54: Feito | H54: O adesivo atual foi reutilizado da caixa antiga | I54: Adesivo | K54: FPM | L54: EJC | M54: 17/01/2020 | N54: C | O54: 29/10/2020 | P54: =IFERROR(VLOOKUP(B54,'Cadastro Estacoes'!$A:$B,2,0),"") -> SISMO®QUIRIRI
A55: P0708 | B55: HMBTCPBA | C55: Definir local instalação torre sensor vento | D55: 0 | E55: 31/03/2020 | F55: =IF(Tabela18[[#This Row],[Estações]]="HMOFICINA","VMS",IFERROR(VLOOKUP(B55,'Cadastro Estacoes'!$A$2:$Z$201,26,0),"")) -> #ERROR! | G55: Feito | K55: CCL | L55: FMS | M55: 20/01/2020 | N55: O | O55: 30/10/2020 | P55: =IFERROR(VLOOKUP(B55,'Cadastro Estacoes'!$A:$B,2,0),"") -> SISMO®BTS
A56: P0744 | B56: HMPPMIRA | C56: Substituir caixa de telemetria de plástico por alguma opção mais segura (pra por o cadeado) | D56: 0 | E56: 22/03/2020 | F56: =IF(Tabela18[[#This Row],[Estações]]="HMOFICINA","VMS",IFERROR(VLOOKUP(B56,'Cadastro Estacoes'!$A$2:$Z$201,26,0),"")) -> #ERROR! | G56: Feito | H56: Necessário desenvolver maneira/caixa para maior proteção ao CR (local existe transito intenso de alunos) | K56: FPM | L56: EJC | M56: 24/01/2020 | N56: O | O56: 30/10/2020 | P56: =IFERROR(VLOOKUP(B56,'Cadastro Estacoes'!$A:$B,2,0),"") -> SISMO®PARANAGUAPILOTS
A57: P0745 | B57: HMPPMIRA | C57: Substituir pacote de sílica | D57: 2 | E57: Permanente | F57: =IF(Tabela18[[#This Row],[Estações]]="HMOFICINA","VMS",IFERROR(VLOOKUP(B57,'Cadastro Estacoes'!$A$2:$Z$201,26,0),"")) -> #ERROR! | G57: Feito | K57: FPM | L57: EJC | M57: 24/01/2020 | N57: C | O57: 30/10/2020 | P57: =IFERROR(VLOOKUP(B57,'Cadastro Estacoes'!$A:$B,2,0),"") -> SISMO®PARANAGUAPILOTS
A58: P0748 | B58: HMQISOURE | C58: Comprar passagem da lancha para agilizar manobra - evitar balsa | D58: 0 | E58: Permanente | F58: =IF(Tabela18[[#This Row],[Estações]]="HMOFICINA","VMS",IFERROR(VLOOKUP(B58,'Cadastro Estacoes'!$A$2:$Z$201,26,0),"")) -> #ERROR! | G58: Feito | H58: A lancha rapida acelera a viagem, dando mais tempo para a manobra | K58: FPM | L58: LFF | M58: 24/01/2020 | N58: C | O58: 30/10/2020 | P58: =IFERROR(VLOOKUP(B58,'Cadastro Estacoes'!$A:$B,2,0),"") -> SISMO®QUIRIRI
A59: P0753 | B59: HMALUMARE | C59: Levar celular com chip TIM | D59: 0 | E59: permanente | F59: =IF(Tabela18[[#This Row],[Estações]]="HMOFICINA","VMS",IFERROR(VLOOKUP(B59,'Cadastro Estacoes'!$A$2:$Z$201,26,0),"")) -> #ERROR! | G59: Feito | H59: Outras operadoras não pegam | I59: Celular + chip tim | J59: 2 | K59: LSP | L59: MAS | M59: 24/01/2020 | N59: C | O59: 18/11/2020 | P59: =IFERROR(VLOOKUP(B59,'Cadastro Estacoes'!$A:$B,2,0),"") -> SISMO®ALUMAR
A60: P0755 | B60: HMALUMARE | C60: Confirmar que estamos liberados e com ART correta antes do campo | D60: 0 | E60: permanente | F60: =IF(Tabela18[[#This Row],[Estações]]="HMOFICINA","VMS",IFERROR(VLOOKUP(B60,'Cadastro Estacoes'!$A$2:$Z$201,26,0),"")) -> #ERROR! | G60: Feito | H60: Confirmar com Saraiva (HM), Heriwelton e Franklin (ALUMAR) | I60: ART + confirmação | J60: 5 | K60: LSP | L60: MAS | M60: 24/01/2020 | N60: O | O60: 19/11/2020 | P60: =IFERROR(VLOOKUP(B60,'Cadastro Estacoes'!$A:$B,2,0),"") -> SISMO®ALUMAR
A61: P0756 | B61: HMALUVENTO | C61: Confirmar que estamos liberados e com ART correta antes do campo | D61: 0 | E61: permanente | F61: =IF(Tabela18[[#This Row],[Estações]]="HMOFICINA","VMS",IFERROR(VLOOKUP(B61,'Cadastro Estacoes'!$A$2:$Z$201,26,0),"")) -> #ERROR! | G61: Feito | H61: Confirmar com Saraiva (HM), Heriwelton e Franklin (ALUMAR) | I61: ART + confirmação | J61: 5 | K61: LSP | L61: MAS | M61: 24/01/2020 | N61: O | O61: 30/11/2020 | P61: =IFERROR(VLOOKUP(B61,'Cadastro Estacoes'!$A:$B,2,0),"") -> SISMO®ALUMAR
A62: P0757 | B62: HMCSNPIER | C62: Levar o giroflex para o acesso com veiculo HM ser liberado. | D62: 0 | E62: permanente | F62: =IF(Tabela18[[#This Row],[Estações]]="HMOFICINA","VMS",IFERROR(VLOOKUP(B62,'Cadastro Estacoes'!$A$2:$Z$201,26,0),"")) -> #ERROR! | G62: Feito | H62: Levar giroflex toda vez que for acessar Pier CSN | I62: Giroflex | K62: EMD | L62: EJC | M62: 27/01/2020 | N62: C | O62: 01/12/2020 | P62: =IFERROR(VLOOKUP(B62,'Cadastro Estacoes'!$A:$B,2,0),"") -> SISMO®CSN
A63: P0772 | B63: HMRGPRATICAGEM | C63: Trocar conector do XR | D63: 2 | E63: 29/05/2020 | F63: =IF(Tabela18[[#This Row],[Estações]]="HMOFICINA","VMS",IFERROR(VLOOKUP(B63,'Cadastro Estacoes'!$A$2:$Z$201,26,0),"")) -> #ERROR! | G63: Feito | K63: CCL | M63: 43857 | N63: O | O63: 10/12/2020 | P63: =IFERROR(VLOOKUP(B63,'Cadastro Estacoes'!$A:$B,2,0),"") -> SISMO®RGPILOTS
A64: P0774 | B64: HMQIABADE | C64: Trocar bateria da estação e realizar inspeção no sistema | D64: 0 | E64: 03/04/2020 | F64: =IF(Tabela18[[#This Row],[Estações]]="HMOFICINA","VMS",IFERROR(VLOOKUP(B64,'Cadastro Estacoes'!$A$2:$Z$201,26,0),"")) -> #ERROR! | G64: Feito | K64: FPM | L64: FMS | M64: 30/01/2020 | N64: C | O64: 11/12/2020 | P64: =IFERROR(VLOOKUP(B64,'Cadastro Estacoes'!$A:$B,2,0),"") -> SISMO®QUIRIRI
A65: P0782 | B65: HMQIABADE | C65: Inspecionar (e trocar se necessário) marégrafo boia e contrapeso | D65: 1 | E65: 03/04/2020 | F65: =IF(Tabela18[[#This Row],[Estações]]="HMOFICINA","VMS",IFERROR(VLOOKUP(B65,'Cadastro Estacoes'!$A$2:$Z$201,26,0),"")) -> #ERROR! | G65: Feito | H65: Dados ficaram constantes dia 30/01 | I65: sistema completo do marégrafo boia e contrapeso | K65: FPM | L65: FMS | M65: 30/01/2020 | N65: C | O65: 14/12/2020 | P65: =IFERROR(VLOOKUP(B65,'Cadastro Estacoes'!$A:$B,2,0),"") -> SISMO®QUIRIRI
A66: P0789 | B66: HMTJMONTANHA | C66: Avaliar necessidade de trocar SL | D66: 0 | E66: 31/03/2020 | F66: =IF(Tabela18[[#This Row],[Estações]]="HMOFICINA","VMS",IFERROR(VLOOKUP(B66,'Cadastro Estacoes'!$A$2:$Z$201,26,0),"")) -> #ERROR! | G66: Feito | H66: enviando Lixo | I66: SL | K66: CCL | L66: LSP | M66: 04/02/2020 | N66: O | O66: 14/12/2020 | P66: =IFERROR(VLOOKUP(B66,'Cadastro Estacoes'!$A:$B,2,0),"") -> SISMO®TAPAJOS
A67: P0790 | B67: HMTJMONTANHA | C67: Colar modens na caixa com velcro | D67: 0 | E67: 31/03/2020 | F67: =IF(Tabela18[[#This Row],[Estações]]="HMOFICINA","VMS",IFERROR(VLOOKUP(B67,'Cadastro Estacoes'!$A$2:$Z$201,26,0),"")) -> #ERROR! | G67: Feito | H67: Modens sem velcro | I67: Velcro | K67: CCL | L67: LSP | M67: 04/02/2020 | N67: C | O67: 14/12/2020 | P67: =IFERROR(VLOOKUP(B67,'Cadastro Estacoes'!$A:$B,2,0),"") -> SISMO®TAPAJOS
A68: P0791 | B68: HMTJMONTANHA | C68: Envio da documentação/ pedido de liberação da equipe | D68: 0 | E68: Permanente | F68: =IF(Tabela18[[#This Row],[Estações]]="HMOFICINA","VMS",IFERROR(VLOOKUP(B68,'Cadastro Estacoes'!$A$2:$Z$201,26,0),"")) -> #ERROR! | G68: Feito | I68: Documentação equipe | K68: CCL | L68: LSP | M68: 04/02/2020 | N68: O | O68: 14/12/2020 | P68: =IFERROR(VLOOKUP(B68,'Cadastro Estacoes'!$A:$B,2,0),"") -> SISMO®TAPAJOS
A69: P0792 | B69: HMTJTORRE1 | C69: avaliar necessidade da troca das antenas (PQ) | D69: 2 | E69: 31/03/2020 | F69: =IF(Tabela18[[#This Row],[Estações]]="HMOFICINA","VMS",IFERROR(VLOOKUP(B69,'Cadastro Estacoes'!$A$2:$Z$201,26,0),"")) -> #ERROR! | G69: Feito | H69: As atuais estavam submersas em mistura insalubre | I69: 2 antenas | K69: CCL | L69: LSP | M69: 04/02/2020 | N69: C | O69: 08/12/2020 | P69: =IFERROR(VLOOKUP(B69,'Cadastro Estacoes'!$A:$B,2,0),"") -> SISMO®TAPAJOS
A70: P0793 | B70: HMTJTORRE1 | C70: Avaliar com terminal possibilidade de higienização no local da estação | D70: 2 | E70: 31/03/2020 | F70: =IF(Tabela18[[#This Row],[Estações]]="HMOFICINA","VMS",IFERROR(VLOOKUP(B70,'Cadastro Estacoes'!$A$2:$Z$201,26,0),"")) -> #ERROR! | G70: Feito | H70: abaixo da caixa da estação, existe mistura de resto de soja e escretas de urubu (3 cm de mistura insalubre) | K70: CCL | L70: LSP | M70: 04/02/2020 | N70: O | O70: 16/12/2020 | P70: =IFERROR(VLOOKUP(B70,'Cadastro Estacoes'!$A:$B,2,0),"") -> SISMO®TAPAJOS
A71: P0794 | B71: HMTJTORRE1 | C71: Limpeza na caixa de telemetria | D71: 0 | E71: 31/03/2020 | F71: =IF(Tabela18[[#This Row],[Estações]]="HMOFICINA","VMS",IFERROR(VLOOKUP(B71,'Cadastro Estacoes'!$A$2:$Z$201,26,0),"")) -> #ERROR! | G71: Feito | H71: Presença de teia de aranha | K71: CCL | L71: LSP | M71: 04/02/2020 | N71: C | O71: 16/12/2020 | P71: =IFERROR(VLOOKUP(B71,'Cadastro Estacoes'!$A:$B,2,0),"") -> SISMO®TAPAJOS
A72: P0795 | B72: HMTJTORRE1 | C72: comprar abraçadeira do tamanho certo para prender tubo do young | D72: 0 | E72: 31/03/2020 | F72: =IF(Tabela18[[#This Row],[Estações]]="HMOFICINA","VMS",IFERROR(VLOOKUP(B72,'Cadastro Estacoes'!$A$2:$Z$201,26,0),"")) -> #ERROR! | G72: Feito | H72: pendencias anteriores nao davam tamanho da abraçadeira | I72: Abraçadeira metal | K72: CCL | L72: LSP | M72: 04/02/2020 | N72: O | O72: 16/12/2020 | P72: =IFERROR(VLOOKUP(B72,'Cadastro Estacoes'!$A:$B,2,0),"") -> SISMO®TAPAJOS
A73: P0796 | B73: HMTJUNITAPAJOS | C73: Levar cabo de painel solar para possibilitar a virada da caixa de bateria | D73: 0 | E73: 31/03/2020 | F73: =IF(Tabela18[[#This Row],[Estações]]="HMOFICINA","VMS",IFERROR(VLOOKUP(B73,'Cadastro Estacoes'!$A$2:$Z$201,26,0),"")) -> #ERROR! | G73: Feito | I73: Cabo Painel 2m | K73: CCL | L73: LSP | M73: 04/02/2020 | N73: C | O73: 16/12/2020 | P73: =IFERROR(VLOOKUP(B73,'Cadastro Estacoes'!$A:$B,2,0),"") -> SISMO®TAPAJOS
A74: P0797 | B74: HMTJUNITAPAJOS | C74: avaliar possibilidade de realizar integração anual | D74: 0 | E74: 31/03/2020 | F74: =IF(Tabela18[[#This Row],[Estações]]="HMOFICINA","VMS",IFERROR(VLOOKUP(B74,'Cadastro Estacoes'!$A$2:$Z$201,26,0),"")) -> #ERROR! | G74: Feito | H74: Duração de 3 dias | I74: Documentação equipe | K74: CCL | L74: LSP | M74: 04/02/2020 | N74: O | O74: 16/12/2020 | P74: =IFERROR(VLOOKUP(B74,'Cadastro Estacoes'!$A:$B,2,0),"") -> SISMO®TAPAJOS
A75: P0804 | B75: HMPCBOIA | C75: Verificar se há acumulo de água dentro do mangrulho | D75: 0 | E75: 31/07/2020 | F75: =IF(Tabela18[[#This Row],[Estações]]="HMOFICINA","VMS",IFERROR(VLOOKUP(B75,'Cadastro Estacoes'!$A$2:$Z$201,26,0),"")) -> #ERROR! | G75: Feito | H75: Levar passa fio para desentupir | I75: Passa fio | K75: POF | L75: RO | M75: 07/02/2020 | N75: C | O75: 16/12/2020 | P75: =IFERROR(VLOOKUP(B75,'Cadastro Estacoes'!$A:$B,2,0),"") -> SISMO®PORTOCEL
A76: P0806 | B76: HMPCPIER | C76: Instalar 2 trava eixos nas dobradiças da caixa ambiental | D76: 0 | E76: 30/04/2020 | F76: =IF(Tabela18[[#This Row],[Estações]]="HMOFICINA","VMS",IFERROR(VLOOKUP(B76,'Cadastro Estacoes'!$A$2:$Z$201,26,0),"")) -> #ERROR! | G76: Feito | H76: Trava eixos de 6mm | I76: 2 peças de 6mm | K76: POF | L76: RO | M76: 07/02/2020 | N76: C | O76: 44186 | P76: =IFERROR(VLOOKUP(B76,'Cadastro Estacoes'!$A:$B,2,0),"") -> SISMO®PORTOCEL
A77: P0816 | B77: HMPCBOIA | C77: Levar chave de boca 9 e 10 | D77: 0 | E77: Permanente | F77: =IF(Tabela18[[#This Row],[Estações]]="HMOFICINA","VMS",IFERROR(VLOOKUP(B77,'Cadastro Estacoes'!$A$2:$Z$201,26,0),"")) -> #ERROR! | G77: Feito | H77: Pegar no almoxarifado. | I77: Chave de boca 9 e 10 | K77: POF | L77: DSS | M77: 10/02/2020 | N77: C | O77: 28/12/2020 | P77: =IFERROR(VLOOKUP(B77,'Cadastro Estacoes'!$A:$B,2,0),"") -> SISMO®PORTOCEL
A78: P0817 | B78: HMPCBOIA | C78: Levar controle do roteador | D78: 0 | E78: Permanente | F78: =IF(Tabela18[[#This Row],[Estações]]="HMOFICINA","VMS",IFERROR(VLOOKUP(B78,'Cadastro Estacoes'!$A$2:$Z$201,26,0),"")) -> #ERROR! | G78: Feito | H78: Pegar no almoxarifado. | I78: Controle do rotedor | K78: POF | L78: DSS | M78: 10/02/2020 | N78: C | O78: 44193 | P78: =IFERROR(VLOOKUP(B78,'Cadastro Estacoes'!$A:$B,2,0),"") -> SISMO®PORTOCEL
A79: P0820 | B79: HMQISOURE | C79: Averiguar remotamente estado marégrafo radar | D79: 0 | E79: 11/02/2020 | F79: =IF(Tabela18[[#This Row],[Estações]]="HMOFICINA","VMS",IFERROR(VLOOKUP(B79,'Cadastro Estacoes'!$A$2:$Z$201,26,0),"")) -> #ERROR! | G79: Feito | H79: Dados inconsistentes, pode ter inclinado novamente. Solicitar ao francisco contato local | K79: FPM | L79: FMS | M79: 10/02/2020 | N79: O | O79: 29/12/2020 | P79: =IFERROR(VLOOKUP(B79,'Cadastro Estacoes'!$A:$B,2,0),"") -> SISMO®QUIRIRI
A80: P0822 | B80: HMTJMONTANHA | C80: Trocar HM801 ou seu chip. sinal intermitente | D80: 0 | E80: 29/05/2020 | F80: =IF(Tabela18[[#This Row],[Estações]]="HMOFICINA","VMS",IFERROR(VLOOKUP(B80,'Cadastro Estacoes'!$A$2:$Z$201,26,0),"")) -> #ERROR! | G80: Feito | H80: Trocar HM801 ou seu chip. sinal intermitente | I80: 1 modem e chips reservas | K80: CCL | L80: FMS | M80: 10/02/2020 | N80: C | O80: 44210 | P80: =IFERROR(VLOOKUP(B80,'Cadastro Estacoes'!$A:$B,2,0),"") -> SISMO®TAPAJOS
A81: P0824 | B81: HMTEPIER | C81: Trocar tubo do marégrafo urgente | D81: 0 | E81: 16/04/2020 | F81: =IF(Tabela18[[#This Row],[Estações]]="HMOFICINA","VMS",IFERROR(VLOOKUP(B81,'Cadastro Estacoes'!$A$2:$Z$201,26,0),"")) -> #ERROR! | G81: Feito | H81: Tubo do maregrafo totalmente com corrosão | I81: tubo de 1polegada | J81: 1 | K81: POF | L81: ESS | M81: 12/02/2020 | N81: C | O81: 44210 | P81: =IFERROR(VLOOKUP(B81,'Cadastro Estacoes'!$A:$B,2,0),"") -> SISMO®TEBIG
A82: P0825 | B82: HMTEPIER | C82: Comprar tubo do maregrafo para subisituição | D82: 0 | E82: 16/04/2020 | F82: =IF(Tabela18[[#This Row],[Estações]]="HMOFICINA","VMS",IFERROR(VLOOKUP(B82,'Cadastro Estacoes'!$A$2:$Z$201,26,0),"")) -> #ERROR! | G82: Feito | H82: Tubo de 1 ou 2 polegada, confirmar com o Fernando | J82: 1 | K82: POF | L82: ESS | M82: 12/02/2020 | N82: O | O82: 15/01/2021 | P82: =IFERROR(VLOOKUP(B82,'Cadastro Estacoes'!$A:$B,2,0),"") -> SISMO®TEBIG
A83: P0826 | B83: HMTEPIER | C83: Retirar poste e base | D83: 0 | E83: 16/04/2020 | F83: =IF(Tabela18[[#This Row],[Estações]]="HMOFICINA","VMS",IFERROR(VLOOKUP(B83,'Cadastro Estacoes'!$A$2:$Z$201,26,0),"")) -> #ERROR! | G83: Feito | H83: retirada devido a corosão | I83: esmilhadeira | J83: 1 | K83: POF | L83: ESS | M83: 12/02/2020 | N83: C | O83: 15/01/2021 | P83: =IFERROR(VLOOKUP(B83,'Cadastro Estacoes'!$A:$B,2,0),"") -> SISMO®TEBIG
A84: P0827 | B84: HMTEPIER | C84: Fazer suporte caixa ALPHA para fixação na torre da VEC | D84: 0 | E84: 16/04/2020 | F84: =IF(Tabela18[[#This Row],[Estações]]="HMOFICINA","VMS",IFERROR(VLOOKUP(B84,'Cadastro Estacoes'!$A$2:$Z$201,26,0),"")) -> #ERROR! | G84: Feito | H84: Caixa será realocado na torre do young | I84: suporte de caixa | J84: 1 | K84: POF | L84: ESS | M84: 12/02/2020 | N84: O | O84: 27/01/2021 | P84: =IFERROR(VLOOKUP(B84,'Cadastro Estacoes'!$A:$B,2,0),"") -> SISMO®TEBIG
A85: P0828 | B85: HMTEPIER | C85: Fazer suporte para painel solar de 30W | D85: 0 | E85: 16/04/2020 | F85: =IF(Tabela18[[#This Row],[Estações]]="HMOFICINA","VMS",IFERROR(VLOOKUP(B85,'Cadastro Estacoes'!$A$2:$Z$201,26,0),"")) -> #ERROR! | G85: Feito | H85: Fazer suporte para fixação na torre do young | I85: suporte de painel | J85: 1 | K85: POF | L85: ESS | M85: 12/02/2020 | N85: O | O85: 04/02/2021 | P85: =IFERROR(VLOOKUP(B85,'Cadastro Estacoes'!$A:$B,2,0),"") -> SISMO®TEBIG
A86: P0829 | B86: HMTEBOIA18WIND | C86: Melhorar subida na boia | D86: 0 | E86: 16/04/2020 | F86: =IF(Tabela18[[#This Row],[Estações]]="HMOFICINA","VMS",IFERROR(VLOOKUP(B86,'Cadastro Estacoes'!$A$2:$Z$201,26,0),"")) -> #ERROR! | G86: Feito | H86: pensar em fazer uma escada, atualmente só conseguimos subir na maré cheia | I86: escada | J86: 1 | K86: POF | L86: ESS | M86: 12/02/2020 | N86: C | O86: 04/02/2021 | P86: =IFERROR(VLOOKUP(B86,'Cadastro Estacoes'!$A:$B,2,0),"") -> SISMO®TEBIG
A87: P0835 | B87: HMSPALEMOA | C87: Levar adesivo e colar na caixa da estação | D87: 2 | E87: 17/03/2020 | F87: =IF(Tabela18[[#This Row],[Estações]]="HMOFICINA","VMS",IFERROR(VLOOKUP(B87,'Cadastro Estacoes'!$A$2:$Z$201,26,0),"")) -> #ERROR! | G87: Feito | H87: Verificar se está pronto (atrelada a pendência P0834) | I87: adeviso HMSPALEMOA | J87: 2 | K87: EMD | L87: MAS | M87: 13/02/2020 | N87: C | O87: 15/02/2021 | P87: =IFERROR(VLOOKUP(B87,'Cadastro Estacoes'!$A:$B,2,0),"") -> SISMO®ALEMOA
A88: P0836 | B88: HMLIPIER | C88: Substituir parafusos de fixação do SL.(Parafuso compridos de latão) | D88: 0 | E88: 30/03/2020 | F88: =IF(Tabela18[[#This Row],[Estações]]="HMOFICINA","VMS",IFERROR(VLOOKUP(B88,'Cadastro Estacoes'!$A$2:$Z$201,26,0),"")) -> #ERROR! | G88: Feito | H88: Parafusos corroídos. | I88: Parafusos de latão | K88: EJC | L88: EJC | M88: 13/02/2020 | N88: C | O88: 03/03/2021 | P88: =IFERROR(VLOOKUP(B88,'Cadastro Estacoes'!$A:$B,2,0),"") -> SISMO®LIBRA/MULTI
A89: P0837 | B89: HMLIPIER | C89: Analisar melhor forma de instalar régua maregráfica | D89: 1 | E89: 30/04/2020 | F89: =IF(Tabela18[[#This Row],[Estações]]="HMOFICINA","VMS",IFERROR(VLOOKUP(B89,'Cadastro Estacoes'!$A$2:$Z$201,26,0),"")) -> #ERROR! | G89: Feito | H89: Realisar analise em campo, fazer registros fotográficos e tirar medidas. | K89: EJC | L89: EJC | M89: 13/02/2020 | N89: C | O89: 03/03/2021 | P89: =IFERROR(VLOOKUP(B89,'Cadastro Estacoes'!$A:$B,2,0),"") -> SISMO®LIBRA/MULTI
A90: P0844 | B90: HMCOSAOVICENTE | C90: Limpeza da regua de mare | D90: 2 | E90: 30/03/2020 | F90: =IF(Tabela18[[#This Row],[Estações]]="HMOFICINA","VMS",IFERROR(VLOOKUP(B90,'Cadastro Estacoes'!$A$2:$Z$201,26,0),"")) -> #ERROR! | G90: Feito | H90: Regua com incrustação,a mesma pode ser danificada na hora da raspagem | I90: vasoura e raspa | J90: 1 | K90: ESS | L90: HAB | M90: 18/02/2020 | N90: C | O90: 03/03/2021 | P90: =IFERROR(VLOOKUP(B90,'Cadastro Estacoes'!$A:$B,2,0),"") -> SISMO®CONSORCIO
A91: P0845 | B91: HMCOSAOVICENTE | C91: Trocar Silica | D91: 2 | E91: 30/03/2020 | F91: =IF(Tabela18[[#This Row],[Estações]]="HMOFICINA","VMS",IFERROR(VLOOKUP(B91,'Cadastro Estacoes'!$A$2:$Z$201,26,0),"")) -> #ERROR! | G91: Feito | H91: Trocar silica na proxima manutenção | I91: silica | J91: 1 | K91: ESS | L91: ESS | M91: 18/02/2020 | N91: C | O91: 09/03/2021 | P91: =IFERROR(VLOOKUP(B91,'Cadastro Estacoes'!$A:$B,2,0),"") -> SISMO®CONSORCIO
A92: P0851 | B92: HMCOBERTIOGA | C92: Colocar colante na caixa ambienta | D92: 2 | E92: 30/03/2020 | F92: =IF(Tabela18[[#This Row],[Estações]]="HMOFICINA","VMS",IFERROR(VLOOKUP(B92,'Cadastro Estacoes'!$A$2:$Z$201,26,0),"")) -> #ERROR! | G92: Feito | H92: Colante ja foi solicitado a Paola | K92: ESS | L92: HAB | M92: 20/02/2020 | N92: C | O92: 11/03/2021 | P92: =IFERROR(VLOOKUP(B92,'Cadastro Estacoes'!$A:$B,2,0),"") -> SISMO®CONSORCIO
A93: P0863 | B93: HMLIB02 | C93: Sanar problema de fundeio | D93: 0 | E93: 30/04/2020 | F93: =IF(Tabela18[[#This Row],[Estações]]="HMOFICINA","VMS",IFERROR(VLOOKUP(B93,'Cadastro Estacoes'!$A$2:$Z$201,26,0),"")) -> #ERROR! | G93: Feito | H93: Mergulhador Rafael Viana irá enviar plano de melhoria do fundeio | K93: EJC | L93: ESS | M93: 26/02/2020 | N93: C | O93: 44266 | P93: =IFERROR(VLOOKUP(B93,'Cadastro Estacoes'!$A:$B,2,0),"") -> SISMO®LIBRA/MULTI
A94: P0865 | B94: HMLIPIER | C94: Verificar se há necessidade de retirada do equipamento por conta da reforma das estacas | D94: 0 | E94: 28/02/2020 | F94: =IF(Tabela18[[#This Row],[Estações]]="HMOFICINA","VMS",IFERROR(VLOOKUP(B94,'Cadastro Estacoes'!$A$2:$Z$201,26,0),"")) -> #ERROR! | G94: Feito | H94: Havera engorda nas estacas, necessario contato com o terminal | K94: EJC | L94: EJC | M94: 26/02/2020 | N94: O | O94: 44274 | P94: =IFERROR(VLOOKUP(B94,'Cadastro Estacoes'!$A:$B,2,0),"") -> SISMO®LIBRA/MULTI
A95: P0868 | B95: HMCOSANWIND | C95: Anemometro (wind) não realiza medição quando se aperoxima de Zero. Encontra-se fora do ar. | D95: 0 | E95: 10/03/2020 | F95: =IF(Tabela18[[#This Row],[Estações]]="HMOFICINA","VMS",IFERROR(VLOOKUP(B95,'Cadastro Estacoes'!$A$2:$Z$201,26,0),"")) -> #ERROR! | G95: Feito | H95: Entrar em contato com terminal e ver a possibilidade de realizar inspeção no equipamento. | K95: EJC | L95: EJC | M95: 28/02/2020 | N95: O | O95: 44279 | P95: =IFERROR(VLOOKUP(B95,'Cadastro Estacoes'!$A:$B,2,0),"") -> SISMO®COSAN
A96: P0869 | B96: HMQIABADE | C96: Maregrafo radar fora de funcionamento | D96: 0 | E96: 10/03/2020 | F96: =IF(Tabela18[[#This Row],[Estações]]="HMOFICINA","VMS",IFERROR(VLOOKUP(B96,'Cadastro Estacoes'!$A$2:$Z$201,26,0),"")) -> #ERROR! | G96: Feito | H96: Solicitar ao Abmael realizar vistoria no marégrafo | K96: FPM | L96: EJC | M96: 28/02/2020 | N96: O | O96: 44281 | P96: =IFERROR(VLOOKUP(B96,'Cadastro Estacoes'!$A:$B,2,0),"") -> SISMO®QUIRIRI
A97: P0870 | B97: HMBTBOIA | C97: Cuidar, ao abrir o mangrulho, para a patola não soltar. | D97: 0 | E97: Permanente | F97: =IF(Tabela18[[#This Row],[Estações]]="HMOFICINA","VMS",IFERROR(VLOOKUP(B97,'Cadastro Estacoes'!$A$2:$Z$201,26,0),"")) -> #ERROR! | G97: Feito | H97: Cuidar com o 'jogo' que a peça tem | I97: calço de borracha | J97: 2 | K97: CCL | L97: MAS | M97: 01/03/2020 | N97: C | O97: 44285 | P97: =IFERROR(VLOOKUP(B97,'Cadastro Estacoes'!$A:$B,2,0),"") -> SISMO®BTS
A98: P0873 | B98: HMBTBOIA | C98: Levar mini boia/flutuante para prender a chave da estação | D98: 0 | E98: Permanente | F98: =IF(Tabela18[[#This Row],[Estações]]="HMOFICINA","VMS",IFERROR(VLOOKUP(B98,'Cadastro Estacoes'!$A$2:$Z$201,26,0),"")) -> #ERROR! | G98: Feito | H98: Improvisar material flutuante | I98: Material flutuante | J98: 3 | K98: CCL | L98: MAS | M98: 01/03/2020 | N98: C | O98: 44300 | P98: =IFERROR(VLOOKUP(B98,'Cadastro Estacoes'!$A:$B,2,0),"") -> SISMO®BTS
A99: P0886 | B99: HMCAWIND | C99: Levar e colar adeviso na caixa anti-explosão | D99: 2 | E99: 01/04/2020 | F99: =IF(Tabela18[[#This Row],[Estações]]="HMOFICINA","VMS",IFERROR(VLOOKUP(B99,'Cadastro Estacoes'!$A$2:$Z$201,26,0),"")) -> #ERROR! | G99: Feito | H99: Caixa anti-explosão | I99: adeviso + | J99: 3 | K99: FPM | L99: MAS | M99: 10/03/2020 | N99: C | O99: 44302 | P99: =IFERROR(VLOOKUP(B99,'Cadastro Estacoes'!$A:$B,2,0),"") -> SISMO®CATTALINI
A100: P0887 | B100: HMCAWIND | C100: Mandar pra fazer o adeviso no tamanho XX cm por XX cm | D100: 2 | E100: 01/04/2020 | F100: =IF(Tabela18[[#This Row],[Estações]]="HMOFICINA","VMS",IFERROR(VLOOKUP(B100,'Cadastro Estacoes'!$A$2:$Z$201,26,0),"")) -> #ERROR! | G100: Feito | H100: Conferir tamanho da caixa anti-explosão E se vamos fazer mesmo (estação de difícil acesso) | J100: 3 | K100: FPM | L100: MAS | M100: 10/03/2020 | N100: O | O100: 44309 | P100: =IFERROR(VLOOKUP(B100,'Cadastro Estacoes'!$A:$B,2,0),"") -> SISMO®CATTALINI
A101: P0896 | B101: HMQIGUARAS | C101: Sanar deficiencia de transmissão, operadora claro interrompendo transmissão constantemente. | D101: 0 | E101: 12/04/2020 | F101: =IF(Tabela18[[#This Row],[Estações]]="HMOFICINA","VMS",IFERROR(VLOOKUP(B101,'Cadastro Estacoes'!$A$2:$Z$201,26,0),"")) -> #ERROR! | G101: Feito | H101: Conectar no modem 506 (Claro) antena comum e conectar no 502 (Vivo) antena aranha. | K101: FPM | L101: ESS | M101: 12/03/2020 | N101: C | O101: 44313 | P101: =IFERROR(VLOOKUP(B101,'Cadastro Estacoes'!$A:$B,2,0),"") -> SISMO®QUIRIRI
...

Sheet FichaCampoV2-POF
A1: Ficha de Campo (V2) | E1: Estação: | F1: HMPDMCTDPIER1 | I1: =VLOOKUP(F1,'Cadastro Estacoes'!A1:AB152,9,0) -> OPERACIONAL | J1: =VLOOKUP(F1,'Cadastro Estacoes'!A1:AB152,10,0) -> Oceanografia Pier | W1: {=IFERROR(INDEX(Pendencias!$A$2:$O$4333,SMALL(IF(Pendencias!$B$2:$B$4333=$F$1,ROW(Pendencias!$B$2:$B$4333)-1),ROW(A1)),1),"")} | X1: {=IFERROR(INDEX(Pendencias!$A$2:$O$4333,SMALL(IF(Pendencias!$B$2:$B$4333=$F$1,ROW(Pendencias!$B$2:$B$4333)-1),ROW(A1)),3),"")} | Y1: {=IFERROR(INDEX(Pendencias!$A$2:$O$4333,SMALL(IF(Pendencias!$B$2:$B$4333=$F$1,ROW(Pendencias!$B$2:$B$4333)-1),ROW(A1)),4),"")} | Z1: {=IFERROR(INDEX(Pendencias!$A$2:$O$4333,SMALL(IF(Pendencias!$B$2:$B$4333=$F$1,ROW(Pendencias!$B$2:$B$4333)-1),ROW(A1)),7),"")} | AA1: {=IF(IFERROR(INDEX(Pendencias!$A$2:$O$4333,SMALL(IF(Pendencias!$B$2:$B$4333=$F$1,ROW(Pendencias!$B$2:$B$4333)-1),ROW(A1)),9),"")=0,"",IFERROR(INDEX(Pendencias!$A$2:$O$4333,SMALL(IF(Pendencias!$B$2:$B$4333=$F$1,ROW(Pendencias!$B$2:$B$4333)-1),ROW(A1)),9),""))}
A2: Cód Viagem | D2: Equipe HM: | H2: Data: | W2: {=IFERROR(INDEX(Pendencias!$A$2:$O$4333,SMALL(IF(Pendencias!$B$2:$B$4333=$F$1,ROW(Pendencias!$B$2:$B$4333)-1),ROW(A2)),1),"")} | X2: {=IFERROR(INDEX(Pendencias!$A$2:$O$4333,SMALL(IF(Pendencias!$B$2:$B$4333=$F$1,ROW(Pendencias!$B$2:$B$4333)-1),ROW(A2)),3),"")} | Y2: {=IFERROR(INDEX(Pendencias!$A$2:$O$4333,SMALL(IF(Pendencias!$B$2:$B$4333=$F$1,ROW(Pendencias!$B$2:$B$4333)-1),ROW(A2)),4),"")} | Z2: {=IFERROR(INDEX(Pendencias!$A$2:$O$4333,SMALL(IF(Pendencias!$B$2:$B$4333=$F$1,ROW(Pendencias!$B$2:$B$4333)-1),ROW(A2)),7),"")} | AA2: {=IF(IFERROR(INDEX(Pendencias!$A$2:$O$4333,SMALL(IF(Pendencias!$B$2:$B$4333=$F$1,ROW(Pendencias!$B$2:$B$4333)-1),ROW(A2)),9),"")=0,"",IFERROR(INDEX(Pendencias!$A$2:$O$4333,SMALL(IF(Pendencias!$B$2:$B$4333=$F$1,ROW(Pendencias!$B$2:$B$4333)-1),ROW(A2)),9),""))}
W3: {=IFERROR(INDEX(Pendencias!$A$2:$O$4333,SMALL(IF(Pendencias!$B$2:$B$4333=$F$1,ROW(Pendencias!$B$2:$B$4333)-1),ROW(A3)),1),"")} | X3: {=IFERROR(INDEX(Pendencias!$A$2:$O$4333,SMALL(IF(Pendencias!$B$2:$B$4333=$F$1,ROW(Pendencias!$B$2:$B$4333)-1),ROW(A3)),3),"")} | Y3: {=IFERROR(INDEX(Pendencias!$A$2:$O$4333,SMALL(IF(Pendencias!$B$2:$B$4333=$F$1,ROW(Pendencias!$B$2:$B$4333)-1),ROW(A3)),4),"")} | Z3: {=IFERROR(INDEX(Pendencias!$A$2:$O$4333,SMALL(IF(Pendencias!$B$2:$B$4333=$F$1,ROW(Pendencias!$B$2:$B$4333)-1),ROW(A3)),7),"")} | AA3: {=IF(IFERROR(INDEX(Pendencias!$A$2:$O$4333,SMALL(IF(Pendencias!$B$2:$B$4333=$F$1,ROW(Pendencias!$B$2:$B$4333)-1),ROW(A3)),9),"")=0,"",IFERROR(INDEX(Pendencias!$A$2:$O$4333,SMALL(IF(Pendencias!$B$2:$B$4333=$F$1,ROW(Pendencias!$B$2:$B$4333)-1),ROW(A3)),9),""))}
A4: ID | B4: Pendências Previstas | J4: Prioridade | W4: {=IFERROR(INDEX(Pendencias!$A$2:$O$4333,SMALL(IF(Pendencias!$B$2:$B$4333=$F$1,ROW(Pendencias!$B$2:$B$4333)-1),ROW(A4)),1),"")} | X4: {=IFERROR(INDEX(Pendencias!$A$2:$O$4333,SMALL(IF(Pendencias!$B$2:$B$4333=$F$1,ROW(Pendencias!$B$2:$B$4333)-1),ROW(A4)),3),"")} | Y4: {=IFERROR(INDEX(Pendencias!$A$2:$O$4333,SMALL(IF(Pendencias!$B$2:$B$4333=$F$1,ROW(Pendencias!$B$2:$B$4333)-1),ROW(A4)),4),"")} | Z4: {=IFERROR(INDEX(Pendencias!$A$2:$O$4333,SMALL(IF(Pendencias!$B$2:$B$4333=$F$1,ROW(Pendencias!$B$2:$B$4333)-1),ROW(A4)),7),"")} | AA4: {=IF(IFERROR(INDEX(Pendencias!$A$2:$O$4333,SMALL(IF(Pendencias!$B$2:$B$4333=$F$1,ROW(Pendencias!$B$2:$B$4333)-1),ROW(A4)),9),"")=0,"",IFERROR(INDEX(Pendencias!$A$2:$O$4333,SMALL(IF(Pendencias!$B$2:$B$4333=$F$1,ROW(Pendencias!$B$2:$B$4333)-1),ROW(A4)),9),""))}
A5: {=IFERROR(INDEX($W$1:$Z$101,SMALL(IF($Z$1:$Z$101="A fazer",ROW($Z$1:$Z$101)),ROW(A1)),1),"")} | B5: {=IFERROR(INDEX($W$1:$Z$101,SMALL(IF($Z$1:$Z$101="A fazer",ROW($Z$1:$Z$101)),ROW(A1)),2),"")} | J5: {=IFERROR(INDEX($W$1:$Z$101,SMALL(IF($Z$1:$Z$101="A fazer",ROW($Z$1:$Z$101)),ROW(A1)),3),"")} | W5: {=IFERROR(INDEX(Pendencias!$A$2:$O$4333,SMALL(IF(Pendencias!$B$2:$B$4333=$F$1,ROW(Pendencias!$B$2:$B$4333)-1),ROW(A5)),1),"")} | X5: {=IFERROR(INDEX(Pendencias!$A$2:$O$4333,SMALL(IF(Pendencias!$B$2:$B$4333=$F$1,ROW(Pendencias!$B$2:$B$4333)-1),ROW(A5)),3),"")} | Y5: {=IFERROR(INDEX(Pendencias!$A$2:$O$4333,SMALL(IF(Pendencias!$B$2:$B$4333=$F$1,ROW(Pendencias!$B$2:$B$4333)-1),ROW(A5)),4),"")} | Z5: {=IFERROR(INDEX(Pendencias!$A$2:$O$4333,SMALL(IF(Pendencias!$B$2:$B$4333=$F$1,ROW(Pendencias!$B$2:$B$4333)-1),ROW(A5)),7),"")} | AA5: {=IF(IFERROR(INDEX(Pendencias!$A$2:$O$4333,SMALL(IF(Pendencias!$B$2:$B$4333=$F$1,ROW(Pendencias!$B$2:$B$4333)-1),ROW(A5)),9),"")=0,"",IFERROR(INDEX(Pendencias!$A$2:$O$4333,SMALL(IF(Pendencias!$B$2:$B$4333=$F$1,ROW(Pendencias!$B$2:$B$4333)-1),ROW(A5)),9),""))}
A6: {=IFERROR(INDEX($W$1:$Z$101,SMALL(IF($Z$1:$Z$101="A fazer",ROW($Z$1:$Z$101)),ROW(A2)),1),"")} | B6: {=IFERROR(INDEX($W$1:$Z$101,SMALL(IF($Z$1:$Z$101="A fazer",ROW($Z$1:$Z$101)),ROW(A2)),2),"")} | J6: {=IFERROR(INDEX($W$1:$Z$101,SMALL(IF($Z$1:$Z$101="A fazer",ROW($Z$1:$Z$101)),ROW(A2)),3),"")} | W6: {=IFERROR(INDEX(Pendencias!$A$2:$O$4333,SMALL(IF(Pendencias!$B$2:$B$4333=$F$1,ROW(Pendencias!$B$2:$B$4333)-1),ROW(A6)),1),"")} | X6: {=IFERROR(INDEX(Pendencias!$A$2:$O$4333,SMALL(IF(Pendencias!$B$2:$B$4333=$F$1,ROW(Pendencias!$B$2:$B$4333)-1),ROW(A6)),3),"")} | Y6: {=IFERROR(INDEX(Pendencias!$A$2:$O$4333,SMALL(IF(Pendencias!$B$2:$B$4333=$F$1,ROW(Pendencias!$B$2:$B$4333)-1),ROW(A6)),4),"")} | Z6: {=IFERROR(INDEX(Pendencias!$A$2:$O$4333,SMALL(IF(Pendencias!$B$2:$B$4333=$F$1,ROW(Pendencias!$B$2:$B$4333)-1),ROW(A6)),7),"")} | AA6: {=IF(IFERROR(INDEX(Pendencias!$A$2:$O$4333,SMALL(IF(Pendencias!$B$2:$B$4333=$F$1,ROW(Pendencias!$B$2:$B$4333)-1),ROW(A6)),9),"")=0,"",IFERROR(INDEX(Pendencias!$A$2:$O$4333,SMALL(IF(Pendencias!$B$2:$B$4333=$F$1,ROW(Pendencias!$B$2:$B$4333)-1),ROW(A6)),9),""))}
A7: {=IFERROR(INDEX($W$1:$Z$101,SMALL(IF($Z$1:$Z$101="A fazer",ROW($Z$1:$Z$101)),ROW(A3)),1),"")} | B7: {=IFERROR(INDEX($W$1:$Z$101,SMALL(IF($Z$1:$Z$101="A fazer",ROW($Z$1:$Z$101)),ROW(A3)),2),"")} | J7: {=IFERROR(INDEX($W$1:$Z$101,SMALL(IF($Z$1:$Z$101="A fazer",ROW($Z$1:$Z$101)),ROW(A3)),3),"")} | W7: {=IFERROR(INDEX(Pendencias!$A$2:$O$4333,SMALL(IF(Pendencias!$B$2:$B$4333=$F$1,ROW(Pendencias!$B$2:$B$4333)-1),ROW(A7)),1),"")} | X7: {=IFERROR(INDEX(Pendencias!$A$2:$O$4333,SMALL(IF(Pendencias!$B$2:$B$4333=$F$1,ROW(Pendencias!$B$2:$B$4333)-1),ROW(A7)),3),"")} | Y7: {=IFERROR(INDEX(Pendencias!$A$2:$O$4333,SMALL(IF(Pendencias!$B$2:$B$4333=$F$1,ROW(Pendencias!$B$2:$B$4333)-1),ROW(A7)),4),"")} | Z7: {=IFERROR(INDEX(Pendencias!$A$2:$O$4333,SMALL(IF(Pendencias!$B$2:$B$4333=$F$1,ROW(Pendencias!$B$2:$B$4333)-1),ROW(A7)),7),"")} | AA7: {=IF(IFERROR(INDEX(Pendencias!$A$2:$O$4333,SMALL(IF(Pendencias!$B$2:$B$4333=$F$1,ROW(Pendencias!$B$2:$B$4333)-1),ROW(A7)),9),"")=0,"",IFERROR(INDEX(Pendencias!$A$2:$O$4333,SMALL(IF(Pendencias!$B$2:$B$4333=$F$1,ROW(Pendencias!$B$2:$B$4333)-1),ROW(A7)),9),""))}
A8: {=IFERROR(INDEX($W$1:$Z$101,SMALL(IF($Z$1:$Z$101="A fazer",ROW($Z$1:$Z$101)),ROW(A4)),1),"")} | B8: {=IFERROR(INDEX($W$1:$Z$101,SMALL(IF($Z$1:$Z$101="A fazer",ROW($Z$1:$Z$101)),ROW(A4)),2),"")} | J8: {=IFERROR(INDEX($W$1:$Z$101,SMALL(IF($Z$1:$Z$101="A fazer",ROW($Z$1:$Z$101)),ROW(A4)),3),"")} | W8: {=IFERROR(INDEX(Pendencias!$A$2:$O$4333,SMALL(IF(Pendencias!$B$2:$B$4333=$F$1,ROW(Pendencias!$B$2:$B$4333)-1),ROW(A8)),1),"")} | X8: {=IFERROR(INDEX(Pendencias!$A$2:$O$4333,SMALL(IF(Pendencias!$B$2:$B$4333=$F$1,ROW(Pendencias!$B$2:$B$4333)-1),ROW(A8)),3),"")} | Y8: {=IFERROR(INDEX(Pendencias!$A$2:$O$4333,SMALL(IF(Pendencias!$B$2:$B$4333=$F$1,ROW(Pendencias!$B$2:$B$4333)-1),ROW(A8)),4),"")} | Z8: {=IFERROR(INDEX(Pendencias!$A$2:$O$4333,SMALL(IF(Pendencias!$B$2:$B$4333=$F$1,ROW(Pendencias!$B$2:$B$4333)-1),ROW(A8)),7),"")} | AA8: {=IF(IFERROR(INDEX(Pendencias!$A$2:$O$4333,SMALL(IF(Pendencias!$B$2:$B$4333=$F$1,ROW(Pendencias!$B$2:$B$4333)-1),ROW(A8)),9),"")=0,"",IFERROR(INDEX(Pendencias!$A$2:$O$4333,SMALL(IF(Pendencias!$B$2:$B$4333=$F$1,ROW(Pendencias!$B$2:$B$4333)-1),ROW(A8)),9),""))}
A9: {=IFERROR(INDEX($W$1:$Z$101,SMALL(IF($Z$1:$Z$101="A fazer",ROW($Z$1:$Z$101)),ROW(A5)),1),"")} | B9: {=IFERROR(INDEX($W$1:$Z$101,SMALL(IF($Z$1:$Z$101="A fazer",ROW($Z$1:$Z$101)),ROW(A5)),2),"")} | J9: {=IFERROR(INDEX($W$1:$Z$101,SMALL(IF($Z$1:$Z$101="A fazer",ROW($Z$1:$Z$101)),ROW(A5)),3),"")} | W9: {=IFERROR(INDEX(Pendencias!$A$2:$O$4333,SMALL(IF(Pendencias!$B$2:$B$4333=$F$1,ROW(Pendencias!$B$2:$B$4333)-1),ROW(A9)),1),"")} | X9: {=IFERROR(INDEX(Pendencias!$A$2:$O$4333,SMALL(IF(Pendencias!$B$2:$B$4333=$F$1,ROW(Pendencias!$B$2:$B$4333)-1),ROW(A9)),3),"")} | Y9: {=IFERROR(INDEX(Pendencias!$A$2:$O$4333,SMALL(IF(Pendencias!$B$2:$B$4333=$F$1,ROW(Pendencias!$B$2:$B$4333)-1),ROW(A9)),4),"")} | Z9: {=IFERROR(INDEX(Pendencias!$A$2:$O$4333,SMALL(IF(Pendencias!$B$2:$B$4333=$F$1,ROW(Pendencias!$B$2:$B$4333)-1),ROW(A9)),7),"")} | AA9: {=IF(IFERROR(INDEX(Pendencias!$A$2:$O$4333,SMALL(IF(Pendencias!$B$2:$B$4333=$F$1,ROW(Pendencias!$B$2:$B$4333)-1),ROW(A9)),9),"")=0,"",IFERROR(INDEX(Pendencias!$A$2:$O$4333,SMALL(IF(Pendencias!$B$2:$B$4333=$F$1,ROW(Pendencias!$B$2:$B$4333)-1),ROW(A9)),9),""))}
A10: {=IFERROR(INDEX($W$1:$Z$101,SMALL(IF($Z$1:$Z$101="A fazer",ROW($Z$1:$Z$101)),ROW(A6)),1),"")} | B10: {=IFERROR(INDEX($W$1:$Z$101,SMALL(IF($Z$1:$Z$101="A fazer",ROW($Z$1:$Z$101)),ROW(A6)),2),"")} | J10: {=IFERROR(INDEX($W$1:$Z$101,SMALL(IF($Z$1:$Z$101="A fazer",ROW($Z$1:$Z$101)),ROW(A6)),3),"")} | W10: {=IFERROR(INDEX(Pendencias!$A$2:$O$4333,SMALL(IF(Pendencias!$B$2:$B$4333=$F$1,ROW(Pendencias!$B$2:$B$4333)-1),ROW(A10)),1),"")} | X10: {=IFERROR(INDEX(Pendencias!$A$2:$O$4333,SMALL(IF(Pendencias!$B$2:$B$4333=$F$1,ROW(Pendencias!$B$2:$B$4333)-1),ROW(A10)),3),"")} | Y10: {=IFERROR(INDEX(Pendencias!$A$2:$O$4333,SMALL(IF(Pendencias!$B$2:$B$4333=$F$1,ROW(Pendencias!$B$2:$B$4333)-1),ROW(A10)),4),"")} | Z10: {=IFERROR(INDEX(Pendencias!$A$2:$O$4333,SMALL(IF(Pendencias!$B$2:$B$4333=$F$1,ROW(Pendencias!$B$2:$B$4333)-1),ROW(A10)),7),"")} | AA10: {=IF(IFERROR(INDEX(Pendencias!$A$2:$O$4333,SMALL(IF(Pendencias!$B$2:$B$4333=$F$1,ROW(Pendencias!$B$2:$B$4333)-1),ROW(A10)),9),"")=0,"",IFERROR(INDEX(Pendencias!$A$2:$O$4333,SMALL(IF(Pendencias!$B$2:$B$4333=$F$1,ROW(Pendencias!$B$2:$B$4333)-1),ROW(A10)),9),""))}
A11: {=IFERROR(INDEX($W$1:$Z$101,SMALL(IF($Z$1:$Z$101="A fazer",ROW($Z$1:$Z$101)),ROW(A7)),1),"")} | B11: {=IFERROR(INDEX($W$1:$Z$101,SMALL(IF($Z$1:$Z$101="A fazer",ROW($Z$1:$Z$101)),ROW(A7)),2),"")} | J11: {=IFERROR(INDEX($W$1:$Z$101,SMALL(IF($Z$1:$Z$101="A fazer",ROW($Z$1:$Z$101)),ROW(A7)),3),"")} | W11: {=IFERROR(INDEX(Pendencias!$A$2:$O$4333,SMALL(IF(Pendencias!$B$2:$B$4333=$F$1,ROW(Pendencias!$B$2:$B$4333)-1),ROW(A11)),1),"")} | X11: {=IFERROR(INDEX(Pendencias!$A$2:$O$4333,SMALL(IF(Pendencias!$B$2:$B$4333=$F$1,ROW(Pendencias!$B$2:$B$4333)-1),ROW(A11)),3),"")} | Y11: {=IFERROR(INDEX(Pendencias!$A$2:$O$4333,SMALL(IF(Pendencias!$B$2:$B$4333=$F$1,ROW(Pendencias!$B$2:$B$4333)-1),ROW(A11)),4),"")} | Z11: {=IFERROR(INDEX(Pendencias!$A$2:$O$4333,SMALL(IF(Pendencias!$B$2:$B$4333=$F$1,ROW(Pendencias!$B$2:$B$4333)-1),ROW(A11)),7),"")} | AA11: {=IF(IFERROR(INDEX(Pendencias!$A$2:$O$4333,SMALL(IF(Pendencias!$B$2:$B$4333=$F$1,ROW(Pendencias!$B$2:$B$4333)-1),ROW(A11)),9),"")=0,"",IFERROR(INDEX(Pendencias!$A$2:$O$4333,SMALL(IF(Pendencias!$B$2:$B$4333=$F$1,ROW(Pendencias!$B$2:$B$4333)-1),ROW(A11)),9),""))}
A12: {=IFERROR(INDEX($W$1:$Z$101,SMALL(IF($Z$1:$Z$101="A fazer",ROW($Z$1:$Z$101)),ROW(A8)),1),"")} | B12: {=IFERROR(INDEX($W$1:$Z$101,SMALL(IF($Z$1:$Z$101="A fazer",ROW($Z$1:$Z$101)),ROW(A8)),2),"")} | J12: {=IFERROR(INDEX($W$1:$Z$101,SMALL(IF($Z$1:$Z$101="A fazer",ROW($Z$1:$Z$101)),ROW(A8)),3),"")} | W12: {=IFERROR(INDEX(Pendencias!$A$2:$O$4333,SMALL(IF(Pendencias!$B$2:$B$4333=$F$1,ROW(Pendencias!$B$2:$B$4333)-1),ROW(A12)),1),"")} | X12: {=IFERROR(INDEX(Pendencias!$A$2:$O$4333,SMALL(IF(Pendencias!$B$2:$B$4333=$F$1,ROW(Pendencias!$B$2:$B$4333)-1),ROW(A12)),3),"")} | Y12: {=IFERROR(INDEX(Pendencias!$A$2:$O$4333,SMALL(IF(Pendencias!$B$2:$B$4333=$F$1,ROW(Pendencias!$B$2:$B$4333)-1),ROW(A12)),4),"")} | Z12: {=IFERROR(INDEX(Pendencias!$A$2:$O$4333,SMALL(IF(Pendencias!$B$2:$B$4333=$F$1,ROW(Pendencias!$B$2:$B$4333)-1),ROW(A12)),7),"")} | AA12: {=IF(IFERROR(INDEX(Pendencias!$A$2:$O$4333,SMALL(IF(Pendencias!$B$2:$B$4333=$F$1,ROW(Pendencias!$B$2:$B$4333)-1),ROW(A12)),9),"")=0,"",IFERROR(INDEX(Pendencias!$A$2:$O$4333,SMALL(IF(Pendencias!$B$2:$B$4333=$F$1,ROW(Pendencias!$B$2:$B$4333)-1),ROW(A12)),9),""))}
A13: {=IFERROR(INDEX($W$1:$Z$101,SMALL(IF($Z$1:$Z$101="A fazer",ROW($Z$1:$Z$101)),ROW(A9)),1),"")} | B13: {=IFERROR(INDEX($W$1:$Z$101,SMALL(IF($Z$1:$Z$101="A fazer",ROW($Z$1:$Z$101)),ROW(A9)),2),"")} | J13: {=IFERROR(INDEX($W$1:$Z$101,SMALL(IF($Z$1:$Z$101="A fazer",ROW($Z$1:$Z$101)),ROW(A9)),3),"")} | W13: {=IFERROR(INDEX(Pendencias!$A$2:$O$4333,SMALL(IF(Pendencias!$B$2:$B$4333=$F$1,ROW(Pendencias!$B$2:$B$4333)-1),ROW(A13)),1),"")} | X13: {=IFERROR(INDEX(Pendencias!$A$2:$O$4333,SMALL(IF(Pendencias!$B$2:$B$4333=$F$1,ROW(Pendencias!$B$2:$B$4333)-1),ROW(A13)),3),"")} | Y13: {=IFERROR(INDEX(Pendencias!$A$2:$O$4333,SMALL(IF(Pendencias!$B$2:$B$4333=$F$1,ROW(Pendencias!$B$2:$B$4333)-1),ROW(A13)),4),"")} | Z13: {=IFERROR(INDEX(Pendencias!$A$2:$O$4333,SMALL(IF(Pendencias!$B$2:$B$4333=$F$1,ROW(Pendencias!$B$2:$B$4333)-1),ROW(A13)),7),"")} | AA13: {=IF(IFERROR(INDEX(Pendencias!$A$2:$O$4333,SMALL(IF(Pendencias!$B$2:$B$4333=$F$1,ROW(Pendencias!$B$2:$B$4333)-1),ROW(A13)),9),"")=0,"",IFERROR(INDEX(Pendencias!$A$2:$O$4333,SMALL(IF(Pendencias!$B$2:$B$4333=$F$1,ROW(Pendencias!$B$2:$B$4333)-1),ROW(A13)),9),""))}
A14: {=IFERROR(INDEX($W$1:$Z$101,SMALL(IF($Z$1:$Z$101="A fazer",ROW($Z$1:$Z$101)),ROW(A10)),1),"")} | B14: {=IFERROR(INDEX($W$1:$Z$101,SMALL(IF($Z$1:$Z$101="A fazer",ROW($Z$1:$Z$101)),ROW(A10)),2),"")} | J14: {=IFERROR(INDEX($W$1:$Z$101,SMALL(IF($Z$1:$Z$101="A fazer",ROW($Z$1:$Z$101)),ROW(A10)),3),"")} | W14: {=IFERROR(INDEX(Pendencias!$A$2:$O$4333,SMALL(IF(Pendencias!$B$2:$B$4333=$F$1,ROW(Pendencias!$B$2:$B$4333)-1),ROW(A14)),1),"")} | X14: {=IFERROR(INDEX(Pendencias!$A$2:$O$4333,SMALL(IF(Pendencias!$B$2:$B$4333=$F$1,ROW(Pendencias!$B$2:$B$4333)-1),ROW(A14)),3),"")} | Y14: {=IFERROR(INDEX(Pendencias!$A$2:$O$4333,SMALL(IF(Pendencias!$B$2:$B$4333=$F$1,ROW(Pendencias!$B$2:$B$4333)-1),ROW(A14)),4),"")} | Z14: {=IFERROR(INDEX(Pendencias!$A$2:$O$4333,SMALL(IF(Pendencias!$B$2:$B$4333=$F$1,ROW(Pendencias!$B$2:$B$4333)-1),ROW(A14)),7),"")} | AA14: {=IF(IFERROR(INDEX(Pendencias!$A$2:$O$4333,SMALL(IF(Pendencias!$B$2:$B$4333=$F$1,ROW(Pendencias!$B$2:$B$4333)-1),ROW(A14)),9),"")=0,"",IFERROR(INDEX(Pendencias!$A$2:$O$4333,SMALL(IF(Pendencias!$B$2:$B$4333=$F$1,ROW(Pendencias!$B$2:$B$4333)-1),ROW(A14)),9),""))}
A15: {=IFERROR(INDEX($W$1:$Z$101,SMALL(IF($Z$1:$Z$101="A fazer",ROW($Z$1:$Z$101)),ROW(A11)),1),"")} | B15: {=IFERROR(INDEX($W$1:$Z$101,SMALL(IF($Z$1:$Z$101="A fazer",ROW($Z$1:$Z$101)),ROW(A11)),2),"")} | J15: {=IFERROR(INDEX($W$1:$Z$101,SMALL(IF($Z$1:$Z$101="A fazer",ROW($Z$1:$Z$101)),ROW(A11)),3),"")} | W15: {=IFERROR(INDEX(Pendencias!$A$2:$O$4333,SMALL(IF(Pendencias!$B$2:$B$4333=$F$1,ROW(Pendencias!$B$2:$B$4333)-1),ROW(A15)),1),"")} | X15: {=IFERROR(INDEX(Pendencias!$A$2:$O$4333,SMALL(IF(Pendencias!$B$2:$B$4333=$F$1,ROW(Pendencias!$B$2:$B$4333)-1),ROW(A15)),3),"")} | Y15: {=IFERROR(INDEX(Pendencias!$A$2:$O$4333,SMALL(IF(Pendencias!$B$2:$B$4333=$F$1,ROW(Pendencias!$B$2:$B$4333)-1),ROW(A15)),4),"")} | Z15: {=IFERROR(INDEX(Pendencias!$A$2:$O$4333,SMALL(IF(Pendencias!$B$2:$B$4333=$F$1,ROW(Pendencias!$B$2:$B$4333)-1),ROW(A15)),7),"")} | AA15: {=IF(IFERROR(INDEX(Pendencias!$A$2:$O$4333,SMALL(IF(Pendencias!$B$2:$B$4333=$F$1,ROW(Pendencias!$B$2:$B$4333)-1),ROW(A15)),9),"")=0,"",IFERROR(INDEX(Pendencias!$A$2:$O$4333,SMALL(IF(Pendencias!$B$2:$B$4333=$F$1,ROW(Pendencias!$B$2:$B$4333)-1),ROW(A15)),9),""))}
W16: {=IFERROR(INDEX(Pendencias!$A$2:$O$4333,SMALL(IF(Pendencias!$B$2:$B$4333=$F$1,ROW(Pendencias!$B$2:$B$4333)-1),ROW(A16)),1),"")} | X16: {=IFERROR(INDEX(Pendencias!$A$2:$O$4333,SMALL(IF(Pendencias!$B$2:$B$4333=$F$1,ROW(Pendencias!$B$2:$B$4333)-1),ROW(A16)),3),"")} | Y16: {=IFERROR(INDEX(Pendencias!$A$2:$O$4333,SMALL(IF(Pendencias!$B$2:$B$4333=$F$1,ROW(Pendencias!$B$2:$B$4333)-1),ROW(A16)),4),"")} | Z16: {=IFERROR(INDEX(Pendencias!$A$2:$O$4333,SMALL(IF(Pendencias!$B$2:$B$4333=$F$1,ROW(Pendencias!$B$2:$B$4333)-1),ROW(A16)),7),"")} | AA16: {=IF(IFERROR(INDEX(Pendencias!$A$2:$O$4333,SMALL(IF(Pendencias!$B$2:$B$4333=$F$1,ROW(Pendencias!$B$2:$B$4333)-1),ROW(A16)),9),"")=0,"",IFERROR(INDEX(Pendencias!$A$2:$O$4333,SMALL(IF(Pendencias!$B$2:$B$4333=$F$1,ROW(Pendencias!$B$2:$B$4333)-1),ROW(A16)),9),""))}
A17: Problemas em aberto na Estação | W17: {=IFERROR(INDEX(Pendencias!$A$2:$O$4333,SMALL(IF(Pendencias!$B$2:$B$4333=$F$1,ROW(Pendencias!$B$2:$B$4333)-1),ROW(A17)),1),"")} | X17: {=IFERROR(INDEX(Pendencias!$A$2:$O$4333,SMALL(IF(Pendencias!$B$2:$B$4333=$F$1,ROW(Pendencias!$B$2:$B$4333)-1),ROW(A17)),3),"")} | Y17: {=IFERROR(INDEX(Pendencias!$A$2:$O$4333,SMALL(IF(Pendencias!$B$2:$B$4333=$F$1,ROW(Pendencias!$B$2:$B$4333)-1),ROW(A17)),4),"")} | Z17: {=IFERROR(INDEX(Pendencias!$A$2:$O$4333,SMALL(IF(Pendencias!$B$2:$B$4333=$F$1,ROW(Pendencias!$B$2:$B$4333)-1),ROW(A17)),7),"")} | AA17: {=IF(IFERROR(INDEX(Pendencias!$A$2:$O$4333,SMALL(IF(Pendencias!$B$2:$B$4333=$F$1,ROW(Pendencias!$B$2:$B$4333)-1),ROW(A17)),9),"")=0,"",IFERROR(INDEX(Pendencias!$A$2:$O$4333,SMALL(IF(Pendencias!$B$2:$B$4333=$F$1,ROW(Pendencias!$B$2:$B$4333)-1),ROW(A17)),9),""))}
A18: KEY | B18: DATA INÍCIO | C18: PRIORIDADE | D18: PROBLEMA | G18: RESUMO DO PROBLEMA | W18: {=IFERROR(INDEX(Pendencias!$A$2:$O$4333,SMALL(IF(Pendencias!$B$2:$B$4333=$F$1,ROW(Pendencias!$B$2:$B$4333)-1),ROW(A18)),1),"")} | X18: {=IFERROR(INDEX(Pendencias!$A$2:$O$4333,SMALL(IF(Pendencias!$B$2:$B$4333=$F$1,ROW(Pendencias!$B$2:$B$4333)-1),ROW(A18)),3),"")} | Y18: {=IFERROR(INDEX(Pendencias!$A$2:$O$4333,SMALL(IF(Pendencias!$B$2:$B$4333=$F$1,ROW(Pendencias!$B$2:$B$4333)-1),ROW(A18)),4),"")} | Z18: {=IFERROR(INDEX(Pendencias!$A$2:$O$4333,SMALL(IF(Pendencias!$B$2:$B$4333=$F$1,ROW(Pendencias!$B$2:$B$4333)-1),ROW(A18)),7),"")} | AA18: {=IF(IFERROR(INDEX(Pendencias!$A$2:$O$4333,SMALL(IF(Pendencias!$B$2:$B$4333=$F$1,ROW(Pendencias!$B$2:$B$4333)-1),ROW(A18)),9),"")=0,"",IFERROR(INDEX(Pendencias!$A$2:$O$4333,SMALL(IF(Pendencias!$B$2:$B$4333=$F$1,ROW(Pendencias!$B$2:$B$4333)-1),ROW(A18)),9),""))}
A19: =IFERROR(INDEX('Problemas em aberto'!$A$2:$G$303,SMALL(IF('Problemas em aberto'!$E$2:$E$303=IFERROR(VLOOKUP($F$1,Tabela5[#All],12,0),""),ROW('Problemas em aberto'!$E$2:$E$303)-1),ROW(A1)),1),"") -> #ERROR! | B19: =IFERROR(INDEX('Problemas em aberto'!$A$2:$G$303,SMALL(IF('Problemas em aberto'!$E$2:$E$303=IFERROR(VLOOKUP($F$1,Tabela5[#All],12,0),""),ROW('Problemas em aberto'!$E$2:$E$303)-1),ROW(A1)),2),"") -> #ERROR! | C19: =IFERROR(INDEX('Problemas em aberto'!$A$2:$G$303,SMALL(IF('Problemas em aberto'!$E$2:$E$303=IFERROR(VLOOKUP($F$1,Tabela5[#All],12,0),""),ROW('Problemas em aberto'!$E$2:$E$303)-1),ROW(A1)),7),"") -> #ERROR! | D19: =IFERROR(INDEX('Problemas em aberto'!$A$2:$G$303,SMALL(IF('Problemas em aberto'!$E$2:$E$303=IFERROR(VLOOKUP($F$1,Tabela5[#All],12,0),""),ROW('Problemas em aberto'!$E$2:$E$303)-1),ROW(A1)),6),"") -> #ERROR! | G19: =IFERROR(INDEX('Problemas em aberto'!$A$2:$G$303,SMALL(IF('Problemas em aberto'!$E$2:$E$303=IFERROR(VLOOKUP($F$1,Tabela5[#All],12,0),""),ROW('Problemas em aberto'!$E$2:$E$303)-1),ROW(A1)),4),"") -> #ERROR! | W19: {=IFERROR(INDEX(Pendencias!$A$2:$O$4333,SMALL(IF(Pendencias!$B$2:$B$4333=$F$1,ROW(Pendencias!$B$2:$B$4333)-1),ROW(A19)),1),"")} | X19: {=IFERROR(INDEX(Pendencias!$A$2:$O$4333,SMALL(IF(Pendencias!$B$2:$B$4333=$F$1,ROW(Pendencias!$B$2:$B$4333)-1),ROW(A19)),3),"")} | Y19: {=IFERROR(INDEX(Pendencias!$A$2:$O$4333,SMALL(IF(Pendencias!$B$2:$B$4333=$F$1,ROW(Pendencias!$B$2:$B$4333)-1),ROW(A19)),4),"")} | Z19: {=IFERROR(INDEX(Pendencias!$A$2:$O$4333,SMALL(IF(Pendencias!$B$2:$B$4333=$F$1,ROW(Pendencias!$B$2:$B$4333)-1),ROW(A19)),7),"")} | AA19: {=IF(IFERROR(INDEX(Pendencias!$A$2:$O$4333,SMALL(IF(Pendencias!$B$2:$B$4333=$F$1,ROW(Pendencias!$B$2:$B$4333)-1),ROW(A19)),9),"")=0,"",IFERROR(INDEX(Pendencias!$A$2:$O$4333,SMALL(IF(Pendencias!$B$2:$B$4333=$F$1,ROW(Pendencias!$B$2:$B$4333)-1),ROW(A19)),9),""))}
A20: =IFERROR(INDEX('Problemas em aberto'!$A$2:$G$303,SMALL(IF('Problemas em aberto'!$E$2:$E$303=IFERROR(VLOOKUP($F$1,Tabela5[#All],12,0),""),ROW('Problemas em aberto'!$E$2:$E$303)-1),ROW(A2)),1),"") -> #ERROR! | B20: =IFERROR(INDEX('Problemas em aberto'!$A$2:$G$303,SMALL(IF('Problemas em aberto'!$E$2:$E$303=IFERROR(VLOOKUP($F$1,Tabela5[#All],12,0),""),ROW('Problemas em aberto'!$E$2:$E$303)-1),ROW(A2)),2),"") -> #ERROR! | C20: =IFERROR(INDEX('Problemas em aberto'!$A$2:$G$303,SMALL(IF('Problemas em aberto'!$E$2:$E$303=IFERROR(VLOOKUP($F$1,Tabela5[#All],12,0),""),ROW('Problemas em aberto'!$E$2:$E$303)-1),ROW(A2)),7),"") -> #ERROR! | D20: =IFERROR(INDEX('Problemas em aberto'!$A$2:$G$303,SMALL(IF('Problemas em aberto'!$E$2:$E$303=IFERROR(VLOOKUP($F$1,Tabela5[#All],12,0),""),ROW('Problemas em aberto'!$E$2:$E$303)-1),ROW(A2)),6),"") -> #ERROR! | G20: =IFERROR(INDEX('Problemas em aberto'!$A$2:$G$303,SMALL(IF('Problemas em aberto'!$E$2:$E$303=IFERROR(VLOOKUP($F$1,Tabela5[#All],12,0),""),ROW('Problemas em aberto'!$E$2:$E$303)-1),ROW(A2)),4),"") -> #ERROR! | W20: {=IFERROR(INDEX(Pendencias!$A$2:$O$4333,SMALL(IF(Pendencias!$B$2:$B$4333=$F$1,ROW(Pendencias!$B$2:$B$4333)-1),ROW(A20)),1),"")} | X20: {=IFERROR(INDEX(Pendencias!$A$2:$O$4333,SMALL(IF(Pendencias!$B$2:$B$4333=$F$1,ROW(Pendencias!$B$2:$B$4333)-1),ROW(A20)),3),"")} | Y20: {=IFERROR(INDEX(Pendencias!$A$2:$O$4333,SMALL(IF(Pendencias!$B$2:$B$4333=$F$1,ROW(Pendencias!$B$2:$B$4333)-1),ROW(A20)),4),"")} | Z20: {=IFERROR(INDEX(Pendencias!$A$2:$O$4333,SMALL(IF(Pendencias!$B$2:$B$4333=$F$1,ROW(Pendencias!$B$2:$B$4333)-1),ROW(A20)),7),"")} | AA20: {=IF(IFERROR(INDEX(Pendencias!$A$2:$O$4333,SMALL(IF(Pendencias!$B$2:$B$4333=$F$1,ROW(Pendencias!$B$2:$B$4333)-1),ROW(A20)),9),"")=0,"",IFERROR(INDEX(Pendencias!$A$2:$O$4333,SMALL(IF(Pendencias!$B$2:$B$4333=$F$1,ROW(Pendencias!$B$2:$B$4333)-1),ROW(A20)),9),""))}
A21: =IFERROR(INDEX('Problemas em aberto'!$A$2:$G$303,SMALL(IF('Problemas em aberto'!$E$2:$E$303=IFERROR(VLOOKUP($F$1,Tabela5[#All],12,0),""),ROW('Problemas em aberto'!$E$2:$E$303)-1),ROW(A3)),1),"") -> #ERROR! | B21: =IFERROR(INDEX('Problemas em aberto'!$A$2:$G$303,SMALL(IF('Problemas em aberto'!$E$2:$E$303=IFERROR(VLOOKUP($F$1,Tabela5[#All],12,0),""),ROW('Problemas em aberto'!$E$2:$E$303)-1),ROW(A3)),2),"") -> #ERROR! | C21: =IFERROR(INDEX('Problemas em aberto'!$A$2:$G$303,SMALL(IF('Problemas em aberto'!$E$2:$E$303=IFERROR(VLOOKUP($F$1,Tabela5[#All],12,0),""),ROW('Problemas em aberto'!$E$2:$E$303)-1),ROW(A3)),7),"") -> #ERROR! | D21: =IFERROR(INDEX('Problemas em aberto'!$A$2:$G$303,SMALL(IF('Problemas em aberto'!$E$2:$E$303=IFERROR(VLOOKUP($F$1,Tabela5[#All],12,0),""),ROW('Problemas em aberto'!$E$2:$E$303)-1),ROW(A3)),6),"") -> #ERROR! | G21: =IFERROR(INDEX('Problemas em aberto'!$A$2:$G$303,SMALL(IF('Problemas em aberto'!$E$2:$E$303=IFERROR(VLOOKUP($F$1,Tabela5[#All],12,0),""),ROW('Problemas em aberto'!$E$2:$E$303)-1),ROW(A3)),4),"") -> #ERROR! | W21: {=IFERROR(INDEX(Pendencias!$A$2:$O$4333,SMALL(IF(Pendencias!$B$2:$B$4333=$F$1,ROW(Pendencias!$B$2:$B$4333)-1),ROW(A21)),1),"")} | X21: {=IFERROR(INDEX(Pendencias!$A$2:$O$4333,SMALL(IF(Pendencias!$B$2:$B$4333=$F$1,ROW(Pendencias!$B$2:$B$4333)-1),ROW(A21)),3),"")} | Y21: {=IFERROR(INDEX(Pendencias!$A$2:$O$4333,SMALL(IF(Pendencias!$B$2:$B$4333=$F$1,ROW(Pendencias!$B$2:$B$4333)-1),ROW(A21)),4),"")} | Z21: {=IFERROR(INDEX(Pendencias!$A$2:$O$4333,SMALL(IF(Pendencias!$B$2:$B$4333=$F$1,ROW(Pendencias!$B$2:$B$4333)-1),ROW(A21)),7),"")} | AA21: {=IF(IFERROR(INDEX(Pendencias!$A$2:$O$4333,SMALL(IF(Pendencias!$B$2:$B$4333=$F$1,ROW(Pendencias!$B$2:$B$4333)-1),ROW(A21)),9),"")=0,"",IFERROR(INDEX(Pendencias!$A$2:$O$4333,SMALL(IF(Pendencias!$B$2:$B$4333=$F$1,ROW(Pendencias!$B$2:$B$4333)-1),ROW(A21)),9),""))}
A22: =IFERROR(INDEX('Problemas em aberto'!$A$2:$G$303,SMALL(IF('Problemas em aberto'!$E$2:$E$303=IFERROR(VLOOKUP($F$1,Tabela5[#All],12,0),""),ROW('Problemas em aberto'!$E$2:$E$303)-1),ROW(A4)),1),"") -> #ERROR! | B22: =IFERROR(INDEX('Problemas em aberto'!$A$2:$G$303,SMALL(IF('Problemas em aberto'!$E$2:$E$303=IFERROR(VLOOKUP($F$1,Tabela5[#All],12,0),""),ROW('Problemas em aberto'!$E$2:$E$303)-1),ROW(A4)),2),"") -> #ERROR! | C22: =IFERROR(INDEX('Problemas em aberto'!$A$2:$G$303,SMALL(IF('Problemas em aberto'!$E$2:$E$303=IFERROR(VLOOKUP($F$1,Tabela5[#All],12,0),""),ROW('Problemas em aberto'!$E$2:$E$303)-1),ROW(A4)),7),"") -> #ERROR! | D22: =IFERROR(INDEX('Problemas em aberto'!$A$2:$G$303,SMALL(IF('Problemas em aberto'!$E$2:$E$303=IFERROR(VLOOKUP($F$1,Tabela5[#All],12,0),""),ROW('Problemas em aberto'!$E$2:$E$303)-1),ROW(A4)),6),"") -> #ERROR! | G22: =IFERROR(INDEX('Problemas em aberto'!$A$2:$G$303,SMALL(IF('Problemas em aberto'!$E$2:$E$303=IFERROR(VLOOKUP($F$1,Tabela5[#All],12,0),""),ROW('Problemas em aberto'!$E$2:$E$303)-1),ROW(A4)),4),"") -> #ERROR! | W22: {=IFERROR(INDEX(Pendencias!$A$2:$O$4333,SMALL(IF(Pendencias!$B$2:$B$4333=$F$1,ROW(Pendencias!$B$2:$B$4333)-1),ROW(A22)),1),"")} | X22: {=IFERROR(INDEX(Pendencias!$A$2:$O$4333,SMALL(IF(Pendencias!$B$2:$B$4333=$F$1,ROW(Pendencias!$B$2:$B$4333)-1),ROW(A22)),3),"")} | Y22: {=IFERROR(INDEX(Pendencias!$A$2:$O$4333,SMALL(IF(Pendencias!$B$2:$B$4333=$F$1,ROW(Pendencias!$B$2:$B$4333)-1),ROW(A22)),4),"")} | Z22: {=IFERROR(INDEX(Pendencias!$A$2:$O$4333,SMALL(IF(Pendencias!$B$2:$B$4333=$F$1,ROW(Pendencias!$B$2:$B$4333)-1),ROW(A22)),7),"")} | AA22: {=IF(IFERROR(INDEX(Pendencias!$A$2:$O$4333,SMALL(IF(Pendencias!$B$2:$B$4333=$F$1,ROW(Pendencias!$B$2:$B$4333)-1),ROW(A22)),9),"")=0,"",IFERROR(INDEX(Pendencias!$A$2:$O$4333,SMALL(IF(Pendencias!$B$2:$B$4333=$F$1,ROW(Pendencias!$B$2:$B$4333)-1),ROW(A22)),9),""))}
A23: =IFERROR(INDEX('Problemas em aberto'!$A$2:$G$303,SMALL(IF('Problemas em aberto'!$E$2:$E$303=IFERROR(VLOOKUP($F$1,Tabela5[#All],12,0),""),ROW('Problemas em aberto'!$E$2:$E$303)-1),ROW(A5)),1),"") -> #ERROR! | B23: =IFERROR(INDEX('Problemas em aberto'!$A$2:$G$303,SMALL(IF('Problemas em aberto'!$E$2:$E$303=IFERROR(VLOOKUP($F$1,Tabela5[#All],12,0),""),ROW('Problemas em aberto'!$E$2:$E$303)-1),ROW(A5)),2),"") -> #ERROR! | C23: =IFERROR(INDEX('Problemas em aberto'!$A$2:$G$303,SMALL(IF('Problemas em aberto'!$E$2:$E$303=IFERROR(VLOOKUP($F$1,Tabela5[#All],12,0),""),ROW('Problemas em aberto'!$E$2:$E$303)-1),ROW(A5)),7),"") -> #ERROR! | D23: =IFERROR(INDEX('Problemas em aberto'!$A$2:$G$303,SMALL(IF('Problemas em aberto'!$E$2:$E$303=IFERROR(VLOOKUP($F$1,Tabela5[#All],12,0),""),ROW('Problemas em aberto'!$E$2:$E$303)-1),ROW(A5)),6),"") -> #ERROR! | G23: =IFERROR(INDEX('Problemas em aberto'!$A$2:$G$303,SMALL(IF('Problemas em aberto'!$E$2:$E$303=IFERROR(VLOOKUP($F$1,Tabela5[#All],12,0),""),ROW('Problemas em aberto'!$E$2:$E$303)-1),ROW(A5)),4),"") -> #ERROR! | W23: {=IFERROR(INDEX(Pendencias!$A$2:$O$4333,SMALL(IF(Pendencias!$B$2:$B$4333=$F$1,ROW(Pendencias!$B$2:$B$4333)-1),ROW(A23)),1),"")} | X23: {=IFERROR(INDEX(Pendencias!$A$2:$O$4333,SMALL(IF(Pendencias!$B$2:$B$4333=$F$1,ROW(Pendencias!$B$2:$B$4333)-1),ROW(A23)),3),"")} | Y23: {=IFERROR(INDEX(Pendencias!$A$2:$O$4333,SMALL(IF(Pendencias!$B$2:$B$4333=$F$1,ROW(Pendencias!$B$2:$B$4333)-1),ROW(A23)),4),"")} | Z23: {=IFERROR(INDEX(Pendencias!$A$2:$O$4333,SMALL(IF(Pendencias!$B$2:$B$4333=$F$1,ROW(Pendencias!$B$2:$B$4333)-1),ROW(A23)),7),"")} | AA23: {=IF(IFERROR(INDEX(Pendencias!$A$2:$O$4333,SMALL(IF(Pendencias!$B$2:$B$4333=$F$1,ROW(Pendencias!$B$2:$B$4333)-1),ROW(A23)),9),"")=0,"",IFERROR(INDEX(Pendencias!$A$2:$O$4333,SMALL(IF(Pendencias!$B$2:$B$4333=$F$1,ROW(Pendencias!$B$2:$B$4333)-1),ROW(A23)),9),""))}
A24: =IFERROR(INDEX('Problemas em aberto'!$A$2:$G$303,SMALL(IF('Problemas em aberto'!$E$2:$E$303=IFERROR(VLOOKUP($F$1,Tabela5[#All],12,0),""),ROW('Problemas em aberto'!$E$2:$E$303)-1),ROW(A6)),1),"") -> #ERROR! | B24: =IFERROR(INDEX('Problemas em aberto'!$A$2:$G$303,SMALL(IF('Problemas em aberto'!$E$2:$E$303=IFERROR(VLOOKUP($F$1,Tabela5[#All],12,0),""),ROW('Problemas em aberto'!$E$2:$E$303)-1),ROW(A6)),2),"") -> #ERROR! | C24: =IFERROR(INDEX('Problemas em aberto'!$A$2:$G$303,SMALL(IF('Problemas em aberto'!$E$2:$E$303=IFERROR(VLOOKUP($F$1,Tabela5[#All],12,0),""),ROW('Problemas em aberto'!$E$2:$E$303)-1),ROW(A6)),7),"") -> #ERROR! | D24: =IFERROR(INDEX('Problemas em aberto'!$A$2:$G$303,SMALL(IF('Problemas em aberto'!$E$2:$E$303=IFERROR(VLOOKUP($F$1,Tabela5[#All],12,0),""),ROW('Problemas em aberto'!$E$2:$E$303)-1),ROW(A6)),6),"") -> #ERROR! | G24: =IFERROR(INDEX('Problemas em aberto'!$A$2:$G$303,SMALL(IF('Problemas em aberto'!$E$2:$E$303=IFERROR(VLOOKUP($F$1,Tabela5[#All],12,0),""),ROW('Problemas em aberto'!$E$2:$E$303)-1),ROW(A6)),4),"") -> #ERROR! | W24: {=IFERROR(INDEX(Pendencias!$A$2:$O$4333,SMALL(IF(Pendencias!$B$2:$B$4333=$F$1,ROW(Pendencias!$B$2:$B$4333)-1),ROW(A24)),1),"")} | X24: {=IFERROR(INDEX(Pendencias!$A$2:$O$4333,SMALL(IF(Pendencias!$B$2:$B$4333=$F$1,ROW(Pendencias!$B$2:$B$4333)-1),ROW(A24)),3),"")} | Y24: {=IFERROR(INDEX(Pendencias!$A$2:$O$4333,SMALL(IF(Pendencias!$B$2:$B$4333=$F$1,ROW(Pendencias!$B$2:$B$4333)-1),ROW(A24)),4),"")} | Z24: {=IFERROR(INDEX(Pendencias!$A$2:$O$4333,SMALL(IF(Pendencias!$B$2:$B$4333=$F$1,ROW(Pendencias!$B$2:$B$4333)-1),ROW(A24)),7),"")} | AA24: {=IF(IFERROR(INDEX(Pendencias!$A$2:$O$4333,SMALL(IF(Pendencias!$B$2:$B$4333=$F$1,ROW(Pendencias!$B$2:$B$4333)-1),ROW(A24)),9),"")=0,"",IFERROR(INDEX(Pendencias!$A$2:$O$4333,SMALL(IF(Pendencias!$B$2:$B$4333=$F$1,ROW(Pendencias!$B$2:$B$4333)-1),ROW(A24)),9),""))}
W25: {=IFERROR(INDEX(Pendencias!$A$2:$O$4333,SMALL(IF(Pendencias!$B$2:$B$4333=$F$1,ROW(Pendencias!$B$2:$B$4333)-1),ROW(A25)),1),"")} | X25: {=IFERROR(INDEX(Pendencias!$A$2:$O$4333,SMALL(IF(Pendencias!$B$2:$B$4333=$F$1,ROW(Pendencias!$B$2:$B$4333)-1),ROW(A25)),3),"")} | Y25: {=IFERROR(INDEX(Pendencias!$A$2:$O$4333,SMALL(IF(Pendencias!$B$2:$B$4333=$F$1,ROW(Pendencias!$B$2:$B$4333)-1),ROW(A25)),4),"")} | Z25: {=IFERROR(INDEX(Pendencias!$A$2:$O$4333,SMALL(IF(Pendencias!$B$2:$B$4333=$F$1,ROW(Pendencias!$B$2:$B$4333)-1),ROW(A25)),7),"")} | AA25: {=IF(IFERROR(INDEX(Pendencias!$A$2:$O$4333,SMALL(IF(Pendencias!$B$2:$B$4333=$F$1,ROW(Pendencias!$B$2:$B$4333)-1),ROW(A25)),9),"")=0,"",IFERROR(INDEX(Pendencias!$A$2:$O$4333,SMALL(IF(Pendencias!$B$2:$B$4333=$F$1,ROW(Pendencias!$B$2:$B$4333)-1),ROW(A25)),9),""))}
A26: Tipo de Manobra (assinale apenas 1) | W26: {=IFERROR(INDEX(Pendencias!$A$2:$O$4333,SMALL(IF(Pendencias!$B$2:$B$4333=$F$1,ROW(Pendencias!$B$2:$B$4333)-1),ROW(A26)),1),"")} | X26: {=IFERROR(INDEX(Pendencias!$A$2:$O$4333,SMALL(IF(Pendencias!$B$2:$B$4333=$F$1,ROW(Pendencias!$B$2:$B$4333)-1),ROW(A26)),3),"")} | Y26: {=IFERROR(INDEX(Pendencias!$A$2:$O$4333,SMALL(IF(Pendencias!$B$2:$B$4333=$F$1,ROW(Pendencias!$B$2:$B$4333)-1),ROW(A26)),4),"")} | Z26: {=IFERROR(INDEX(Pendencias!$A$2:$O$4333,SMALL(IF(Pendencias!$B$2:$B$4333=$F$1,ROW(Pendencias!$B$2:$B$4333)-1),ROW(A26)),7),"")} | AA26: {=IF(IFERROR(INDEX(Pendencias!$A$2:$O$4333,SMALL(IF(Pendencias!$B$2:$B$4333=$F$1,ROW(Pendencias!$B$2:$B$4333)-1),ROW(A26)),9),"")=0,"",IFERROR(INDEX(Pendencias!$A$2:$O$4333,SMALL(IF(Pendencias!$B$2:$B$4333=$F$1,ROW(Pendencias!$B$2:$B$4333)-1),ROW(A26)),9),""))}
A27: Emergencial ( ) | C27: Preventiva ( ) | E27: Instalação ( ) | G27: Desinstalação ( ) | I27: Aferição ( ) | L27: {=IFERROR(INDEX(Pendencias!$A$2:$O$209,SMALL(IF(Pendencias!$B$2:$B$209=$F$1,ROW(Pendencias!$B$2:$B$209)-1),ROW(A32)),1),"")} | O27: {=IFERROR(INDEX(Pendencias!$A$2:$O$209,SMALL(IF(Pendencias!$B$2:$B$209=$F$1,ROW(Pendencias!$B$2:$B$209)-1),ROW(A32)),7),"")} | W27: {=IFERROR(INDEX(Pendencias!$A$2:$O$4333,SMALL(IF(Pendencias!$B$2:$B$4333=$F$1,ROW(Pendencias!$B$2:$B$4333)-1),ROW(A27)),1),"")} | X27: {=IFERROR(INDEX(Pendencias!$A$2:$O$4333,SMALL(IF(Pendencias!$B$2:$B$4333=$F$1,ROW(Pendencias!$B$2:$B$4333)-1),ROW(A27)),3),"")} | Y27: {=IFERROR(INDEX(Pendencias!$A$2:$O$4333,SMALL(IF(Pendencias!$B$2:$B$4333=$F$1,ROW(Pendencias!$B$2:$B$4333)-1),ROW(A27)),4),"")} | Z27: {=IFERROR(INDEX(Pendencias!$A$2:$O$4333,SMALL(IF(Pendencias!$B$2:$B$4333=$F$1,ROW(Pendencias!$B$2:$B$4333)-1),ROW(A27)),7),"")} | AA27: {=IF(IFERROR(INDEX(Pendencias!$A$2:$O$4333,SMALL(IF(Pendencias!$B$2:$B$4333=$F$1,ROW(Pendencias!$B$2:$B$4333)-1),ROW(A27)),9),"")=0,"",IFERROR(INDEX(Pendencias!$A$2:$O$4333,SMALL(IF(Pendencias!$B$2:$B$4333=$F$1,ROW(Pendencias!$B$2:$B$4333)-1),ROW(A27)),9),""))}
A28: Vistoria ( ) | C28: Visita técnica ( ) | E28: Nivelamento Régua( ) | H28: Outro: | L28: {=IFERROR(INDEX(Pendencias!$A$2:$O$209,SMALL(IF(Pendencias!$B$2:$B$209=$F$1,ROW(Pendencias!$B$2:$B$209)-1),ROW(A33)),1),"")} | O28: {=IFERROR(INDEX(Pendencias!$A$2:$O$209,SMALL(IF(Pendencias!$B$2:$B$209=$F$1,ROW(Pendencias!$B$2:$B$209)-1),ROW(A33)),7),"")} | W28: {=IFERROR(INDEX(Pendencias!$A$2:$O$4333,SMALL(IF(Pendencias!$B$2:$B$4333=$F$1,ROW(Pendencias!$B$2:$B$4333)-1),ROW(A28)),1),"")} | X28: {=IFERROR(INDEX(Pendencias!$A$2:$O$4333,SMALL(IF(Pendencias!$B$2:$B$4333=$F$1,ROW(Pendencias!$B$2:$B$4333)-1),ROW(A28)),3),"")} | Y28: {=IFERROR(INDEX(Pendencias!$A$2:$O$4333,SMALL(IF(Pendencias!$B$2:$B$4333=$F$1,ROW(Pendencias!$B$2:$B$4333)-1),ROW(A28)),4),"")} | Z28: {=IFERROR(INDEX(Pendencias!$A$2:$O$4333,SMALL(IF(Pendencias!$B$2:$B$4333=$F$1,ROW(Pendencias!$B$2:$B$4333)-1),ROW(A28)),7),"")} | AA28: {=IF(IFERROR(INDEX(Pendencias!$A$2:$O$4333,SMALL(IF(Pendencias!$B$2:$B$4333=$F$1,ROW(Pendencias!$B$2:$B$4333)-1),ROW(A28)),9),"")=0,"",IFERROR(INDEX(Pendencias!$A$2:$O$4333,SMALL(IF(Pendencias!$B$2:$B$4333=$F$1,ROW(Pendencias!$B$2:$B$4333)-1),ROW(A28)),9),""))}
L29: {=IFERROR(INDEX(Pendencias!$A$2:$O$209,SMALL(IF(Pendencias!$B$2:$B$209=$F$1,ROW(Pendencias!$B$2:$B$209)-1),ROW(A34)),1),"")} | O29: {=IFERROR(INDEX(Pendencias!$A$2:$O$209,SMALL(IF(Pendencias!$B$2:$B$209=$F$1,ROW(Pendencias!$B$2:$B$209)-1),ROW(A34)),7),"")} | W29: {=IFERROR(INDEX(Pendencias!$A$2:$O$4333,SMALL(IF(Pendencias!$B$2:$B$4333=$F$1,ROW(Pendencias!$B$2:$B$4333)-1),ROW(A29)),1),"")} | X29: {=IFERROR(INDEX(Pendencias!$A$2:$O$4333,SMALL(IF(Pendencias!$B$2:$B$4333=$F$1,ROW(Pendencias!$B$2:$B$4333)-1),ROW(A29)),3),"")} | Y29: {=IFERROR(INDEX(Pendencias!$A$2:$O$4333,SMALL(IF(Pendencias!$B$2:$B$4333=$F$1,ROW(Pendencias!$B$2:$B$4333)-1),ROW(A29)),4),"")} | Z29: {=IFERROR(INDEX(Pendencias!$A$2:$O$4333,SMALL(IF(Pendencias!$B$2:$B$4333=$F$1,ROW(Pendencias!$B$2:$B$4333)-1),ROW(A29)),7),"")} | AA29: {=IF(IFERROR(INDEX(Pendencias!$A$2:$O$4333,SMALL(IF(Pendencias!$B$2:$B$4333=$F$1,ROW(Pendencias!$B$2:$B$4333)-1),ROW(A29)),9),"")=0,"",IFERROR(INDEX(Pendencias!$A$2:$O$4333,SMALL(IF(Pendencias!$B$2:$B$4333=$F$1,ROW(Pendencias!$B$2:$B$4333)-1),ROW(A29)),9),""))}
A30: Motivo e Objetivos da Manobra | W30: {=IFERROR(INDEX(Pendencias!$A$2:$O$4333,SMALL(IF(Pendencias!$B$2:$B$4333=$F$1,ROW(Pendencias!$B$2:$B$4333)-1),ROW(A30)),1),"")} | X30: {=IFERROR(INDEX(Pendencias!$A$2:$O$4333,SMALL(IF(Pendencias!$B$2:$B$4333=$F$1,ROW(Pendencias!$B$2:$B$4333)-1),ROW(A30)),3),"")} | Y30: {=IFERROR(INDEX(Pendencias!$A$2:$O$4333,SMALL(IF(Pendencias!$B$2:$B$4333=$F$1,ROW(Pendencias!$B$2:$B$4333)-1),ROW(A30)),4),"")} | Z30: {=IFERROR(INDEX(Pendencias!$A$2:$O$4333,SMALL(IF(Pendencias!$B$2:$B$4333=$F$1,ROW(Pendencias!$B$2:$B$4333)-1),ROW(A30)),7),"")} | AA30: {=IF(IFERROR(INDEX(Pendencias!$A$2:$O$4333,SMALL(IF(Pendencias!$B$2:$B$4333=$F$1,ROW(Pendencias!$B$2:$B$4333)-1),ROW(A30)),9),"")=0,"",IFERROR(INDEX(Pendencias!$A$2:$O$4333,SMALL(IF(Pendencias!$B$2:$B$4333=$F$1,ROW(Pendencias!$B$2:$B$4333)-1),ROW(A30)),9),""))}
A31: Estou indo para realizar manutenção preventiva.. .. | W31: {=IFERROR(INDEX(Pendencias!$A$2:$O$4333,SMALL(IF(Pendencias!$B$2:$B$4333=$F$1,ROW(Pendencias!$B$2:$B$4333)-1),ROW(A31)),1),"")} | X31: {=IFERROR(INDEX(Pendencias!$A$2:$O$4333,SMALL(IF(Pendencias!$B$2:$B$4333=$F$1,ROW(Pendencias!$B$2:$B$4333)-1),ROW(A31)),3),"")} | Y31: {=IFERROR(INDEX(Pendencias!$A$2:$O$4333,SMALL(IF(Pendencias!$B$2:$B$4333=$F$1,ROW(Pendencias!$B$2:$B$4333)-1),ROW(A31)),4),"")} | Z31: {=IFERROR(INDEX(Pendencias!$A$2:$O$4333,SMALL(IF(Pendencias!$B$2:$B$4333=$F$1,ROW(Pendencias!$B$2:$B$4333)-1),ROW(A31)),7),"")} | AA31: {=IF(IFERROR(INDEX(Pendencias!$A$2:$O$4333,SMALL(IF(Pendencias!$B$2:$B$4333=$F$1,ROW(Pendencias!$B$2:$B$4333)-1),ROW(A31)),9),"")=0,"",IFERROR(INDEX(Pendencias!$A$2:$O$4333,SMALL(IF(Pendencias!$B$2:$B$4333=$F$1,ROW(Pendencias!$B$2:$B$4333)-1),ROW(A31)),9),""))}
W32: {=IFERROR(INDEX(Pendencias!$A$2:$O$4333,SMALL(IF(Pendencias!$B$2:$B$4333=$F$1,ROW(Pendencias!$B$2:$B$4333)-1),ROW(A32)),1),"")} | X32: {=IFERROR(INDEX(Pendencias!$A$2:$O$4333,SMALL(IF(Pendencias!$B$2:$B$4333=$F$1,ROW(Pendencias!$B$2:$B$4333)-1),ROW(A32)),3),"")} | Y32: {=IFERROR(INDEX(Pendencias!$A$2:$O$4333,SMALL(IF(Pendencias!$B$2:$B$4333=$F$1,ROW(Pendencias!$B$2:$B$4333)-1),ROW(A32)),4),"")} | Z32: {=IFERROR(INDEX(Pendencias!$A$2:$O$4333,SMALL(IF(Pendencias!$B$2:$B$4333=$F$1,ROW(Pendencias!$B$2:$B$4333)-1),ROW(A32)),7),"")} | AA32: {=IF(IFERROR(INDEX(Pendencias!$A$2:$O$4333,SMALL(IF(Pendencias!$B$2:$B$4333=$F$1,ROW(Pendencias!$B$2:$B$4333)-1),ROW(A32)),9),"")=0,"",IFERROR(INDEX(Pendencias!$A$2:$O$4333,SMALL(IF(Pendencias!$B$2:$B$4333=$F$1,ROW(Pendencias!$B$2:$B$4333)-1),ROW(A32)),9),""))}
A33: Avisos Importantes | W33: {=IFERROR(INDEX(Pendencias!$A$2:$O$4333,SMALL(IF(Pendencias!$B$2:$B$4333=$F$1,ROW(Pendencias!$B$2:$B$4333)-1),ROW(A33)),1),"")} | X33: {=IFERROR(INDEX(Pendencias!$A$2:$O$4333,SMALL(IF(Pendencias!$B$2:$B$4333=$F$1,ROW(Pendencias!$B$2:$B$4333)-1),ROW(A33)),3),"")} | Y33: {=IFERROR(INDEX(Pendencias!$A$2:$O$4333,SMALL(IF(Pendencias!$B$2:$B$4333=$F$1,ROW(Pendencias!$B$2:$B$4333)-1),ROW(A33)),4),"")} | Z33: {=IFERROR(INDEX(Pendencias!$A$2:$O$4333,SMALL(IF(Pendencias!$B$2:$B$4333=$F$1,ROW(Pendencias!$B$2:$B$4333)-1),ROW(A33)),7),"")} | AA33: {=IF(IFERROR(INDEX(Pendencias!$A$2:$O$4333,SMALL(IF(Pendencias!$B$2:$B$4333=$F$1,ROW(Pendencias!$B$2:$B$4333)-1),ROW(A33)),9),"")=0,"",IFERROR(INDEX(Pendencias!$A$2:$O$4333,SMALL(IF(Pendencias!$B$2:$B$4333=$F$1,ROW(Pendencias!$B$2:$B$4333)-1),ROW(A33)),9),""))}
A34: =IFERROR(VLOOKUP(F1,'Cadastro Estacoes'!A:AD,30,0),"") | W34: {=IFERROR(INDEX(Pendencias!$A$2:$O$4333,SMALL(IF(Pendencias!$B$2:$B$4333=$F$1,ROW(Pendencias!$B$2:$B$4333)-1),ROW(A34)),1),"")} | X34: {=IFERROR(INDEX(Pendencias!$A$2:$O$4333,SMALL(IF(Pendencias!$B$2:$B$4333=$F$1,ROW(Pendencias!$B$2:$B$4333)-1),ROW(A34)),3),"")} | Y34: {=IFERROR(INDEX(Pendencias!$A$2:$O$4333,SMALL(IF(Pendencias!$B$2:$B$4333=$F$1,ROW(Pendencias!$B$2:$B$4333)-1),ROW(A34)),4),"")} | Z34: {=IFERROR(INDEX(Pendencias!$A$2:$O$4333,SMALL(IF(Pendencias!$B$2:$B$4333=$F$1,ROW(Pendencias!$B$2:$B$4333)-1),ROW(A34)),7),"")} | AA34: {=IF(IFERROR(INDEX(Pendencias!$A$2:$O$4333,SMALL(IF(Pendencias!$B$2:$B$4333=$F$1,ROW(Pendencias!$B$2:$B$4333)-1),ROW(A34)),9),"")=0,"",IFERROR(INDEX(Pendencias!$A$2:$O$4333,SMALL(IF(Pendencias!$B$2:$B$4333=$F$1,ROW(Pendencias!$B$2:$B$4333)-1),ROW(A34)),9),""))}
A35: EPI OBRIGATÓRIO
A36: =VLOOKUP(F1,'Cadastro Estacoes'!A:AC,29,0) -> CALÇA BRIM E CAMISETA MANGA LONGA; BOTINA COM BICO DE PVC; COLETE SALVA-VIDAS (OUTROS EPI'S PODEM SER NECESSÁRIOS, DEPENDENDO DA ATIVIDADE ESPECÍFICA A SER EXECUTADA) | W36: {=IFERROR(INDEX(Pendencias!$A$2:$O$209,SMALL(IF(Pendencias!$B$2:$B$209=$F$1,ROW(Pendencias!$B$2:$B$209)-1),ROW(A39)),1),"")} | X36: {=IFERROR(INDEX(Pendencias!$A$2:$O$209,SMALL(IF(Pendencias!$B$2:$B$209=$F$1,ROW(Pendencias!$B$2:$B$209)-1),ROW(A39)),3),"")} | Y36: {=IFERROR(INDEX(Pendencias!$A$2:$O$209,SMALL(IF(Pendencias!$B$2:$B$209=$F$1,ROW(Pendencias!$B$2:$B$209)-1),ROW(A39)),4),"")} | Z36: {=IFERROR(INDEX(Pendencias!$A$2:$O$209,SMALL(IF(Pendencias!$B$2:$B$209=$F$1,ROW(Pendencias!$B$2:$B$209)-1),ROW(A39)),7),"")} | AA36: {=IF(IFERROR(INDEX(Pendencias!$A$2:$O$209,SMALL(IF(Pendencias!$B$2:$B$209=$F$1,ROW(Pendencias!$B$2:$B$209)-1),ROW(A39)),9),"")=0,"",IFERROR(INDEX(Pendencias!$A$2:$O$209,SMALL(IF(Pendencias!$B$2:$B$209=$F$1,ROW(Pendencias!$B$2:$B$209)-1),ROW(A39)),9),""))}
A37: Horário de Início da Manobra | F37: Horário Término da Manobra | W37: {=IFERROR(INDEX(Pendencias!$A$2:$O$209,SMALL(IF(Pendencias!$B$2:$B$209=$F$1,ROW(Pendencias!$B$2:$B$209)-1),ROW(A40)),1),"")} | X37: {=IFERROR(INDEX(Pendencias!$A$2:$O$209,SMALL(IF(Pendencias!$B$2:$B$209=$F$1,ROW(Pendencias!$B$2:$B$209)-1),ROW(A40)),3),"")} | Y37: {=IFERROR(INDEX(Pendencias!$A$2:$O$209,SMALL(IF(Pendencias!$B$2:$B$209=$F$1,ROW(Pendencias!$B$2:$B$209)-1),ROW(A40)),4),"")} | Z37: {=IFERROR(INDEX(Pendencias!$A$2:$O$209,SMALL(IF(Pendencias!$B$2:$B$209=$F$1,ROW(Pendencias!$B$2:$B$209)-1),ROW(A40)),7),"")} | AA37: {=IF(IFERROR(INDEX(Pendencias!$A$2:$O$209,SMALL(IF(Pendencias!$B$2:$B$209=$F$1,ROW(Pendencias!$B$2:$B$209)-1),ROW(A40)),9),"")=0,"",IFERROR(INDEX(Pendencias!$A$2:$O$209,SMALL(IF(Pendencias!$B$2:$B$209=$F$1,ROW(Pendencias!$B$2:$B$209)-1),ROW(A40)),9),""))}
W38: {=IFERROR(INDEX(Pendencias!$A$2:$O$209,SMALL(IF(Pendencias!$B$2:$B$209=$F$1,ROW(Pendencias!$B$2:$B$209)-1),ROW(A41)),1),"")} | X38: {=IFERROR(INDEX(Pendencias!$A$2:$O$209,SMALL(IF(Pendencias!$B$2:$B$209=$F$1,ROW(Pendencias!$B$2:$B$209)-1),ROW(A41)),3),"")} | Y38: {=IFERROR(INDEX(Pendencias!$A$2:$O$209,SMALL(IF(Pendencias!$B$2:$B$209=$F$1,ROW(Pendencias!$B$2:$B$209)-1),ROW(A41)),4),"")} | Z38: {=IFERROR(INDEX(Pendencias!$A$2:$O$209,SMALL(IF(Pendencias!$B$2:$B$209=$F$1,ROW(Pendencias!$B$2:$B$209)-1),ROW(A41)),7),"")} | AA38: {=IF(IFERROR(INDEX(Pendencias!$A$2:$O$209,SMALL(IF(Pendencias!$B$2:$B$209=$F$1,ROW(Pendencias!$B$2:$B$209)-1),ROW(A41)),9),"")=0,"",IFERROR(INDEX(Pendencias!$A$2:$O$209,SMALL(IF(Pendencias!$B$2:$B$209=$F$1,ROW(Pendencias!$B$2:$B$209)-1),ROW(A41)),9),""))}
A39: Condições ambientais no ínicio da manobra | C39: Sem Chuva ( ) | F39: Chuva Fraca ( ) | I39: Chuva Forte ( ) | W39: {=IFERROR(INDEX(Pendencias!$A$2:$O$209,SMALL(IF(Pendencias!$B$2:$B$209=$F$1,ROW(Pendencias!$B$2:$B$209)-1),ROW(A42)),1),"")} | X39: {=IFERROR(INDEX(Pendencias!$A$2:$O$209,SMALL(IF(Pendencias!$B$2:$B$209=$F$1,ROW(Pendencias!$B$2:$B$209)-1),ROW(A42)),3),"")} | Y39: {=IFERROR(INDEX(Pendencias!$A$2:$O$209,SMALL(IF(Pendencias!$B$2:$B$209=$F$1,ROW(Pendencias!$B$2:$B$209)-1),ROW(A42)),4),"")} | Z39: {=IFERROR(INDEX(Pendencias!$A$2:$O$209,SMALL(IF(Pendencias!$B$2:$B$209=$F$1,ROW(Pendencias!$B$2:$B$209)-1),ROW(A42)),7),"")} | AA39: {=IF(IFERROR(INDEX(Pendencias!$A$2:$O$209,SMALL(IF(Pendencias!$B$2:$B$209=$F$1,ROW(Pendencias!$B$2:$B$209)-1),ROW(A42)),9),"")=0,"",IFERROR(INDEX(Pendencias!$A$2:$O$209,SMALL(IF(Pendencias!$B$2:$B$209=$F$1,ROW(Pendencias!$B$2:$B$209)-1),ROW(A42)),9),""))}
C40: Ventos Fracos ( ) | F40: Vento Moderado ( ) | I40: Ventos Fortes ( ) | W40: {=IFERROR(INDEX(Pendencias!$A$2:$O$209,SMALL(IF(Pendencias!$B$2:$B$209=$F$1,ROW(Pendencias!$B$2:$B$209)-1),ROW(A43)),1),"")} | X40: {=IFERROR(INDEX(Pendencias!$A$2:$O$209,SMALL(IF(Pendencias!$B$2:$B$209=$F$1,ROW(Pendencias!$B$2:$B$209)-1),ROW(A43)),3),"")} | Y40: {=IFERROR(INDEX(Pendencias!$A$2:$O$209,SMALL(IF(Pendencias!$B$2:$B$209=$F$1,ROW(Pendencias!$B$2:$B$209)-1),ROW(A43)),4),"")} | Z40: {=IFERROR(INDEX(Pendencias!$A$2:$O$209,SMALL(IF(Pendencias!$B$2:$B$209=$F$1,ROW(Pendencias!$B$2:$B$209)-1),ROW(A43)),7),"")} | AA40: {=IF(IFERROR(INDEX(Pendencias!$A$2:$O$209,SMALL(IF(Pendencias!$B$2:$B$209=$F$1,ROW(Pendencias!$B$2:$B$209)-1),ROW(A43)),9),"")=0,"",IFERROR(INDEX(Pendencias!$A$2:$O$209,SMALL(IF(Pendencias!$B$2:$B$209=$F$1,ROW(Pendencias!$B$2:$B$209)-1),ROW(A43)),9),""))}
C41: Mar Calmo ( ) | F41: Ondas Moderadas ( ) | I41: Ondas Altas ( ) | W41: {=IFERROR(INDEX(Pendencias!$A$2:$O$209,SMALL(IF(Pendencias!$B$2:$B$209=$F$1,ROW(Pendencias!$B$2:$B$209)-1),ROW(A44)),1),"")} | X41: {=IFERROR(INDEX(Pendencias!$A$2:$O$209,SMALL(IF(Pendencias!$B$2:$B$209=$F$1,ROW(Pendencias!$B$2:$B$209)-1),ROW(A44)),3),"")} | Y41: {=IFERROR(INDEX(Pendencias!$A$2:$O$209,SMALL(IF(Pendencias!$B$2:$B$209=$F$1,ROW(Pendencias!$B$2:$B$209)-1),ROW(A44)),4),"")} | Z41: {=IFERROR(INDEX(Pendencias!$A$2:$O$209,SMALL(IF(Pendencias!$B$2:$B$209=$F$1,ROW(Pendencias!$B$2:$B$209)-1),ROW(A44)),7),"")} | AA41: {=IF(IFERROR(INDEX(Pendencias!$A$2:$O$209,SMALL(IF(Pendencias!$B$2:$B$209=$F$1,ROW(Pendencias!$B$2:$B$209)-1),ROW(A44)),9),"")=0,"",IFERROR(INDEX(Pendencias!$A$2:$O$209,SMALL(IF(Pendencias!$B$2:$B$209=$F$1,ROW(Pendencias!$B$2:$B$209)-1),ROW(A44)),9),""))}
C42: Correntes Fracas ( ) | F42: Correntes Moderadas ( ) | I42: Correntes Fortes ( ) | W42: {=IFERROR(INDEX(Pendencias!$A$2:$O$209,SMALL(IF(Pendencias!$B$2:$B$209=$F$1,ROW(Pendencias!$B$2:$B$209)-1),ROW(A45)),1),"")} | X42: {=IFERROR(INDEX(Pendencias!$A$2:$O$209,SMALL(IF(Pendencias!$B$2:$B$209=$F$1,ROW(Pendencias!$B$2:$B$209)-1),ROW(A45)),3),"")} | Y42: {=IFERROR(INDEX(Pendencias!$A$2:$O$209,SMALL(IF(Pendencias!$B$2:$B$209=$F$1,ROW(Pendencias!$B$2:$B$209)-1),ROW(A45)),4),"")} | Z42: {=IFERROR(INDEX(Pendencias!$A$2:$O$209,SMALL(IF(Pendencias!$B$2:$B$209=$F$1,ROW(Pendencias!$B$2:$B$209)-1),ROW(A45)),7),"")} | AA42: {=IF(IFERROR(INDEX(Pendencias!$A$2:$O$209,SMALL(IF(Pendencias!$B$2:$B$209=$F$1,ROW(Pendencias!$B$2:$B$209)-1),ROW(A45)),9),"")=0,"",IFERROR(INDEX(Pendencias!$A$2:$O$209,SMALL(IF(Pendencias!$B$2:$B$209=$F$1,ROW(Pendencias!$B$2:$B$209)-1),ROW(A45)),9),""))}
W43: {=IFERROR(INDEX(Pendencias!$A$2:$O$209,SMALL(IF(Pendencias!$B$2:$B$209=$F$1,ROW(Pendencias!$B$2:$B$209)-1),ROW(A46)),1),"")} | X43: {=IFERROR(INDEX(Pendencias!$A$2:$O$209,SMALL(IF(Pendencias!$B$2:$B$209=$F$1,ROW(Pendencias!$B$2:$B$209)-1),ROW(A46)),3),"")} | Y43: {=IFERROR(INDEX(Pendencias!$A$2:$O$209,SMALL(IF(Pendencias!$B$2:$B$209=$F$1,ROW(Pendencias!$B$2:$B$209)-1),ROW(A46)),4),"")} | Z43: {=IFERROR(INDEX(Pendencias!$A$2:$O$209,SMALL(IF(Pendencias!$B$2:$B$209=$F$1,ROW(Pendencias!$B$2:$B$209)-1),ROW(A46)),7),"")} | AA43: {=IF(IFERROR(INDEX(Pendencias!$A$2:$O$209,SMALL(IF(Pendencias!$B$2:$B$209=$F$1,ROW(Pendencias!$B$2:$B$209)-1),ROW(A46)),9),"")=0,"",IFERROR(INDEX(Pendencias!$A$2:$O$209,SMALL(IF(Pendencias!$B$2:$B$209=$F$1,ROW(Pendencias!$B$2:$B$209)-1),ROW(A46)),9),""))}
A44: Informações sobre embarcação, tripulação e mergulho | W44: {=IFERROR(INDEX(Pendencias!$A$2:$O$209,SMALL(IF(Pendencias!$B$2:$B$209=$F$1,ROW(Pendencias!$B$2:$B$209)-1),ROW(A47)),1),"")} | X44: {=IFERROR(INDEX(Pendencias!$A$2:$O$209,SMALL(IF(Pendencias!$B$2:$B$209=$F$1,ROW(Pendencias!$B$2:$B$209)-1),ROW(A47)),3),"")} | Y44: {=IFERROR(INDEX(Pendencias!$A$2:$O$209,SMALL(IF(Pendencias!$B$2:$B$209=$F$1,ROW(Pendencias!$B$2:$B$209)-1),ROW(A47)),4),"")} | Z44: {=IFERROR(INDEX(Pendencias!$A$2:$O$209,SMALL(IF(Pendencias!$B$2:$B$209=$F$1,ROW(Pendencias!$B$2:$B$209)-1),ROW(A47)),7),"")} | AA44: {=IF(IFERROR(INDEX(Pendencias!$A$2:$O$209,SMALL(IF(Pendencias!$B$2:$B$209=$F$1,ROW(Pendencias!$B$2:$B$209)-1),ROW(A47)),9),"")=0,"",IFERROR(INDEX(Pendencias!$A$2:$O$209,SMALL(IF(Pendencias!$B$2:$B$209=$F$1,ROW(Pendencias!$B$2:$B$209)-1),ROW(A47)),9),""))}
A45: Embarcação 1: | F45: Embarcação 2: | W45: {=IFERROR(INDEX(Pendencias!$A$2:$O$209,SMALL(IF(Pendencias!$B$2:$B$209=$F$1,ROW(Pendencias!$B$2:$B$209)-1),ROW(A48)),1),"")} | X45: {=IFERROR(INDEX(Pendencias!$A$2:$O$209,SMALL(IF(Pendencias!$B$2:$B$209=$F$1,ROW(Pendencias!$B$2:$B$209)-1),ROW(A48)),3),"")} | Y45: {=IFERROR(INDEX(Pendencias!$A$2:$O$209,SMALL(IF(Pendencias!$B$2:$B$209=$F$1,ROW(Pendencias!$B$2:$B$209)-1),ROW(A48)),4),"")} | Z45: {=IFERROR(INDEX(Pendencias!$A$2:$O$209,SMALL(IF(Pendencias!$B$2:$B$209=$F$1,ROW(Pendencias!$B$2:$B$209)-1),ROW(A48)),7),"")} | AA45: {=IF(IFERROR(INDEX(Pendencias!$A$2:$O$209,SMALL(IF(Pendencias!$B$2:$B$209=$F$1,ROW(Pendencias!$B$2:$B$209)-1),ROW(A48)),9),"")=0,"",IFERROR(INDEX(Pendencias!$A$2:$O$209,SMALL(IF(Pendencias!$B$2:$B$209=$F$1,ROW(Pendencias!$B$2:$B$209)-1),ROW(A48)),9),""))}
A46: Mestre Emb. 1: | F46: Mestre Emb. 2: | W46: {=IFERROR(INDEX(Pendencias!$A$2:$O$209,SMALL(IF(Pendencias!$B$2:$B$209=$F$1,ROW(Pendencias!$B$2:$B$209)-1),ROW(A49)),1),"")} | X46: {=IFERROR(INDEX(Pendencias!$A$2:$O$209,SMALL(IF(Pendencias!$B$2:$B$209=$F$1,ROW(Pendencias!$B$2:$B$209)-1),ROW(A49)),3),"")} | Y46: {=IFERROR(INDEX(Pendencias!$A$2:$O$209,SMALL(IF(Pendencias!$B$2:$B$209=$F$1,ROW(Pendencias!$B$2:$B$209)-1),ROW(A49)),4),"")} | Z46: {=IFERROR(INDEX(Pendencias!$A$2:$O$209,SMALL(IF(Pendencias!$B$2:$B$209=$F$1,ROW(Pendencias!$B$2:$B$209)-1),ROW(A49)),7),"")} | AA46: {=IF(IFERROR(INDEX(Pendencias!$A$2:$O$209,SMALL(IF(Pendencias!$B$2:$B$209=$F$1,ROW(Pendencias!$B$2:$B$209)-1),ROW(A49)),9),"")=0,"",IFERROR(INDEX(Pendencias!$A$2:$O$209,SMALL(IF(Pendencias!$B$2:$B$209=$F$1,ROW(Pendencias!$B$2:$B$209)-1),ROW(A49)),9),""))}
A47: Marinheiros Emb.1: | F47: Marinheiros Emb.2: | W47: {=IFERROR(INDEX(Pendencias!$A$2:$O$209,SMALL(IF(Pendencias!$B$2:$B$209=$F$1,ROW(Pendencias!$B$2:$B$209)-1),ROW(A50)),1),"")} | X47: {=IFERROR(INDEX(Pendencias!$A$2:$O$209,SMALL(IF(Pendencias!$B$2:$B$209=$F$1,ROW(Pendencias!$B$2:$B$209)-1),ROW(A50)),3),"")} | Y47: {=IFERROR(INDEX(Pendencias!$A$2:$O$209,SMALL(IF(Pendencias!$B$2:$B$209=$F$1,ROW(Pendencias!$B$2:$B$209)-1),ROW(A50)),4),"")} | Z47: {=IFERROR(INDEX(Pendencias!$A$2:$O$209,SMALL(IF(Pendencias!$B$2:$B$209=$F$1,ROW(Pendencias!$B$2:$B$209)-1),ROW(A50)),7),"")} | AA47: {=IF(IFERROR(INDEX(Pendencias!$A$2:$O$209,SMALL(IF(Pendencias!$B$2:$B$209=$F$1,ROW(Pendencias!$B$2:$B$209)-1),ROW(A50)),9),"")=0,"",IFERROR(INDEX(Pendencias!$A$2:$O$209,SMALL(IF(Pendencias!$B$2:$B$209=$F$1,ROW(Pendencias!$B$2:$B$209)-1),ROW(A50)),9),""))}
A48: Empresa Embarcação: | W48: {=IFERROR(INDEX(Pendencias!$A$2:$O$209,SMALL(IF(Pendencias!$B$2:$B$209=$F$1,ROW(Pendencias!$B$2:$B$209)-1),ROW(A51)),1),"")} | X48: {=IFERROR(INDEX(Pendencias!$A$2:$O$209,SMALL(IF(Pendencias!$B$2:$B$209=$F$1,ROW(Pendencias!$B$2:$B$209)-1),ROW(A51)),3),"")} | Y48: {=IFERROR(INDEX(Pendencias!$A$2:$O$209,SMALL(IF(Pendencias!$B$2:$B$209=$F$1,ROW(Pendencias!$B$2:$B$209)-1),ROW(A51)),4),"")} | Z48: {=IFERROR(INDEX(Pendencias!$A$2:$O$209,SMALL(IF(Pendencias!$B$2:$B$209=$F$1,ROW(Pendencias!$B$2:$B$209)-1),ROW(A51)),7),"")} | AA48: {=IF(IFERROR(INDEX(Pendencias!$A$2:$O$209,SMALL(IF(Pendencias!$B$2:$B$209=$F$1,ROW(Pendencias!$B$2:$B$209)-1),ROW(A51)),9),"")=0,"",IFERROR(INDEX(Pendencias!$A$2:$O$209,SMALL(IF(Pendencias!$B$2:$B$209=$F$1,ROW(Pendencias!$B$2:$B$209)-1),ROW(A51)),9),""))}
A49: Mergulhadores: | W49: {=IFERROR(INDEX(Pendencias!$A$2:$O$209,SMALL(IF(Pendencias!$B$2:$B$209=$F$1,ROW(Pendencias!$B$2:$B$209)-1),ROW(A52)),1),"")} | X49: {=IFERROR(INDEX(Pendencias!$A$2:$O$209,SMALL(IF(Pendencias!$B$2:$B$209=$F$1,ROW(Pendencias!$B$2:$B$209)-1),ROW(A52)),3),"")} | Y49: {=IFERROR(INDEX(Pendencias!$A$2:$O$209,SMALL(IF(Pendencias!$B$2:$B$209=$F$1,ROW(Pendencias!$B$2:$B$209)-1),ROW(A52)),4),"")} | Z49: {=IFERROR(INDEX(Pendencias!$A$2:$O$209,SMALL(IF(Pendencias!$B$2:$B$209=$F$1,ROW(Pendencias!$B$2:$B$209)-1),ROW(A52)),7),"")} | AA49: {=IF(IFERROR(INDEX(Pendencias!$A$2:$O$209,SMALL(IF(Pendencias!$B$2:$B$209=$F$1,ROW(Pendencias!$B$2:$B$209)-1),ROW(A52)),9),"")=0,"",IFERROR(INDEX(Pendencias!$A$2:$O$209,SMALL(IF(Pendencias!$B$2:$B$209=$F$1,ROW(Pendencias!$B$2:$B$209)-1),ROW(A52)),9),""))}
A50: Empresa Mergulho: | W50: {=IFERROR(INDEX(Pendencias!$A$2:$O$209,SMALL(IF(Pendencias!$B$2:$B$209=$F$1,ROW(Pendencias!$B$2:$B$209)-1),ROW(A53)),1),"")} | X50: {=IFERROR(INDEX(Pendencias!$A$2:$O$209,SMALL(IF(Pendencias!$B$2:$B$209=$F$1,ROW(Pendencias!$B$2:$B$209)-1),ROW(A53)),3),"")} | Y50: {=IFERROR(INDEX(Pendencias!$A$2:$O$209,SMALL(IF(Pendencias!$B$2:$B$209=$F$1,ROW(Pendencias!$B$2:$B$209)-1),ROW(A53)),4),"")} | Z50: {=IFERROR(INDEX(Pendencias!$A$2:$O$209,SMALL(IF(Pendencias!$B$2:$B$209=$F$1,ROW(Pendencias!$B$2:$B$209)-1),ROW(A53)),7),"")} | AA50: {=IF(IFERROR(INDEX(Pendencias!$A$2:$O$209,SMALL(IF(Pendencias!$B$2:$B$209=$F$1,ROW(Pendencias!$B$2:$B$209)-1),ROW(A53)),9),"")=0,"",IFERROR(INDEX(Pendencias!$A$2:$O$209,SMALL(IF(Pendencias!$B$2:$B$209=$F$1,ROW(Pendencias!$B$2:$B$209)-1),ROW(A53)),9),""))}
A51: Terceiros (nomes e empresa): | W51: {=IFERROR(INDEX(Pendencias!$A$2:$O$209,SMALL(IF(Pendencias!$B$2:$B$209=$F$1,ROW(Pendencias!$B$2:$B$209)-1),ROW(A54)),1),"")} | X51: {=IFERROR(INDEX(Pendencias!$A$2:$O$209,SMALL(IF(Pendencias!$B$2:$B$209=$F$1,ROW(Pendencias!$B$2:$B$209)-1),ROW(A54)),3),"")} | Y51: {=IFERROR(INDEX(Pendencias!$A$2:$O$209,SMALL(IF(Pendencias!$B$2:$B$209=$F$1,ROW(Pendencias!$B$2:$B$209)-1),ROW(A54)),4),"")} | Z51: {=IFERROR(INDEX(Pendencias!$A$2:$O$209,SMALL(IF(Pendencias!$B$2:$B$209=$F$1,ROW(Pendencias!$B$2:$B$209)-1),ROW(A54)),7),"")} | AA51: {=IF(IFERROR(INDEX(Pendencias!$A$2:$O$209,SMALL(IF(Pendencias!$B$2:$B$209=$F$1,ROW(Pendencias!$B$2:$B$209)-1),ROW(A54)),9),"")=0,"",IFERROR(INDEX(Pendencias!$A$2:$O$209,SMALL(IF(Pendencias!$B$2:$B$209=$F$1,ROW(Pendencias!$B$2:$B$209)-1),ROW(A54)),9),""))}
A52: CheckList Procedimentos e Ficha de Campo | G52: =F1 -> HMPDMCTDPIER1 | W52: {=IFERROR(INDEX(Pendencias!$A$2:$O$209,SMALL(IF(Pendencias!$B$2:$B$209=$F$1,ROW(Pendencias!$B$2:$B$209)-1),ROW(A55)),1),"")} | X52: {=IFERROR(INDEX(Pendencias!$A$2:$O$209,SMALL(IF(Pendencias!$B$2:$B$209=$F$1,ROW(Pendencias!$B$2:$B$209)-1),ROW(A55)),3),"")} | Y52: {=IFERROR(INDEX(Pendencias!$A$2:$O$209,SMALL(IF(Pendencias!$B$2:$B$209=$F$1,ROW(Pendencias!$B$2:$B$209)-1),ROW(A55)),4),"")} | Z52: {=IFERROR(INDEX(Pendencias!$A$2:$O$209,SMALL(IF(Pendencias!$B$2:$B$209=$F$1,ROW(Pendencias!$B$2:$B$209)-1),ROW(A55)),7),"")} | AA52: {=IF(IFERROR(INDEX(Pendencias!$A$2:$O$209,SMALL(IF(Pendencias!$B$2:$B$209=$F$1,ROW(Pendencias!$B$2:$B$209)-1),ROW(A55)),9),"")=0,"",IFERROR(INDEX(Pendencias!$A$2:$O$209,SMALL(IF(Pendencias!$B$2:$B$209=$F$1,ROW(Pendencias!$B$2:$B$209)-1),ROW(A55)),9),""))}
W53: {=IFERROR(INDEX(Pendencias!$A$2:$O$209,SMALL(IF(Pendencias!$B$2:$B$209=$F$1,ROW(Pendencias!$B$2:$B$209)-1),ROW(A56)),1),"")} | X53: {=IFERROR(INDEX(Pendencias!$A$2:$O$209,SMALL(IF(Pendencias!$B$2:$B$209=$F$1,ROW(Pendencias!$B$2:$B$209)-1),ROW(A56)),3),"")} | Y53: {=IFERROR(INDEX(Pendencias!$A$2:$O$209,SMALL(IF(Pendencias!$B$2:$B$209=$F$1,ROW(Pendencias!$B$2:$B$209)-1),ROW(A56)),4),"")} | Z53: {=IFERROR(INDEX(Pendencias!$A$2:$O$209,SMALL(IF(Pendencias!$B$2:$B$209=$F$1,ROW(Pendencias!$B$2:$B$209)-1),ROW(A56)),7),"")} | AA53: {=IF(IFERROR(INDEX(Pendencias!$A$2:$O$209,SMALL(IF(Pendencias!$B$2:$B$209=$F$1,ROW(Pendencias!$B$2:$B$209)-1),ROW(A56)),9),"")=0,"",IFERROR(INDEX(Pendencias!$A$2:$O$209,SMALL(IF(Pendencias!$B$2:$B$209=$F$1,ROW(Pendencias!$B$2:$B$209)-1),ROW(A56)),9),""))}
W54: {=IFERROR(INDEX(Pendencias!$A$2:$O$209,SMALL(IF(Pendencias!$B$2:$B$209=$F$1,ROW(Pendencias!$B$2:$B$209)-1),ROW(A57)),1),"")} | X54: {=IFERROR(INDEX(Pendencias!$A$2:$O$209,SMALL(IF(Pendencias!$B$2:$B$209=$F$1,ROW(Pendencias!$B$2:$B$209)-1),ROW(A57)),3),"")} | Y54: {=IFERROR(INDEX(Pendencias!$A$2:$O$209,SMALL(IF(Pendencias!$B$2:$B$209=$F$1,ROW(Pendencias!$B$2:$B$209)-1),ROW(A57)),4),"")} | Z54: {=IFERROR(INDEX(Pendencias!$A$2:$O$209,SMALL(IF(Pendencias!$B$2:$B$209=$F$1,ROW(Pendencias!$B$2:$B$209)-1),ROW(A57)),7),"")} | AA54: {=IF(IFERROR(INDEX(Pendencias!$A$2:$O$209,SMALL(IF(Pendencias!$B$2:$B$209=$F$1,ROW(Pendencias!$B$2:$B$209)-1),ROW(A57)),9),"")=0,"",IFERROR(INDEX(Pendencias!$A$2:$O$209,SMALL(IF(Pendencias!$B$2:$B$209=$F$1,ROW(Pendencias!$B$2:$B$209)-1),ROW(A57)),9),""))}
W55: {=IFERROR(INDEX(Pendencias!$A$2:$O$209,SMALL(IF(Pendencias!$B$2:$B$209=$F$1,ROW(Pendencias!$B$2:$B$209)-1),ROW(A58)),1),"")} | X55: {=IFERROR(INDEX(Pendencias!$A$2:$O$209,SMALL(IF(Pendencias!$B$2:$B$209=$F$1,ROW(Pendencias!$B$2:$B$209)-1),ROW(A58)),3),"")} | Y55: {=IFERROR(INDEX(Pendencias!$A$2:$O$209,SMALL(IF(Pendencias!$B$2:$B$209=$F$1,ROW(Pendencias!$B$2:$B$209)-1),ROW(A58)),4),"")} | Z55: {=IFERROR(INDEX(Pendencias!$A$2:$O$209,SMALL(IF(Pendencias!$B$2:$B$209=$F$1,ROW(Pendencias!$B$2:$B$209)-1),ROW(A58)),7),"")} | AA55: {=IF(IFERROR(INDEX(Pendencias!$A$2:$O$209,SMALL(IF(Pendencias!$B$2:$B$209=$F$1,ROW(Pendencias!$B$2:$B$209)-1),ROW(A58)),9),"")=0,"",IFERROR(INDEX(Pendencias!$A$2:$O$209,SMALL(IF(Pendencias!$B$2:$B$209=$F$1,ROW(Pendencias!$B$2:$B$209)-1),ROW(A58)),9),""))}
A56: Checklist de Fotografias Obrigatórias | W56: {=IFERROR(INDEX(Pendencias!$A$2:$O$209,SMALL(IF(Pendencias!$B$2:$B$209=$F$1,ROW(Pendencias!$B$2:$B$209)-1),ROW(A59)),1),"")} | X56: {=IFERROR(INDEX(Pendencias!$A$2:$O$209,SMALL(IF(Pendencias!$B$2:$B$209=$F$1,ROW(Pendencias!$B$2:$B$209)-1),ROW(A59)),3),"")} | Y56: {=IFERROR(INDEX(Pendencias!$A$2:$O$209,SMALL(IF(Pendencias!$B$2:$B$209=$F$1,ROW(Pendencias!$B$2:$B$209)-1),ROW(A59)),4),"")} | Z56: {=IFERROR(INDEX(Pendencias!$A$2:$O$209,SMALL(IF(Pendencias!$B$2:$B$209=$F$1,ROW(Pendencias!$B$2:$B$209)-1),ROW(A59)),7),"")} | AA56: {=IF(IFERROR(INDEX(Pendencias!$A$2:$O$209,SMALL(IF(Pendencias!$B$2:$B$209=$F$1,ROW(Pendencias!$B$2:$B$209)-1),ROW(A59)),9),"")=0,"",IFERROR(INDEX(Pendencias!$A$2:$O$209,SMALL(IF(Pendencias!$B$2:$B$209=$F$1,ROW(Pendencias!$B$2:$B$209)-1),ROW(A59)),9),""))}
A57: Embarcação | D57: Material Embarcado | G57: Chegando / Saindo da Estação | W57: {=IFERROR(INDEX(Pendencias!$A$2:$O$209,SMALL(IF(Pendencias!$B$2:$B$209=$F$1,ROW(Pendencias!$B$2:$B$209)-1),ROW(A60)),1),"")} | X57: {=IFERROR(INDEX(Pendencias!$A$2:$O$209,SMALL(IF(Pendencias!$B$2:$B$209=$F$1,ROW(Pendencias!$B$2:$B$209)-1),ROW(A60)),3),"")} | Y57: {=IFERROR(INDEX(Pendencias!$A$2:$O$209,SMALL(IF(Pendencias!$B$2:$B$209=$F$1,ROW(Pendencias!$B$2:$B$209)-1),ROW(A60)),4),"")} | Z57: {=IFERROR(INDEX(Pendencias!$A$2:$O$209,SMALL(IF(Pendencias!$B$2:$B$209=$F$1,ROW(Pendencias!$B$2:$B$209)-1),ROW(A60)),7),"")} | AA57: {=IF(IFERROR(INDEX(Pendencias!$A$2:$O$209,SMALL(IF(Pendencias!$B$2:$B$209=$F$1,ROW(Pendencias!$B$2:$B$209)-1),ROW(A60)),9),"")=0,"",IFERROR(INDEX(Pendencias!$A$2:$O$209,SMALL(IF(Pendencias!$B$2:$B$209=$F$1,ROW(Pendencias!$B$2:$B$209)-1),ROW(A60)),9),""))}
A58: Caixa dentro / fora | D58: Mergulhador | G58: ADCP antes / após limpeza | W58: {=IFERROR(INDEX(Pendencias!$A$2:$O$209,SMALL(IF(Pendencias!$B$2:$B$209=$F$1,ROW(Pendencias!$B$2:$B$209)-1),ROW(A61)),1),"")} | X58: {=IFERROR(INDEX(Pendencias!$A$2:$O$209,SMALL(IF(Pendencias!$B$2:$B$209=$F$1,ROW(Pendencias!$B$2:$B$209)-1),ROW(A61)),3),"")} | Y58: {=IFERROR(INDEX(Pendencias!$A$2:$O$209,SMALL(IF(Pendencias!$B$2:$B$209=$F$1,ROW(Pendencias!$B$2:$B$209)-1),ROW(A61)),4),"")} | Z58: {=IFERROR(INDEX(Pendencias!$A$2:$O$209,SMALL(IF(Pendencias!$B$2:$B$209=$F$1,ROW(Pendencias!$B$2:$B$209)-1),ROW(A61)),7),"")} | AA58: {=IF(IFERROR(INDEX(Pendencias!$A$2:$O$209,SMALL(IF(Pendencias!$B$2:$B$209=$F$1,ROW(Pendencias!$B$2:$B$209)-1),ROW(A61)),9),"")=0,"",IFERROR(INDEX(Pendencias!$A$2:$O$209,SMALL(IF(Pendencias!$B$2:$B$209=$F$1,ROW(Pendencias!$B$2:$B$209)-1),ROW(A61)),9),""))}
A59: Conector ADCP | D59: Estruturas e suportes | G59: Marégrafo | I59: Boia | W59: {=IFERROR(INDEX(Pendencias!$A$2:$O$209,SMALL(IF(Pendencias!$B$2:$B$209=$F$1,ROW(Pendencias!$B$2:$B$209)-1),ROW(A62)),1),"")} | X59: {=IFERROR(INDEX(Pendencias!$A$2:$O$209,SMALL(IF(Pendencias!$B$2:$B$209=$F$1,ROW(Pendencias!$B$2:$B$209)-1),ROW(A62)),3),"")} | Y59: {=IFERROR(INDEX(Pendencias!$A$2:$O$209,SMALL(IF(Pendencias!$B$2:$B$209=$F$1,ROW(Pendencias!$B$2:$B$209)-1),ROW(A62)),4),"")} | Z59: {=IFERROR(INDEX(Pendencias!$A$2:$O$209,SMALL(IF(Pendencias!$B$2:$B$209=$F$1,ROW(Pendencias!$B$2:$B$209)-1),ROW(A62)),7),"")} | AA59: {=IF(IFERROR(INDEX(Pendencias!$A$2:$O$209,SMALL(IF(Pendencias!$B$2:$B$209=$F$1,ROW(Pendencias!$B$2:$B$209)-1),ROW(A62)),9),"")=0,"",IFERROR(INDEX(Pendencias!$A$2:$O$209,SMALL(IF(Pendencias!$B$2:$B$209=$F$1,ROW(Pendencias!$B$2:$B$209)-1),ROW(A62)),9),""))}
A60: Est. Meteorológica | D60: Painel Solar | G60: Fotos para Marketing | W60: {=IFERROR(INDEX(Pendencias!$A$2:$O$209,SMALL(IF(Pendencias!$B$2:$B$209=$F$1,ROW(Pendencias!$B$2:$B$209)-1),ROW(A63)),1),"")} | X60: {=IFERROR(INDEX(Pendencias!$A$2:$O$209,SMALL(IF(Pendencias!$B$2:$B$209=$F$1,ROW(Pendencias!$B$2:$B$209)-1),ROW(A63)),3),"")} | Y60: {=IFERROR(INDEX(Pendencias!$A$2:$O$209,SMALL(IF(Pendencias!$B$2:$B$209=$F$1,ROW(Pendencias!$B$2:$B$209)-1),ROW(A63)),4),"")} | Z60: {=IFERROR(INDEX(Pendencias!$A$2:$O$209,SMALL(IF(Pendencias!$B$2:$B$209=$F$1,ROW(Pendencias!$B$2:$B$209)-1),ROW(A63)),7),"")} | AA60: {=IF(IFERROR(INDEX(Pendencias!$A$2:$O$209,SMALL(IF(Pendencias!$B$2:$B$209=$F$1,ROW(Pendencias!$B$2:$B$209)-1),ROW(A63)),9),"")=0,"",IFERROR(INDEX(Pendencias!$A$2:$O$209,SMALL(IF(Pendencias!$B$2:$B$209=$F$1,ROW(Pendencias!$B$2:$B$209)-1),ROW(A63)),9),""))}
W61: {=IFERROR(INDEX(Pendencias!$A$2:$O$209,SMALL(IF(Pendencias!$B$2:$B$209=$F$1,ROW(Pendencias!$B$2:$B$209)-1),ROW(A64)),1),"")} | X61: {=IFERROR(INDEX(Pendencias!$A$2:$O$209,SMALL(IF(Pendencias!$B$2:$B$209=$F$1,ROW(Pendencias!$B$2:$B$209)-1),ROW(A64)),3),"")} | Y61: {=IFERROR(INDEX(Pendencias!$A$2:$O$209,SMALL(IF(Pendencias!$B$2:$B$209=$F$1,ROW(Pendencias!$B$2:$B$209)-1),ROW(A64)),4),"")} | Z61: {=IFERROR(INDEX(Pendencias!$A$2:$O$209,SMALL(IF(Pendencias!$B$2:$B$209=$F$1,ROW(Pendencias!$B$2:$B$209)-1),ROW(A64)),7),"")} | AA61: {=IF(IFERROR(INDEX(Pendencias!$A$2:$O$209,SMALL(IF(Pendencias!$B$2:$B$209=$F$1,ROW(Pendencias!$B$2:$B$209)-1),ROW(A64)),9),"")=0,"",IFERROR(INDEX(Pendencias!$A$2:$O$209,SMALL(IF(Pendencias!$B$2:$B$209=$F$1,ROW(Pendencias!$B$2:$B$209)-1),ROW(A64)),9),""))}
A62: Conservação das Estruturas (OK = ótimo estado; Observação = foi observada alguma anomalia/observação; Foi Subst = foi substituído). Descrever as observações/anomalias abaixo. | W62: {=IFERROR(INDEX(Pendencias!$A$2:$O$209,SMALL(IF(Pendencias!$B$2:$B$209=$F$1,ROW(Pendencias!$B$2:$B$209)-1),ROW(A65)),1),"")} | X62: {=IFERROR(INDEX(Pendencias!$A$2:$O$209,SMALL(IF(Pendencias!$B$2:$B$209=$F$1,ROW(Pendencias!$B$2:$B$209)-1),ROW(A65)),3),"")} | Y62: {=IFERROR(INDEX(Pendencias!$A$2:$O$209,SMALL(IF(Pendencias!$B$2:$B$209=$F$1,ROW(Pendencias!$B$2:$B$209)-1),ROW(A65)),4),"")} | Z62: {=IFERROR(INDEX(Pendencias!$A$2:$O$209,SMALL(IF(Pendencias!$B$2:$B$209=$F$1,ROW(Pendencias!$B$2:$B$209)-1),ROW(A65)),7),"")} | AA62: {=IF(IFERROR(INDEX(Pendencias!$A$2:$O$209,SMALL(IF(Pendencias!$B$2:$B$209=$F$1,ROW(Pendencias!$B$2:$B$209)-1),ROW(A65)),9),"")=0,"",IFERROR(INDEX(Pendencias!$A$2:$O$209,SMALL(IF(Pendencias!$B$2:$B$209=$F$1,ROW(Pendencias!$B$2:$B$209)-1),ROW(A65)),9),""))}
W63: {=IFERROR(INDEX(Pendencias!$A$2:$O$209,SMALL(IF(Pendencias!$B$2:$B$209=$F$1,ROW(Pendencias!$B$2:$B$209)-1),ROW(A66)),1),"")} | X63: {=IFERROR(INDEX(Pendencias!$A$2:$O$209,SMALL(IF(Pendencias!$B$2:$B$209=$F$1,ROW(Pendencias!$B$2:$B$209)-1),ROW(A66)),3),"")} | Y63: {=IFERROR(INDEX(Pendencias!$A$2:$O$209,SMALL(IF(Pendencias!$B$2:$B$209=$F$1,ROW(Pendencias!$B$2:$B$209)-1),ROW(A66)),4),"")} | Z63: {=IFERROR(INDEX(Pendencias!$A$2:$O$209,SMALL(IF(Pendencias!$B$2:$B$209=$F$1,ROW(Pendencias!$B$2:$B$209)-1),ROW(A66)),7),"")} | AA63: {=IF(IFERROR(INDEX(Pendencias!$A$2:$O$209,SMALL(IF(Pendencias!$B$2:$B$209=$F$1,ROW(Pendencias!$B$2:$B$209)-1),ROW(A66)),9),"")=0,"",IFERROR(INDEX(Pendencias!$A$2:$O$209,SMALL(IF(Pendencias!$B$2:$B$209=$F$1,ROW(Pendencias!$B$2:$B$209)-1),ROW(A66)),9),""))}
A64: ADCP [Estação contém ADCP: SIM ( ) NÃO (x ) DEIXAR EM BRANCO O QUE NÃO INSPECIONADO! | W64: {=IFERROR(INDEX(Pendencias!$A$2:$O$209,SMALL(IF(Pendencias!$B$2:$B$209=$F$1,ROW(Pendencias!$B$2:$B$209)-1),ROW(A67)),1),"")} | X64: {=IFERROR(INDEX(Pendencias!$A$2:$O$209,SMALL(IF(Pendencias!$B$2:$B$209=$F$1,ROW(Pendencias!$B$2:$B$209)-1),ROW(A67)),3),"")} | Y64: {=IFERROR(INDEX(Pendencias!$A$2:$O$209,SMALL(IF(Pendencias!$B$2:$B$209=$F$1,ROW(Pendencias!$B$2:$B$209)-1),ROW(A67)),4),"")} | Z64: {=IFERROR(INDEX(Pendencias!$A$2:$O$209,SMALL(IF(Pendencias!$B$2:$B$209=$F$1,ROW(Pendencias!$B$2:$B$209)-1),ROW(A67)),7),"")} | AA64: {=IF(IFERROR(INDEX(Pendencias!$A$2:$O$209,SMALL(IF(Pendencias!$B$2:$B$209=$F$1,ROW(Pendencias!$B$2:$B$209)-1),ROW(A67)),9),"")=0,"",IFERROR(INDEX(Pendencias!$A$2:$O$209,SMALL(IF(Pendencias!$B$2:$B$209=$F$1,ROW(Pendencias!$B$2:$B$209)-1),ROW(A67)),9),""))}
A65: ADCP | C65: OK ( ) Observação ( ) Foi Subst ( ) | F65: Anodos ADCP | W65: {=IFERROR(INDEX(Pendencias!$A$2:$O$209,SMALL(IF(Pendencias!$B$2:$B$209=$F$1,ROW(Pendencias!$B$2:$B$209)-1),ROW(A68)),1),"")} | X65: {=IFERROR(INDEX(Pendencias!$A$2:$O$209,SMALL(IF(Pendencias!$B$2:$B$209=$F$1,ROW(Pendencias!$B$2:$B$209)-1),ROW(A68)),3),"")} | Y65: {=IFERROR(INDEX(Pendencias!$A$2:$O$209,SMALL(IF(Pendencias!$B$2:$B$209=$F$1,ROW(Pendencias!$B$2:$B$209)-1),ROW(A68)),4),"")} | Z65: {=IFERROR(INDEX(Pendencias!$A$2:$O$209,SMALL(IF(Pendencias!$B$2:$B$209=$F$1,ROW(Pendencias!$B$2:$B$209)-1),ROW(A68)),7),"")} | AA65: {=IF(IFERROR(INDEX(Pendencias!$A$2:$O$209,SMALL(IF(Pendencias!$B$2:$B$209=$F$1,ROW(Pendencias!$B$2:$B$209)-1),ROW(A68)),9),"")=0,"",IFERROR(INDEX(Pendencias!$A$2:$O$209,SMALL(IF(Pendencias!$B$2:$B$209=$F$1,ROW(Pendencias!$B$2:$B$209)-1),ROW(A68)),9),""))}
A66: Suporte ADCP | C66: OK ( ) Observação ( ) Foi Subst ( ) | F66: Transdutores ADCP | H66: OK ( ) Observação ( ) Foi Subst ( ) | W66: {=IFERROR(INDEX(Pendencias!$A$2:$O$209,SMALL(IF(Pendencias!$B$2:$B$209=$F$1,ROW(Pendencias!$B$2:$B$209)-1),ROW(A69)),1),"")} | X66: {=IFERROR(INDEX(Pendencias!$A$2:$O$209,SMALL(IF(Pendencias!$B$2:$B$209=$F$1,ROW(Pendencias!$B$2:$B$209)-1),ROW(A69)),3),"")} | Y66: {=IFERROR(INDEX(Pendencias!$A$2:$O$209,SMALL(IF(Pendencias!$B$2:$B$209=$F$1,ROW(Pendencias!$B$2:$B$209)-1),ROW(A69)),4),"")} | Z66: {=IFERROR(INDEX(Pendencias!$A$2:$O$209,SMALL(IF(Pendencias!$B$2:$B$209=$F$1,ROW(Pendencias!$B$2:$B$209)-1),ROW(A69)),7),"")} | AA66: {=IF(IFERROR(INDEX(Pendencias!$A$2:$O$209,SMALL(IF(Pendencias!$B$2:$B$209=$F$1,ROW(Pendencias!$B$2:$B$209)-1),ROW(A69)),9),"")=0,"",IFERROR(INDEX(Pendencias!$A$2:$O$209,SMALL(IF(Pendencias!$B$2:$B$209=$F$1,ROW(Pendencias!$B$2:$B$209)-1),ROW(A69)),9),""))}
A67: Conector Cabo | C67: OK ( ) Observação ( ) Foi Subst ( ) | F67: Cabo ADCP | H67: OK ( ) Observação ( ) Foi Subst ( ) | W67: {=IFERROR(INDEX(Pendencias!$A$2:$O$209,SMALL(IF(Pendencias!$B$2:$B$209=$F$1,ROW(Pendencias!$B$2:$B$209)-1),ROW(A70)),1),"")} | X67: {=IFERROR(INDEX(Pendencias!$A$2:$O$209,SMALL(IF(Pendencias!$B$2:$B$209=$F$1,ROW(Pendencias!$B$2:$B$209)-1),ROW(A70)),3),"")} | Y67: {=IFERROR(INDEX(Pendencias!$A$2:$O$209,SMALL(IF(Pendencias!$B$2:$B$209=$F$1,ROW(Pendencias!$B$2:$B$209)-1),ROW(A70)),4),"")} | Z67: {=IFERROR(INDEX(Pendencias!$A$2:$O$209,SMALL(IF(Pendencias!$B$2:$B$209=$F$1,ROW(Pendencias!$B$2:$B$209)-1),ROW(A70)),7),"")} | AA67: {=IF(IFERROR(INDEX(Pendencias!$A$2:$O$209,SMALL(IF(Pendencias!$B$2:$B$209=$F$1,ROW(Pendencias!$B$2:$B$209)-1),ROW(A70)),9),"")=0,"",IFERROR(INDEX(Pendencias!$A$2:$O$209,SMALL(IF(Pendencias!$B$2:$B$209=$F$1,ROW(Pendencias!$B$2:$B$209)-1),ROW(A70)),9),""))}
A68: Incrustação | C68: Muita ( ) Média ( ) Pouca ( ) | W68: {=IFERROR(INDEX(Pendencias!$A$2:$O$209,SMALL(IF(Pendencias!$B$2:$B$209=$F$1,ROW(Pendencias!$B$2:$B$209)-1),ROW(A71)),1),"")} | X68: {=IFERROR(INDEX(Pendencias!$A$2:$O$209,SMALL(IF(Pendencias!$B$2:$B$209=$F$1,ROW(Pendencias!$B$2:$B$209)-1),ROW(A71)),3),"")} | Y68: {=IFERROR(INDEX(Pendencias!$A$2:$O$209,SMALL(IF(Pendencias!$B$2:$B$209=$F$1,ROW(Pendencias!$B$2:$B$209)-1),ROW(A71)),4),"")} | Z68: {=IFERROR(INDEX(Pendencias!$A$2:$O$209,SMALL(IF(Pendencias!$B$2:$B$209=$F$1,ROW(Pendencias!$B$2:$B$209)-1),ROW(A71)),7),"")} | AA68: {=IF(IFERROR(INDEX(Pendencias!$A$2:$O$209,SMALL(IF(Pendencias!$B$2:$B$209=$F$1,ROW(Pendencias!$B$2:$B$209)-1),ROW(A71)),9),"")=0,"",IFERROR(INDEX(Pendencias!$A$2:$O$209,SMALL(IF(Pendencias!$B$2:$B$209=$F$1,ROW(Pendencias!$B$2:$B$209)-1),ROW(A71)),9),""))}
W69: {=IFERROR(INDEX(Pendencias!$A$2:$O$209,SMALL(IF(Pendencias!$B$2:$B$209=$F$1,ROW(Pendencias!$B$2:$B$209)-1),ROW(A72)),1),"")} | X69: {=IFERROR(INDEX(Pendencias!$A$2:$O$209,SMALL(IF(Pendencias!$B$2:$B$209=$F$1,ROW(Pendencias!$B$2:$B$209)-1),ROW(A72)),3),"")} | Y69: {=IFERROR(INDEX(Pendencias!$A$2:$O$209,SMALL(IF(Pendencias!$B$2:$B$209=$F$1,ROW(Pendencias!$B$2:$B$209)-1),ROW(A72)),4),"")} | Z69: {=IFERROR(INDEX(Pendencias!$A$2:$O$209,SMALL(IF(Pendencias!$B$2:$B$209=$F$1,ROW(Pendencias!$B$2:$B$209)-1),ROW(A72)),7),"")} | AA69: {=IF(IFERROR(INDEX(Pendencias!$A$2:$O$209,SMALL(IF(Pendencias!$B$2:$B$209=$F$1,ROW(Pendencias!$B$2:$B$209)-1),ROW(A72)),9),"")=0,"",IFERROR(INDEX(Pendencias!$A$2:$O$209,SMALL(IF(Pendencias!$B$2:$B$209=$F$1,ROW(Pendencias!$B$2:$B$209)-1),ROW(A72)),9),""))}
A70: Marégrafo [Estação contém Marégrafo: SIM ( ) NÃO ( x )] DEIXAR EM BRANCO O QUE NÃO INSPECIONADO! | W70: {=IFERROR(INDEX(Pendencias!$A$2:$O$209,SMALL(IF(Pendencias!$B$2:$B$209=$F$1,ROW(Pendencias!$B$2:$B$209)-1),ROW(A73)),1),"")} | X70: {=IFERROR(INDEX(Pendencias!$A$2:$O$209,SMALL(IF(Pendencias!$B$2:$B$209=$F$1,ROW(Pendencias!$B$2:$B$209)-1),ROW(A73)),3),"")} | Y70: {=IFERROR(INDEX(Pendencias!$A$2:$O$209,SMALL(IF(Pendencias!$B$2:$B$209=$F$1,ROW(Pendencias!$B$2:$B$209)-1),ROW(A73)),4),"")} | Z70: {=IFERROR(INDEX(Pendencias!$A$2:$O$209,SMALL(IF(Pendencias!$B$2:$B$209=$F$1,ROW(Pendencias!$B$2:$B$209)-1),ROW(A73)),7),"")} | AA70: {=IF(IFERROR(INDEX(Pendencias!$A$2:$O$209,SMALL(IF(Pendencias!$B$2:$B$209=$F$1,ROW(Pendencias!$B$2:$B$209)-1),ROW(A73)),9),"")=0,"",IFERROR(INDEX(Pendencias!$A$2:$O$209,SMALL(IF(Pendencias!$B$2:$B$209=$F$1,ROW(Pendencias!$B$2:$B$209)-1),ROW(A73)),9),""))}
A71: Marégrafo | C71: OK ( ) Observação ( ) Foi Subst ( ) | F71: Suporte Marégrafo | H71: OK ( ) Observação ( ) Foi Subst ( ) | W71: {=IFERROR(INDEX(Pendencias!$A$2:$O$209,SMALL(IF(Pendencias!$B$2:$B$209=$F$1,ROW(Pendencias!$B$2:$B$209)-1),ROW(A74)),1),"")} | X71: {=IFERROR(INDEX(Pendencias!$A$2:$O$209,SMALL(IF(Pendencias!$B$2:$B$209=$F$1,ROW(Pendencias!$B$2:$B$209)-1),ROW(A74)),3),"")} | Y71: {=IFERROR(INDEX(Pendencias!$A$2:$O$209,SMALL(IF(Pendencias!$B$2:$B$209=$F$1,ROW(Pendencias!$B$2:$B$209)-1),ROW(A74)),4),"")} | Z71: {=IFERROR(INDEX(Pendencias!$A$2:$O$209,SMALL(IF(Pendencias!$B$2:$B$209=$F$1,ROW(Pendencias!$B$2:$B$209)-1),ROW(A74)),7),"")} | AA71: {=IF(IFERROR(INDEX(Pendencias!$A$2:$O$209,SMALL(IF(Pendencias!$B$2:$B$209=$F$1,ROW(Pendencias!$B$2:$B$209)-1),ROW(A74)),9),"")=0,"",IFERROR(INDEX(Pendencias!$A$2:$O$209,SMALL(IF(Pendencias!$B$2:$B$209=$F$1,ROW(Pendencias!$B$2:$B$209)-1),ROW(A74)),9),""))}
F72: Régua de Maré: | H72: OK ( ) Observação ( ) Foi Subst ( ) | W72: {=IFERROR(INDEX(Pendencias!$A$2:$O$209,SMALL(IF(Pendencias!$B$2:$B$209=$F$1,ROW(Pendencias!$B$2:$B$209)-1),ROW(A75)),1),"")} | X72: {=IFERROR(INDEX(Pendencias!$A$2:$O$209,SMALL(IF(Pendencias!$B$2:$B$209=$F$1,ROW(Pendencias!$B$2:$B$209)-1),ROW(A75)),3),"")} | Y72: {=IFERROR(INDEX(Pendencias!$A$2:$O$209,SMALL(IF(Pendencias!$B$2:$B$209=$F$1,ROW(Pendencias!$B$2:$B$209)-1),ROW(A75)),4),"")} | Z72: {=IFERROR(INDEX(Pendencias!$A$2:$O$209,SMALL(IF(Pendencias!$B$2:$B$209=$F$1,ROW(Pendencias!$B$2:$B$209)-1),ROW(A75)),7),"")} | AA72: {=IF(IFERROR(INDEX(Pendencias!$A$2:$O$209,SMALL(IF(Pendencias!$B$2:$B$209=$F$1,ROW(Pendencias!$B$2:$B$209)-1),ROW(A75)),9),"")=0,"",IFERROR(INDEX(Pendencias!$A$2:$O$209,SMALL(IF(Pendencias!$B$2:$B$209=$F$1,ROW(Pendencias!$B$2:$B$209)-1),ROW(A75)),9),""))}
W73: {=IFERROR(INDEX(Pendencias!$A$2:$O$209,SMALL(IF(Pendencias!$B$2:$B$209=$F$1,ROW(Pendencias!$B$2:$B$209)-1),ROW(A76)),1),"")} | X73: {=IFERROR(INDEX(Pendencias!$A$2:$O$209,SMALL(IF(Pendencias!$B$2:$B$209=$F$1,ROW(Pendencias!$B$2:$B$209)-1),ROW(A76)),3),"")} | Y73: {=IFERROR(INDEX(Pendencias!$A$2:$O$209,SMALL(IF(Pendencias!$B$2:$B$209=$F$1,ROW(Pendencias!$B$2:$B$209)-1),ROW(A76)),4),"")} | Z73: {=IFERROR(INDEX(Pendencias!$A$2:$O$209,SMALL(IF(Pendencias!$B$2:$B$209=$F$1,ROW(Pendencias!$B$2:$B$209)-1),ROW(A76)),7),"")} | AA73: {=IF(IFERROR(INDEX(Pendencias!$A$2:$O$209,SMALL(IF(Pendencias!$B$2:$B$209=$F$1,ROW(Pendencias!$B$2:$B$209)-1),ROW(A76)),9),"")=0,"",IFERROR(INDEX(Pendencias!$A$2:$O$209,SMALL(IF(Pendencias!$B$2:$B$209=$F$1,ROW(Pendencias!$B$2:$B$209)-1),ROW(A76)),9),""))}
A74: Anemômetro [Estação contém anemômetro: SIM ( )NÃO ( x )] DEIXAR EM BRANCO O QUE NÃO INSPECIONADO! | W74: {=IFERROR(INDEX(Pendencias!$A$2:$O$209,SMALL(IF(Pendencias!$B$2:$B$209=$F$1,ROW(Pendencias!$B$2:$B$209)-1),ROW(A77)),1),"")} | X74: {=IFERROR(INDEX(Pendencias!$A$2:$O$209,SMALL(IF(Pendencias!$B$2:$B$209=$F$1,ROW(Pendencias!$B$2:$B$209)-1),ROW(A77)),3),"")} | Y74: {=IFERROR(INDEX(Pendencias!$A$2:$O$209,SMALL(IF(Pendencias!$B$2:$B$209=$F$1,ROW(Pendencias!$B$2:$B$209)-1),ROW(A77)),4),"")} | Z74: {=IFERROR(INDEX(Pendencias!$A$2:$O$209,SMALL(IF(Pendencias!$B$2:$B$209=$F$1,ROW(Pendencias!$B$2:$B$209)-1),ROW(A77)),7),"")} | AA74: {=IF(IFERROR(INDEX(Pendencias!$A$2:$O$209,SMALL(IF(Pendencias!$B$2:$B$209=$F$1,ROW(Pendencias!$B$2:$B$209)-1),ROW(A77)),9),"")=0,"",IFERROR(INDEX(Pendencias!$A$2:$O$209,SMALL(IF(Pendencias!$B$2:$B$209=$F$1,ROW(Pendencias!$B$2:$B$209)-1),ROW(A77)),9),""))}
A75: Sensor de Vento | C75: OK ( ) Observação ( ) Foi Subst ( ) | F75: Suporte do sensor | H75: OK ( ) Observação ( ) Foi Subst ( ) | W75: {=IFERROR(INDEX(Pendencias!$A$2:$O$209,SMALL(IF(Pendencias!$B$2:$B$209=$F$1,ROW(Pendencias!$B$2:$B$209)-1),ROW(A78)),1),"")} | X75: {=IFERROR(INDEX(Pendencias!$A$2:$O$209,SMALL(IF(Pendencias!$B$2:$B$209=$F$1,ROW(Pendencias!$B$2:$B$209)-1),ROW(A78)),3),"")} | Y75: {=IFERROR(INDEX(Pendencias!$A$2:$O$209,SMALL(IF(Pendencias!$B$2:$B$209=$F$1,ROW(Pendencias!$B$2:$B$209)-1),ROW(A78)),4),"")} | Z75: {=IFERROR(INDEX(Pendencias!$A$2:$O$209,SMALL(IF(Pendencias!$B$2:$B$209=$F$1,ROW(Pendencias!$B$2:$B$209)-1),ROW(A78)),7),"")} | AA75: {=IF(IFERROR(INDEX(Pendencias!$A$2:$O$209,SMALL(IF(Pendencias!$B$2:$B$209=$F$1,ROW(Pendencias!$B$2:$B$209)-1),ROW(A78)),9),"")=0,"",IFERROR(INDEX(Pendencias!$A$2:$O$209,SMALL(IF(Pendencias!$B$2:$B$209=$F$1,ROW(Pendencias!$B$2:$B$209)-1),ROW(A78)),9),""))}
W76: {=IFERROR(INDEX(Pendencias!$A$2:$O$209,SMALL(IF(Pendencias!$B$2:$B$209=$F$1,ROW(Pendencias!$B$2:$B$209)-1),ROW(A79)),1),"")} | X76: {=IFERROR(INDEX(Pendencias!$A$2:$O$209,SMALL(IF(Pendencias!$B$2:$B$209=$F$1,ROW(Pendencias!$B$2:$B$209)-1),ROW(A79)),3),"")} | Y76: {=IFERROR(INDEX(Pendencias!$A$2:$O$209,SMALL(IF(Pendencias!$B$2:$B$209=$F$1,ROW(Pendencias!$B$2:$B$209)-1),ROW(A79)),4),"")} | Z76: {=IFERROR(INDEX(Pendencias!$A$2:$O$209,SMALL(IF(Pendencias!$B$2:$B$209=$F$1,ROW(Pendencias!$B$2:$B$209)-1),ROW(A79)),7),"")} | AA76: {=IF(IFERROR(INDEX(Pendencias!$A$2:$O$209,SMALL(IF(Pendencias!$B$2:$B$209=$F$1,ROW(Pendencias!$B$2:$B$209)-1),ROW(A79)),9),"")=0,"",IFERROR(INDEX(Pendencias!$A$2:$O$209,SMALL(IF(Pendencias!$B$2:$B$209=$F$1,ROW(Pendencias!$B$2:$B$209)-1),ROW(A79)),9),""))}
A77: Ondógrafo [Estação contém ondógrafo: SIM ( ) NÃO ( x )] DEIXAR EM BRANCO O QUE NÃO INSPECIONADO! | W77: {=IFERROR(INDEX(Pendencias!$A$2:$O$209,SMALL(IF(Pendencias!$B$2:$B$209=$F$1,ROW(Pendencias!$B$2:$B$209)-1),ROW(A80)),1),"")} | X77: {=IFERROR(INDEX(Pendencias!$A$2:$O$209,SMALL(IF(Pendencias!$B$2:$B$209=$F$1,ROW(Pendencias!$B$2:$B$209)-1),ROW(A80)),3),"")} | Y77: {=IFERROR(INDEX(Pendencias!$A$2:$O$209,SMALL(IF(Pendencias!$B$2:$B$209=$F$1,ROW(Pendencias!$B$2:$B$209)-1),ROW(A80)),4),"")} | Z77: {=IFERROR(INDEX(Pendencias!$A$2:$O$209,SMALL(IF(Pendencias!$B$2:$B$209=$F$1,ROW(Pendencias!$B$2:$B$209)-1),ROW(A80)),7),"")} | AA77: {=IF(IFERROR(INDEX(Pendencias!$A$2:$O$209,SMALL(IF(Pendencias!$B$2:$B$209=$F$1,ROW(Pendencias!$B$2:$B$209)-1),ROW(A80)),9),"")=0,"",IFERROR(INDEX(Pendencias!$A$2:$O$209,SMALL(IF(Pendencias!$B$2:$B$209=$F$1,ROW(Pendencias!$B$2:$B$209)-1),ROW(A80)),9),""))}
A78: Ondógrafo | C78: OK ( ) Observação ( ) Foi Subst ( ) | W78: {=IFERROR(INDEX(Pendencias!$A$2:$O$209,SMALL(IF(Pendencias!$B$2:$B$209=$F$1,ROW(Pendencias!$B$2:$B$209)-1),ROW(A81)),1),"")} | X78: {=IFERROR(INDEX(Pendencias!$A$2:$O$209,SMALL(IF(Pendencias!$B$2:$B$209=$F$1,ROW(Pendencias!$B$2:$B$209)-1),ROW(A81)),3),"")} | Y78: {=IFERROR(INDEX(Pendencias!$A$2:$O$209,SMALL(IF(Pendencias!$B$2:$B$209=$F$1,ROW(Pendencias!$B$2:$B$209)-1),ROW(A81)),4),"")} | Z78: {=IFERROR(INDEX(Pendencias!$A$2:$O$209,SMALL(IF(Pendencias!$B$2:$B$209=$F$1,ROW(Pendencias!$B$2:$B$209)-1),ROW(A81)),7),"")} | AA78: {=IF(IFERROR(INDEX(Pendencias!$A$2:$O$209,SMALL(IF(Pendencias!$B$2:$B$209=$F$1,ROW(Pendencias!$B$2:$B$209)-1),ROW(A81)),9),"")=0,"",IFERROR(INDEX(Pendencias!$A$2:$O$209,SMALL(IF(Pendencias!$B$2:$B$209=$F$1,ROW(Pendencias!$B$2:$B$209)-1),ROW(A81)),9),""))}
W79: {=IFERROR(INDEX(Pendencias!$A$2:$O$209,SMALL(IF(Pendencias!$B$2:$B$209=$F$1,ROW(Pendencias!$B$2:$B$209)-1),ROW(A82)),1),"")} | X79: {=IFERROR(INDEX(Pendencias!$A$2:$O$209,SMALL(IF(Pendencias!$B$2:$B$209=$F$1,ROW(Pendencias!$B$2:$B$209)-1),ROW(A82)),3),"")} | Y79: {=IFERROR(INDEX(Pendencias!$A$2:$O$209,SMALL(IF(Pendencias!$B$2:$B$209=$F$1,ROW(Pendencias!$B$2:$B$209)-1),ROW(A82)),4),"")} | Z79: {=IFERROR(INDEX(Pendencias!$A$2:$O$209,SMALL(IF(Pendencias!$B$2:$B$209=$F$1,ROW(Pendencias!$B$2:$B$209)-1),ROW(A82)),7),"")} | AA79: {=IF(IFERROR(INDEX(Pendencias!$A$2:$O$209,SMALL(IF(Pendencias!$B$2:$B$209=$F$1,ROW(Pendencias!$B$2:$B$209)-1),ROW(A82)),9),"")=0,"",IFERROR(INDEX(Pendencias!$A$2:$O$209,SMALL(IF(Pendencias!$B$2:$B$209=$F$1,ROW(Pendencias!$B$2:$B$209)-1),ROW(A82)),9),""))}
A80: Demais estruturas DEIXAR EM BRANCO O QUE NÃO INSPECIONADO! & RISCAR O QUE NÃO SE APLICA! | W80: {=IFERROR(INDEX(Pendencias!$A$2:$O$209,SMALL(IF(Pendencias!$B$2:$B$209=$F$1,ROW(Pendencias!$B$2:$B$209)-1),ROW(A83)),1),"")} | X80: {=IFERROR(INDEX(Pendencias!$A$2:$O$209,SMALL(IF(Pendencias!$B$2:$B$209=$F$1,ROW(Pendencias!$B$2:$B$209)-1),ROW(A83)),3),"")} | Y80: {=IFERROR(INDEX(Pendencias!$A$2:$O$209,SMALL(IF(Pendencias!$B$2:$B$209=$F$1,ROW(Pendencias!$B$2:$B$209)-1),ROW(A83)),4),"")} | Z80: {=IFERROR(INDEX(Pendencias!$A$2:$O$209,SMALL(IF(Pendencias!$B$2:$B$209=$F$1,ROW(Pendencias!$B$2:$B$209)-1),ROW(A83)),7),"")} | AA80: {=IF(IFERROR(INDEX(Pendencias!$A$2:$O$209,SMALL(IF(Pendencias!$B$2:$B$209=$F$1,ROW(Pendencias!$B$2:$B$209)-1),ROW(A83)),9),"")=0,"",IFERROR(INDEX(Pendencias!$A$2:$O$209,SMALL(IF(Pendencias!$B$2:$B$209=$F$1,ROW(Pendencias!$B$2:$B$209)-1),ROW(A83)),9),""))}
A81: Caixa Telemetria | C81: OK ( ) Observação ( ) Foi Subst ( ) | F81: Suporte da Caixa | H81: OK ( ) Observação ( ) Foi Subst ( ) | W81: {=IFERROR(INDEX(Pendencias!$A$2:$O$209,SMALL(IF(Pendencias!$B$2:$B$209=$F$1,ROW(Pendencias!$B$2:$B$209)-1),ROW(A84)),1),"")} | X81: {=IFERROR(INDEX(Pendencias!$A$2:$O$209,SMALL(IF(Pendencias!$B$2:$B$209=$F$1,ROW(Pendencias!$B$2:$B$209)-1),ROW(A84)),3),"")} | Y81: {=IFERROR(INDEX(Pendencias!$A$2:$O$209,SMALL(IF(Pendencias!$B$2:$B$209=$F$1,ROW(Pendencias!$B$2:$B$209)-1),ROW(A84)),4),"")} | Z81: {=IFERROR(INDEX(Pendencias!$A$2:$O$209,SMALL(IF(Pendencias!$B$2:$B$209=$F$1,ROW(Pendencias!$B$2:$B$209)-1),ROW(A84)),7),"")} | AA81: {=IF(IFERROR(INDEX(Pendencias!$A$2:$O$209,SMALL(IF(Pendencias!$B$2:$B$209=$F$1,ROW(Pendencias!$B$2:$B$209)-1),ROW(A84)),9),"")=0,"",IFERROR(INDEX(Pendencias!$A$2:$O$209,SMALL(IF(Pendencias!$B$2:$B$209=$F$1,ROW(Pendencias!$B$2:$B$209)-1),ROW(A84)),9),""))}
A82: Controlador Solar | C82: OK ( ) Observação ( ) Foi Subst ( ) | F82: Painel Solar | H82: OK ( ) Observação ( ) Foi Subst ( ) | W82: {=IFERROR(INDEX(Pendencias!$A$2:$O$209,SMALL(IF(Pendencias!$B$2:$B$209=$F$1,ROW(Pendencias!$B$2:$B$209)-1),ROW(A85)),1),"")} | X82: {=IFERROR(INDEX(Pendencias!$A$2:$O$209,SMALL(IF(Pendencias!$B$2:$B$209=$F$1,ROW(Pendencias!$B$2:$B$209)-1),ROW(A85)),3),"")} | Y82: {=IFERROR(INDEX(Pendencias!$A$2:$O$209,SMALL(IF(Pendencias!$B$2:$B$209=$F$1,ROW(Pendencias!$B$2:$B$209)-1),ROW(A85)),4),"")} | Z82: {=IFERROR(INDEX(Pendencias!$A$2:$O$209,SMALL(IF(Pendencias!$B$2:$B$209=$F$1,ROW(Pendencias!$B$2:$B$209)-1),ROW(A85)),7),"")} | AA82: {=IF(IFERROR(INDEX(Pendencias!$A$2:$O$209,SMALL(IF(Pendencias!$B$2:$B$209=$F$1,ROW(Pendencias!$B$2:$B$209)-1),ROW(A85)),9),"")=0,"",IFERROR(INDEX(Pendencias!$A$2:$O$209,SMALL(IF(Pendencias!$B$2:$B$209=$F$1,ROW(Pendencias!$B$2:$B$209)-1),ROW(A85)),9),""))}
A83: Modem 1 | C83: OK ( ) Observação ( ) Foi Subst ( ) | F83: Suporte Painel Solar | H83: OK ( ) Observação ( ) Foi Subst ( ) | W83: {=IFERROR(INDEX(Pendencias!$A$2:$O$209,SMALL(IF(Pendencias!$B$2:$B$209=$F$1,ROW(Pendencias!$B$2:$B$209)-1),ROW(A86)),1),"")} | X83: {=IFERROR(INDEX(Pendencias!$A$2:$O$209,SMALL(IF(Pendencias!$B$2:$B$209=$F$1,ROW(Pendencias!$B$2:$B$209)-1),ROW(A86)),3),"")} | Y83: {=IFERROR(INDEX(Pendencias!$A$2:$O$209,SMALL(IF(Pendencias!$B$2:$B$209=$F$1,ROW(Pendencias!$B$2:$B$209)-1),ROW(A86)),4),"")} | Z83: {=IFERROR(INDEX(Pendencias!$A$2:$O$209,SMALL(IF(Pendencias!$B$2:$B$209=$F$1,ROW(Pendencias!$B$2:$B$209)-1),ROW(A86)),7),"")} | AA83: {=IF(IFERROR(INDEX(Pendencias!$A$2:$O$209,SMALL(IF(Pendencias!$B$2:$B$209=$F$1,ROW(Pendencias!$B$2:$B$209)-1),ROW(A86)),9),"")=0,"",IFERROR(INDEX(Pendencias!$A$2:$O$209,SMALL(IF(Pendencias!$B$2:$B$209=$F$1,ROW(Pendencias!$B$2:$B$209)-1),ROW(A86)),9),""))}
A84: Modem 2 | C84: OK ( ) Observação ( ) Foi Subst ( ) | F84: Cabo Y | H84: OK ( ) Observação ( ) Foi Subst ( ) | W84: {=IFERROR(INDEX(Pendencias!$A$2:$O$209,SMALL(IF(Pendencias!$B$2:$B$209=$F$1,ROW(Pendencias!$B$2:$B$209)-1),ROW(A87)),1),"")} | X84: {=IFERROR(INDEX(Pendencias!$A$2:$O$209,SMALL(IF(Pendencias!$B$2:$B$209=$F$1,ROW(Pendencias!$B$2:$B$209)-1),ROW(A87)),3),"")} | Y84: {=IFERROR(INDEX(Pendencias!$A$2:$O$209,SMALL(IF(Pendencias!$B$2:$B$209=$F$1,ROW(Pendencias!$B$2:$B$209)-1),ROW(A87)),4),"")} | Z84: {=IFERROR(INDEX(Pendencias!$A$2:$O$209,SMALL(IF(Pendencias!$B$2:$B$209=$F$1,ROW(Pendencias!$B$2:$B$209)-1),ROW(A87)),7),"")} | AA84: {=IF(IFERROR(INDEX(Pendencias!$A$2:$O$209,SMALL(IF(Pendencias!$B$2:$B$209=$F$1,ROW(Pendencias!$B$2:$B$209)-1),ROW(A87)),9),"")=0,"",IFERROR(INDEX(Pendencias!$A$2:$O$209,SMALL(IF(Pendencias!$B$2:$B$209=$F$1,ROW(Pendencias!$B$2:$B$209)-1),ROW(A87)),9),""))}
A85: Torre | C85: ----------------------------------------------- | F85: Fiação | H85: OK ( ) Observação ( ) Foi Subst ( ) | W85: {=IFERROR(INDEX(Pendencias!$A$2:$O$209,SMALL(IF(Pendencias!$B$2:$B$209=$F$1,ROW(Pendencias!$B$2:$B$209)-1),ROW(A88)),1),"")} | X85: {=IFERROR(INDEX(Pendencias!$A$2:$O$209,SMALL(IF(Pendencias!$B$2:$B$209=$F$1,ROW(Pendencias!$B$2:$B$209)-1),ROW(A88)),3),"")} | Y85: {=IFERROR(INDEX(Pendencias!$A$2:$O$209,SMALL(IF(Pendencias!$B$2:$B$209=$F$1,ROW(Pendencias!$B$2:$B$209)-1),ROW(A88)),4),"")} | Z85: {=IFERROR(INDEX(Pendencias!$A$2:$O$209,SMALL(IF(Pendencias!$B$2:$B$209=$F$1,ROW(Pendencias!$B$2:$B$209)-1),ROW(A88)),7),"")} | AA85: {=IF(IFERROR(INDEX(Pendencias!$A$2:$O$209,SMALL(IF(Pendencias!$B$2:$B$209=$F$1,ROW(Pendencias!$B$2:$B$209)-1),ROW(A88)),9),"")=0,"",IFERROR(INDEX(Pendencias!$A$2:$O$209,SMALL(IF(Pendencias!$B$2:$B$209=$F$1,ROW(Pendencias!$B$2:$B$209)-1),ROW(A88)),9),""))}
A86: Lanterna | C86: OK ( ) Observação ( ) Foi Subst ( ) | F86: Antenas | H86: OK ( ) Observação ( ) Foi Subst ( ) | W86: {=IFERROR(INDEX(Pendencias!$A$2:$O$209,SMALL(IF(Pendencias!$B$2:$B$209=$F$1,ROW(Pendencias!$B$2:$B$209)-1),ROW(A89)),1),"")} | X86: {=IFERROR(INDEX(Pendencias!$A$2:$O$209,SMALL(IF(Pendencias!$B$2:$B$209=$F$1,ROW(Pendencias!$B$2:$B$209)-1),ROW(A89)),3),"")} | Y86: {=IFERROR(INDEX(Pendencias!$A$2:$O$209,SMALL(IF(Pendencias!$B$2:$B$209=$F$1,ROW(Pendencias!$B$2:$B$209)-1),ROW(A89)),4),"")} | Z86: {=IFERROR(INDEX(Pendencias!$A$2:$O$209,SMALL(IF(Pendencias!$B$2:$B$209=$F$1,ROW(Pendencias!$B$2:$B$209)-1),ROW(A89)),7),"")} | AA86: {=IF(IFERROR(INDEX(Pendencias!$A$2:$O$209,SMALL(IF(Pendencias!$B$2:$B$209=$F$1,ROW(Pendencias!$B$2:$B$209)-1),ROW(A89)),9),"")=0,"",IFERROR(INDEX(Pendencias!$A$2:$O$209,SMALL(IF(Pendencias!$B$2:$B$209=$F$1,ROW(Pendencias!$B$2:$B$209)-1),ROW(A89)),9),""))}
A87: Boia | C87: OK ( ) Observação ( ) Foi Subst ( ) | F87: Bateria | H87: OK ( ) Observação ( ) Foi Subst ( ) | W87: {=IFERROR(INDEX(Pendencias!$A$2:$O$209,SMALL(IF(Pendencias!$B$2:$B$209=$F$1,ROW(Pendencias!$B$2:$B$209)-1),ROW(A90)),1),"")} | X87: {=IFERROR(INDEX(Pendencias!$A$2:$O$209,SMALL(IF(Pendencias!$B$2:$B$209=$F$1,ROW(Pendencias!$B$2:$B$209)-1),ROW(A90)),3),"")} | Y87: {=IFERROR(INDEX(Pendencias!$A$2:$O$209,SMALL(IF(Pendencias!$B$2:$B$209=$F$1,ROW(Pendencias!$B$2:$B$209)-1),ROW(A90)),4),"")} | Z87: {=IFERROR(INDEX(Pendencias!$A$2:$O$209,SMALL(IF(Pendencias!$B$2:$B$209=$F$1,ROW(Pendencias!$B$2:$B$209)-1),ROW(A90)),7),"")} | AA87: {=IF(IFERROR(INDEX(Pendencias!$A$2:$O$209,SMALL(IF(Pendencias!$B$2:$B$209=$F$1,ROW(Pendencias!$B$2:$B$209)-1),ROW(A90)),9),"")=0,"",IFERROR(INDEX(Pendencias!$A$2:$O$209,SMALL(IF(Pendencias!$B$2:$B$209=$F$1,ROW(Pendencias!$B$2:$B$209)-1),ROW(A90)),9),""))}
A88: Corrente Boia | C88: OK ( ) Observação ( ) Foi Subst ( ) | F88: Cabo Boia | H88: OK ( ) Observação ( ) Foi Subst ( ) | W88: {=IFERROR(INDEX(Pendencias!$A$2:$O$209,SMALL(IF(Pendencias!$B$2:$B$209=$F$1,ROW(Pendencias!$B$2:$B$209)-1),ROW(A91)),1),"")} | X88: {=IFERROR(INDEX(Pendencias!$A$2:$O$209,SMALL(IF(Pendencias!$B$2:$B$209=$F$1,ROW(Pendencias!$B$2:$B$209)-1),ROW(A91)),3),"")} | Y88: {=IFERROR(INDEX(Pendencias!$A$2:$O$209,SMALL(IF(Pendencias!$B$2:$B$209=$F$1,ROW(Pendencias!$B$2:$B$209)-1),ROW(A91)),4),"")} | Z88: {=IFERROR(INDEX(Pendencias!$A$2:$O$209,SMALL(IF(Pendencias!$B$2:$B$209=$F$1,ROW(Pendencias!$B$2:$B$209)-1),ROW(A91)),7),"")} | AA88: {=IF(IFERROR(INDEX(Pendencias!$A$2:$O$209,SMALL(IF(Pendencias!$B$2:$B$209=$F$1,ROW(Pendencias!$B$2:$B$209)-1),ROW(A91)),9),"")=0,"",IFERROR(INDEX(Pendencias!$A$2:$O$209,SMALL(IF(Pendencias!$B$2:$B$209=$F$1,ROW(Pendencias!$B$2:$B$209)-1),ROW(A91)),9),""))}
W89: {=IFERROR(INDEX(Pendencias!$A$2:$O$209,SMALL(IF(Pendencias!$B$2:$B$209=$F$1,ROW(Pendencias!$B$2:$B$209)-1),ROW(A92)),1),"")} | X89: {=IFERROR(INDEX(Pendencias!$A$2:$O$209,SMALL(IF(Pendencias!$B$2:$B$209=$F$1,ROW(Pendencias!$B$2:$B$209)-1),ROW(A92)),3),"")} | Y89: {=IFERROR(INDEX(Pendencias!$A$2:$O$209,SMALL(IF(Pendencias!$B$2:$B$209=$F$1,ROW(Pendencias!$B$2:$B$209)-1),ROW(A92)),4),"")} | Z89: {=IFERROR(INDEX(Pendencias!$A$2:$O$209,SMALL(IF(Pendencias!$B$2:$B$209=$F$1,ROW(Pendencias!$B$2:$B$209)-1),ROW(A92)),7),"")} | AA89: {=IF(IFERROR(INDEX(Pendencias!$A$2:$O$209,SMALL(IF(Pendencias!$B$2:$B$209=$F$1,ROW(Pendencias!$B$2:$B$209)-1),ROW(A92)),9),"")=0,"",IFERROR(INDEX(Pendencias!$A$2:$O$209,SMALL(IF(Pendencias!$B$2:$B$209=$F$1,ROW(Pendencias!$B$2:$B$209)-1),ROW(A92)),9),""))}
W90: {=IFERROR(INDEX(Pendencias!$A$2:$O$209,SMALL(IF(Pendencias!$B$2:$B$209=$F$1,ROW(Pendencias!$B$2:$B$209)-1),ROW(A93)),1),"")} | X90: {=IFERROR(INDEX(Pendencias!$A$2:$O$209,SMALL(IF(Pendencias!$B$2:$B$209=$F$1,ROW(Pendencias!$B$2:$B$209)-1),ROW(A93)),3),"")} | Y90: {=IFERROR(INDEX(Pendencias!$A$2:$O$209,SMALL(IF(Pendencias!$B$2:$B$209=$F$1,ROW(Pendencias!$B$2:$B$209)-1),ROW(A93)),4),"")} | Z90: {=IFERROR(INDEX(Pendencias!$A$2:$O$209,SMALL(IF(Pendencias!$B$2:$B$209=$F$1,ROW(Pendencias!$B$2:$B$209)-1),ROW(A93)),7),"")} | AA90: {=IF(IFERROR(INDEX(Pendencias!$A$2:$O$209,SMALL(IF(Pendencias!$B$2:$B$209=$F$1,ROW(Pendencias!$B$2:$B$209)-1),ROW(A93)),9),"")=0,"",IFERROR(INDEX(Pendencias!$A$2:$O$209,SMALL(IF(Pendencias!$B$2:$B$209=$F$1,ROW(Pendencias!$B$2:$B$209)-1),ROW(A93)),9),""))}
W91: {=IFERROR(INDEX(Pendencias!$A$2:$O$209,SMALL(IF(Pendencias!$B$2:$B$209=$F$1,ROW(Pendencias!$B$2:$B$209)-1),ROW(A94)),1),"")} | X91: {=IFERROR(INDEX(Pendencias!$A$2:$O$209,SMALL(IF(Pendencias!$B$2:$B$209=$F$1,ROW(Pendencias!$B$2:$B$209)-1),ROW(A94)),3),"")} | Y91: {=IFERROR(INDEX(Pendencias!$A$2:$O$209,SMALL(IF(Pendencias!$B$2:$B$209=$F$1,ROW(Pendencias!$B$2:$B$209)-1),ROW(A94)),4),"")} | Z91: {=IFERROR(INDEX(Pendencias!$A$2:$O$209,SMALL(IF(Pendencias!$B$2:$B$209=$F$1,ROW(Pendencias!$B$2:$B$209)-1),ROW(A94)),7),"")} | AA91: {=IF(IFERROR(INDEX(Pendencias!$A$2:$O$209,SMALL(IF(Pendencias!$B$2:$B$209=$F$1,ROW(Pendencias!$B$2:$B$209)-1),ROW(A94)),9),"")=0,"",IFERROR(INDEX(Pendencias!$A$2:$O$209,SMALL(IF(Pendencias!$B$2:$B$209=$F$1,ROW(Pendencias!$B$2:$B$209)-1),ROW(A94)),9),""))}
W92: {=IFERROR(INDEX(Pendencias!$A$2:$O$209,SMALL(IF(Pendencias!$B$2:$B$209=$F$1,ROW(Pendencias!$B$2:$B$209)-1),ROW(A95)),1),"")} | X92: {=IFERROR(INDEX(Pendencias!$A$2:$O$209,SMALL(IF(Pendencias!$B$2:$B$209=$F$1,ROW(Pendencias!$B$2:$B$209)-1),ROW(A95)),3),"")} | Y92: {=IFERROR(INDEX(Pendencias!$A$2:$O$209,SMALL(IF(Pendencias!$B$2:$B$209=$F$1,ROW(Pendencias!$B$2:$B$209)-1),ROW(A95)),4),"")} | Z92: {=IFERROR(INDEX(Pendencias!$A$2:$O$209,SMALL(IF(Pendencias!$B$2:$B$209=$F$1,ROW(Pendencias!$B$2:$B$209)-1),ROW(A95)),7),"")} | AA92: {=IF(IFERROR(INDEX(Pendencias!$A$2:$O$209,SMALL(IF(Pendencias!$B$2:$B$209=$F$1,ROW(Pendencias!$B$2:$B$209)-1),ROW(A95)),9),"")=0,"",IFERROR(INDEX(Pendencias!$A$2:$O$209,SMALL(IF(Pendencias!$B$2:$B$209=$F$1,ROW(Pendencias!$B$2:$B$209)-1),ROW(A95)),9),""))}
A93: CheckList Procedimentos e Ficha de Campo | G93: =F1 -> HMPDMCTDPIER1 | W93: {=IFERROR(INDEX(Pendencias!$A$2:$O$209,SMALL(IF(Pendencias!$B$2:$B$209=$F$1,ROW(Pendencias!$B$2:$B$209)-1),ROW(A96)),1),"")} | X93: {=IFERROR(INDEX(Pendencias!$A$2:$O$209,SMALL(IF(Pendencias!$B$2:$B$209=$F$1,ROW(Pendencias!$B$2:$B$209)-1),ROW(A96)),3),"")} | Y93: {=IFERROR(INDEX(Pendencias!$A$2:$O$209,SMALL(IF(Pendencias!$B$2:$B$209=$F$1,ROW(Pendencias!$B$2:$B$209)-1),ROW(A96)),4),"")} | Z93: {=IFERROR(INDEX(Pendencias!$A$2:$O$209,SMALL(IF(Pendencias!$B$2:$B$209=$F$1,ROW(Pendencias!$B$2:$B$209)-1),ROW(A96)),7),"")} | AA93: {=IF(IFERROR(INDEX(Pendencias!$A$2:$O$209,SMALL(IF(Pendencias!$B$2:$B$209=$F$1,ROW(Pendencias!$B$2:$B$209)-1),ROW(A96)),9),"")=0,"",IFERROR(INDEX(Pendencias!$A$2:$O$209,SMALL(IF(Pendencias!$B$2:$B$209=$F$1,ROW(Pendencias!$B$2:$B$209)-1),ROW(A96)),9),""))}
A94: OBS: gerar LOG de toda configuração do ADCP para posteriores vistorias | W94: {=IFERROR(INDEX(Pendencias!$A$2:$O$209,SMALL(IF(Pendencias!$B$2:$B$209=$F$1,ROW(Pendencias!$B$2:$B$209)-1),ROW(A97)),1),"")} | X94: {=IFERROR(INDEX(Pendencias!$A$2:$O$209,SMALL(IF(Pendencias!$B$2:$B$209=$F$1,ROW(Pendencias!$B$2:$B$209)-1),ROW(A97)),3),"")} | Y94: {=IFERROR(INDEX(Pendencias!$A$2:$O$209,SMALL(IF(Pendencias!$B$2:$B$209=$F$1,ROW(Pendencias!$B$2:$B$209)-1),ROW(A97)),4),"")} | Z94: {=IFERROR(INDEX(Pendencias!$A$2:$O$209,SMALL(IF(Pendencias!$B$2:$B$209=$F$1,ROW(Pendencias!$B$2:$B$209)-1),ROW(A97)),7),"")} | AA94: {=IF(IFERROR(INDEX(Pendencias!$A$2:$O$209,SMALL(IF(Pendencias!$B$2:$B$209=$F$1,ROW(Pendencias!$B$2:$B$209)-1),ROW(A97)),9),"")=0,"",IFERROR(INDEX(Pendencias!$A$2:$O$209,SMALL(IF(Pendencias!$B$2:$B$209=$F$1,ROW(Pendencias!$B$2:$B$209)-1),ROW(A97)),9),""))}
A95: Preencher com SIM ou NÃO. Riscar se não se aplica | W95: {=IFERROR(INDEX(Pendencias!$A$2:$O$209,SMALL(IF(Pendencias!$B$2:$B$209=$F$1,ROW(Pendencias!$B$2:$B$209)-1),ROW(A98)),1),"")} | X95: {=IFERROR(INDEX(Pendencias!$A$2:$O$209,SMALL(IF(Pendencias!$B$2:$B$209=$F$1,ROW(Pendencias!$B$2:$B$209)-1),ROW(A98)),3),"")} | Y95: {=IFERROR(INDEX(Pendencias!$A$2:$O$209,SMALL(IF(Pendencias!$B$2:$B$209=$F$1,ROW(Pendencias!$B$2:$B$209)-1),ROW(A98)),4),"")} | Z95: {=IFERROR(INDEX(Pendencias!$A$2:$O$209,SMALL(IF(Pendencias!$B$2:$B$209=$F$1,ROW(Pendencias!$B$2:$B$209)-1),ROW(A98)),7),"")} | AA95: {=IF(IFERROR(INDEX(Pendencias!$A$2:$O$209,SMALL(IF(Pendencias!$B$2:$B$209=$F$1,ROW(Pendencias!$B$2:$B$209)-1),ROW(A98)),9),"")=0,"",IFERROR(INDEX(Pendencias!$A$2:$O$209,SMALL(IF(Pendencias!$B$2:$B$209=$F$1,ROW(Pendencias!$B$2:$B$209)-1),ROW(A98)),9),""))}
A96: Download dados | D96: Observações: Pós campo | H96: Calibração Bússola ADCP | W96: {=IFERROR(INDEX(Pendencias!$A$2:$O$209,SMALL(IF(Pendencias!$B$2:$B$209=$F$1,ROW(Pendencias!$B$2:$B$209)-1),ROW(A99)),1),"")} | X96: {=IFERROR(INDEX(Pendencias!$A$2:$O$209,SMALL(IF(Pendencias!$B$2:$B$209=$F$1,ROW(Pendencias!$B$2:$B$209)-1),ROW(A99)),3),"")} | Y96: {=IFERROR(INDEX(Pendencias!$A$2:$O$209,SMALL(IF(Pendencias!$B$2:$B$209=$F$1,ROW(Pendencias!$B$2:$B$209)-1),ROW(A99)),4),"")} | Z96: {=IFERROR(INDEX(Pendencias!$A$2:$O$209,SMALL(IF(Pendencias!$B$2:$B$209=$F$1,ROW(Pendencias!$B$2:$B$209)-1),ROW(A99)),7),"")} | AA96: {=IF(IFERROR(INDEX(Pendencias!$A$2:$O$209,SMALL(IF(Pendencias!$B$2:$B$209=$F$1,ROW(Pendencias!$B$2:$B$209)-1),ROW(A99)),9),"")=0,"",IFERROR(INDEX(Pendencias!$A$2:$O$209,SMALL(IF(Pendencias!$B$2:$B$209=$F$1,ROW(Pendencias!$B$2:$B$209)-1),ROW(A99)),9),""))}
A97: Format memória | D97: Download LOG | H97: H: | J97: Não foi feita ( ) | W97: {=IFERROR(INDEX(Pendencias!$A$2:$O$209,SMALL(IF(Pendencias!$B$2:$B$209=$F$1,ROW(Pendencias!$B$2:$B$209)-1),ROW(A100)),1),"")} | X97: {=IFERROR(INDEX(Pendencias!$A$2:$O$209,SMALL(IF(Pendencias!$B$2:$B$209=$F$1,ROW(Pendencias!$B$2:$B$209)-1),ROW(A100)),3),"")} | Y97: {=IFERROR(INDEX(Pendencias!$A$2:$O$209,SMALL(IF(Pendencias!$B$2:$B$209=$F$1,ROW(Pendencias!$B$2:$B$209)-1),ROW(A100)),4),"")} | Z97: {=IFERROR(INDEX(Pendencias!$A$2:$O$209,SMALL(IF(Pendencias!$B$2:$B$209=$F$1,ROW(Pendencias!$B$2:$B$209)-1),ROW(A100)),7),"")} | AA97: {=IF(IFERROR(INDEX(Pendencias!$A$2:$O$209,SMALL(IF(Pendencias!$B$2:$B$209=$F$1,ROW(Pendencias!$B$2:$B$209)-1),ROW(A100)),9),"")=0,"",IFERROR(INDEX(Pendencias!$A$2:$O$209,SMALL(IF(Pendencias!$B$2:$B$209=$F$1,ROW(Pendencias!$B$2:$B$209)-1),ROW(A100)),9),""))}
A98: Mudança Config. * | D98: Ajuste de horário | H98: V: | W98: {=IFERROR(INDEX(Pendencias!$A$2:$O$209,SMALL(IF(Pendencias!$B$2:$B$209=$F$1,ROW(Pendencias!$B$2:$B$209)-1),ROW(A101)),1),"")} | X98: {=IFERROR(INDEX(Pendencias!$A$2:$O$209,SMALL(IF(Pendencias!$B$2:$B$209=$F$1,ROW(Pendencias!$B$2:$B$209)-1),ROW(A101)),3),"")} | Y98: {=IFERROR(INDEX(Pendencias!$A$2:$O$209,SMALL(IF(Pendencias!$B$2:$B$209=$F$1,ROW(Pendencias!$B$2:$B$209)-1),ROW(A101)),4),"")} | Z98: {=IFERROR(INDEX(Pendencias!$A$2:$O$209,SMALL(IF(Pendencias!$B$2:$B$209=$F$1,ROW(Pendencias!$B$2:$B$209)-1),ROW(A101)),7),"")} | AA98: {=IF(IFERROR(INDEX(Pendencias!$A$2:$O$209,SMALL(IF(Pendencias!$B$2:$B$209=$F$1,ROW(Pendencias!$B$2:$B$209)-1),ROW(A101)),9),"")=0,"",IFERROR(INDEX(Pendencias!$A$2:$O$209,SMALL(IF(Pendencias!$B$2:$B$209=$F$1,ROW(Pendencias!$B$2:$B$209)-1),ROW(A101)),9),""))}
A99: Limpeza Painel Solar | D99: Mudança Rotina Datalog | H99: Amb: | J99: N/A ( x ) | W99: {=IFERROR(INDEX(Pendencias!$A$2:$O$209,SMALL(IF(Pendencias!$B$2:$B$209=$F$1,ROW(Pendencias!$B$2:$B$209)-1),ROW(A102)),1),"")} | X99: {=IFERROR(INDEX(Pendencias!$A$2:$O$209,SMALL(IF(Pendencias!$B$2:$B$209=$F$1,ROW(Pendencias!$B$2:$B$209)-1),ROW(A102)),3),"")} | Y99: {=IFERROR(INDEX(Pendencias!$A$2:$O$209,SMALL(IF(Pendencias!$B$2:$B$209=$F$1,ROW(Pendencias!$B$2:$B$209)-1),ROW(A102)),4),"")} | Z99: {=IFERROR(INDEX(Pendencias!$A$2:$O$209,SMALL(IF(Pendencias!$B$2:$B$209=$F$1,ROW(Pendencias!$B$2:$B$209)-1),ROW(A102)),7),"")} | AA99: {=IF(IFERROR(INDEX(Pendencias!$A$2:$O$209,SMALL(IF(Pendencias!$B$2:$B$209=$F$1,ROW(Pendencias!$B$2:$B$209)-1),ROW(A102)),9),"")=0,"",IFERROR(INDEX(Pendencias!$A$2:$O$209,SMALL(IF(Pendencias!$B$2:$B$209=$F$1,ROW(Pendencias!$B$2:$B$209)-1),ROW(A102)),9),""))}
A100: Offset SensorPressão | D100: Resgate do ADCP | G100: Feita por: Equipe HM( ) Mergulhadores( ) | W100: {=IFERROR(INDEX(Pendencias!$A$2:$O$209,SMALL(IF(Pendencias!$B$2:$B$209=$F$1,ROW(Pendencias!$B$2:$B$209)-1),ROW(A103)),1),"")} | X100: {=IFERROR(INDEX(Pendencias!$A$2:$O$209,SMALL(IF(Pendencias!$B$2:$B$209=$F$1,ROW(Pendencias!$B$2:$B$209)-1),ROW(A103)),3),"")} | Y100: {=IFERROR(INDEX(Pendencias!$A$2:$O$209,SMALL(IF(Pendencias!$B$2:$B$209=$F$1,ROW(Pendencias!$B$2:$B$209)-1),ROW(A103)),4),"")} | Z100: {=IFERROR(INDEX(Pendencias!$A$2:$O$209,SMALL(IF(Pendencias!$B$2:$B$209=$F$1,ROW(Pendencias!$B$2:$B$209)-1),ROW(A103)),7),"")} | AA100: {=IF(IFERROR(INDEX(Pendencias!$A$2:$O$209,SMALL(IF(Pendencias!$B$2:$B$209=$F$1,ROW(Pendencias!$B$2:$B$209)-1),ROW(A103)),9),"")=0,"",IFERROR(INDEX(Pendencias!$A$2:$O$209,SMALL(IF(Pendencias!$B$2:$B$209=$F$1,ROW(Pendencias!$B$2:$B$209)-1),ROW(A103)),9),""))}
...

Sheet FichaCampo
A1: Ficha de Campo | E1: Estação: | F1: AXYS039 | H1: AUV ( ) | I1: AXYS ( X ) | J1: BMO ( ) | W1: {=IFERROR(INDEX(Pendencias!$A$2:$O$4333,SMALL(IF(Pendencias!$B$2:$B$4333=$F$1,ROW(Pendencias!$B$2:$B$4333)-1),ROW(A1)),1),"")} | X1: {=IFERROR(INDEX(Pendencias!$A$2:$O$4333,SMALL(IF(Pendencias!$B$2:$B$4333=$F$1,ROW(Pendencias!$B$2:$B$4333)-1),ROW(A1)),3),"")} | Y1: {=IFERROR(INDEX(Pendencias!$A$2:$O$4333,SMALL(IF(Pendencias!$B$2:$B$4333=$F$1,ROW(Pendencias!$B$2:$B$4333)-1),ROW(A1)),4),"")} | Z1: {=IFERROR(INDEX(Pendencias!$A$2:$O$4333,SMALL(IF(Pendencias!$B$2:$B$4333=$F$1,ROW(Pendencias!$B$2:$B$4333)-1),ROW(A1)),7),"")} | AA1: {=IF(IFERROR(INDEX(Pendencias!$A$2:$O$4333,SMALL(IF(Pendencias!$B$2:$B$4333=$F$1,ROW(Pendencias!$B$2:$B$4333)-1),ROW(A1)),9),"")=0,"",IFERROR(INDEX(Pendencias!$A$2:$O$4333,SMALL(IF(Pendencias!$B$2:$B$4333=$F$1,ROW(Pendencias!$B$2:$B$4333)-1),ROW(A1)),9),""))}
A2: Comissão: | D2: Responsável: | H2: Data: | W2: {=IFERROR(INDEX(Pendencias!$A$2:$O$4333,SMALL(IF(Pendencias!$B$2:$B$4333=$F$1,ROW(Pendencias!$B$2:$B$4333)-1),ROW(A2)),1),"")} | X2: {=IFERROR(INDEX(Pendencias!$A$2:$O$4333,SMALL(IF(Pendencias!$B$2:$B$4333=$F$1,ROW(Pendencias!$B$2:$B$4333)-1),ROW(A2)),3),"")} | Y2: {=IFERROR(INDEX(Pendencias!$A$2:$O$4333,SMALL(IF(Pendencias!$B$2:$B$4333=$F$1,ROW(Pendencias!$B$2:$B$4333)-1),ROW(A2)),4),"")} | Z2: {=IFERROR(INDEX(Pendencias!$A$2:$O$4333,SMALL(IF(Pendencias!$B$2:$B$4333=$F$1,ROW(Pendencias!$B$2:$B$4333)-1),ROW(A2)),7),"")} | AA2: {=IF(IFERROR(INDEX(Pendencias!$A$2:$O$4333,SMALL(IF(Pendencias!$B$2:$B$4333=$F$1,ROW(Pendencias!$B$2:$B$4333)-1),ROW(A2)),9),"")=0,"",IFERROR(INDEX(Pendencias!$A$2:$O$4333,SMALL(IF(Pendencias!$B$2:$B$4333=$F$1,ROW(Pendencias!$B$2:$B$4333)-1),ROW(A2)),9),""))}
A3: Latitude: | D3: Longitude: | H3: Prof.local: | W3: {=IFERROR(INDEX(Pendencias!$A$2:$O$4333,SMALL(IF(Pendencias!$B$2:$B$4333=$F$1,ROW(Pendencias!$B$2:$B$4333)-1),ROW(A3)),1),"")} | X3: {=IFERROR(INDEX(Pendencias!$A$2:$O$4333,SMALL(IF(Pendencias!$B$2:$B$4333=$F$1,ROW(Pendencias!$B$2:$B$4333)-1),ROW(A3)),3),"")} | Y3: {=IFERROR(INDEX(Pendencias!$A$2:$O$4333,SMALL(IF(Pendencias!$B$2:$B$4333=$F$1,ROW(Pendencias!$B$2:$B$4333)-1),ROW(A3)),4),"")} | Z3: {=IFERROR(INDEX(Pendencias!$A$2:$O$4333,SMALL(IF(Pendencias!$B$2:$B$4333=$F$1,ROW(Pendencias!$B$2:$B$4333)-1),ROW(A3)),7),"")} | AA3: {=IF(IFERROR(INDEX(Pendencias!$A$2:$O$4333,SMALL(IF(Pendencias!$B$2:$B$4333=$F$1,ROW(Pendencias!$B$2:$B$4333)-1),ROW(A3)),9),"")=0,"",IFERROR(INDEX(Pendencias!$A$2:$O$4333,SMALL(IF(Pendencias!$B$2:$B$4333=$F$1,ROW(Pendencias!$B$2:$B$4333)-1),ROW(A3)),9),""))}
A4: Argos ID: | D4: INMARSAT ID: | H4: MMSI:
A5: ID | B5: Pendências Previstas | J5: Status | W5: {=IFERROR(INDEX(Pendencias!$A$2:$O$4333,SMALL(IF(Pendencias!$B$2:$B$4333=$F$1,ROW(Pendencias!$B$2:$B$4333)-1),ROW(A5)),1),"")} | X5: {=IFERROR(INDEX(Pendencias!$A$2:$O$4333,SMALL(IF(Pendencias!$B$2:$B$4333=$F$1,ROW(Pendencias!$B$2:$B$4333)-1),ROW(A5)),3),"")} | Y5: {=IFERROR(INDEX(Pendencias!$A$2:$O$4333,SMALL(IF(Pendencias!$B$2:$B$4333=$F$1,ROW(Pendencias!$B$2:$B$4333)-1),ROW(A5)),4),"")} | Z5: {=IFERROR(INDEX(Pendencias!$A$2:$O$4333,SMALL(IF(Pendencias!$B$2:$B$4333=$F$1,ROW(Pendencias!$B$2:$B$4333)-1),ROW(A5)),7),"")} | AA5: {=IF(IFERROR(INDEX(Pendencias!$A$2:$O$4333,SMALL(IF(Pendencias!$B$2:$B$4333=$F$1,ROW(Pendencias!$B$2:$B$4333)-1),ROW(A5)),9),"")=0,"",IFERROR(INDEX(Pendencias!$A$2:$O$4333,SMALL(IF(Pendencias!$B$2:$B$4333=$F$1,ROW(Pendencias!$B$2:$B$4333)-1),ROW(A5)),9),""))}
A6: 1 | B6: Pintura da boia | J6: ok | W6: {=IFERROR(INDEX(Pendencias!$A$2:$O$4333,SMALL(IF(Pendencias!$B$2:$B$4333=$F$1,ROW(Pendencias!$B$2:$B$4333)-1),ROW(A6)),1),"")} | X6: {=IFERROR(INDEX(Pendencias!$A$2:$O$4333,SMALL(IF(Pendencias!$B$2:$B$4333=$F$1,ROW(Pendencias!$B$2:$B$4333)-1),ROW(A6)),3),"")} | Y6: {=IFERROR(INDEX(Pendencias!$A$2:$O$4333,SMALL(IF(Pendencias!$B$2:$B$4333=$F$1,ROW(Pendencias!$B$2:$B$4333)-1),ROW(A6)),4),"")} | Z6: {=IFERROR(INDEX(Pendencias!$A$2:$O$4333,SMALL(IF(Pendencias!$B$2:$B$4333=$F$1,ROW(Pendencias!$B$2:$B$4333)-1),ROW(A6)),7),"")} | AA6: {=IF(IFERROR(INDEX(Pendencias!$A$2:$O$4333,SMALL(IF(Pendencias!$B$2:$B$4333=$F$1,ROW(Pendencias!$B$2:$B$4333)-1),ROW(A6)),9),"")=0,"",IFERROR(INDEX(Pendencias!$A$2:$O$4333,SMALL(IF(Pendencias!$B$2:$B$4333=$F$1,ROW(Pendencias!$B$2:$B$4333)-1),ROW(A6)),9),""))}
A7: 2 | B7: Montagem de banco de baterias e paineis solares | J7: ok | W7: {=IFERROR(INDEX(Pendencias!$A$2:$O$4333,SMALL(IF(Pendencias!$B$2:$B$4333=$F$1,ROW(Pendencias!$B$2:$B$4333)-1),ROW(A7)),1),"")} | X7: {=IFERROR(INDEX(Pendencias!$A$2:$O$4333,SMALL(IF(Pendencias!$B$2:$B$4333=$F$1,ROW(Pendencias!$B$2:$B$4333)-1),ROW(A7)),3),"")} | Y7: {=IFERROR(INDEX(Pendencias!$A$2:$O$4333,SMALL(IF(Pendencias!$B$2:$B$4333=$F$1,ROW(Pendencias!$B$2:$B$4333)-1),ROW(A7)),4),"")} | Z7: {=IFERROR(INDEX(Pendencias!$A$2:$O$4333,SMALL(IF(Pendencias!$B$2:$B$4333=$F$1,ROW(Pendencias!$B$2:$B$4333)-1),ROW(A7)),7),"")} | AA7: {=IF(IFERROR(INDEX(Pendencias!$A$2:$O$4333,SMALL(IF(Pendencias!$B$2:$B$4333=$F$1,ROW(Pendencias!$B$2:$B$4333)-1),ROW(A7)),9),"")=0,"",IFERROR(INDEX(Pendencias!$A$2:$O$4333,SMALL(IF(Pendencias!$B$2:$B$4333=$F$1,ROW(Pendencias!$B$2:$B$4333)-1),ROW(A7)),9),""))}
A8: 3 | B8: Confecção e passagem dos cabos | J8: ok | W8: {=IFERROR(INDEX(Pendencias!$A$2:$O$4333,SMALL(IF(Pendencias!$B$2:$B$4333=$F$1,ROW(Pendencias!$B$2:$B$4333)-1),ROW(A8)),1),"")} | X8: {=IFERROR(INDEX(Pendencias!$A$2:$O$4333,SMALL(IF(Pendencias!$B$2:$B$4333=$F$1,ROW(Pendencias!$B$2:$B$4333)-1),ROW(A8)),3),"")} | Y8: {=IFERROR(INDEX(Pendencias!$A$2:$O$4333,SMALL(IF(Pendencias!$B$2:$B$4333=$F$1,ROW(Pendencias!$B$2:$B$4333)-1),ROW(A8)),4),"")} | Z8: {=IFERROR(INDEX(Pendencias!$A$2:$O$4333,SMALL(IF(Pendencias!$B$2:$B$4333=$F$1,ROW(Pendencias!$B$2:$B$4333)-1),ROW(A8)),7),"")} | AA8: {=IF(IFERROR(INDEX(Pendencias!$A$2:$O$4333,SMALL(IF(Pendencias!$B$2:$B$4333=$F$1,ROW(Pendencias!$B$2:$B$4333)-1),ROW(A8)),9),"")=0,"",IFERROR(INDEX(Pendencias!$A$2:$O$4333,SMALL(IF(Pendencias!$B$2:$B$4333=$F$1,ROW(Pendencias!$B$2:$B$4333)-1),ROW(A8)),9),""))}
A9: 4 | B9: Instalação de estruturas e suportes | J9: ok | W9: {=IFERROR(INDEX(Pendencias!$A$2:$O$4333,SMALL(IF(Pendencias!$B$2:$B$4333=$F$1,ROW(Pendencias!$B$2:$B$4333)-1),ROW(A9)),1),"")} | X9: {=IFERROR(INDEX(Pendencias!$A$2:$O$4333,SMALL(IF(Pendencias!$B$2:$B$4333=$F$1,ROW(Pendencias!$B$2:$B$4333)-1),ROW(A9)),3),"")} | Y9: {=IFERROR(INDEX(Pendencias!$A$2:$O$4333,SMALL(IF(Pendencias!$B$2:$B$4333=$F$1,ROW(Pendencias!$B$2:$B$4333)-1),ROW(A9)),4),"")} | Z9: {=IFERROR(INDEX(Pendencias!$A$2:$O$4333,SMALL(IF(Pendencias!$B$2:$B$4333=$F$1,ROW(Pendencias!$B$2:$B$4333)-1),ROW(A9)),7),"")} | AA9: {=IF(IFERROR(INDEX(Pendencias!$A$2:$O$4333,SMALL(IF(Pendencias!$B$2:$B$4333=$F$1,ROW(Pendencias!$B$2:$B$4333)-1),ROW(A9)),9),"")=0,"",IFERROR(INDEX(Pendencias!$A$2:$O$4333,SMALL(IF(Pendencias!$B$2:$B$4333=$F$1,ROW(Pendencias!$B$2:$B$4333)-1),ROW(A9)),9),""))}
A10: 5 | B10: Instalação dos sensores e equipamentos acessórios | J10: ok | W10: {=IFERROR(INDEX(Pendencias!$A$2:$O$4333,SMALL(IF(Pendencias!$B$2:$B$4333=$F$1,ROW(Pendencias!$B$2:$B$4333)-1),ROW(A10)),1),"")} | X10: {=IFERROR(INDEX(Pendencias!$A$2:$O$4333,SMALL(IF(Pendencias!$B$2:$B$4333=$F$1,ROW(Pendencias!$B$2:$B$4333)-1),ROW(A10)),3),"")} | Y10: {=IFERROR(INDEX(Pendencias!$A$2:$O$4333,SMALL(IF(Pendencias!$B$2:$B$4333=$F$1,ROW(Pendencias!$B$2:$B$4333)-1),ROW(A10)),4),"")} | Z10: {=IFERROR(INDEX(Pendencias!$A$2:$O$4333,SMALL(IF(Pendencias!$B$2:$B$4333=$F$1,ROW(Pendencias!$B$2:$B$4333)-1),ROW(A10)),7),"")} | AA10: {=IF(IFERROR(INDEX(Pendencias!$A$2:$O$4333,SMALL(IF(Pendencias!$B$2:$B$4333=$F$1,ROW(Pendencias!$B$2:$B$4333)-1),ROW(A10)),9),"")=0,"",IFERROR(INDEX(Pendencias!$A$2:$O$4333,SMALL(IF(Pendencias!$B$2:$B$4333=$F$1,ROW(Pendencias!$B$2:$B$4333)-1),ROW(A10)),9),""))}
A11: 6 | B11: Teste de transmissão, comunicação e coleta de dados | W11: {=IFERROR(INDEX(Pendencias!$A$2:$O$4333,SMALL(IF(Pendencias!$B$2:$B$4333=$F$1,ROW(Pendencias!$B$2:$B$4333)-1),ROW(A11)),1),"")} | X11: {=IFERROR(INDEX(Pendencias!$A$2:$O$4333,SMALL(IF(Pendencias!$B$2:$B$4333=$F$1,ROW(Pendencias!$B$2:$B$4333)-1),ROW(A11)),3),"")} | Y11: {=IFERROR(INDEX(Pendencias!$A$2:$O$4333,SMALL(IF(Pendencias!$B$2:$B$4333=$F$1,ROW(Pendencias!$B$2:$B$4333)-1),ROW(A11)),4),"")} | Z11: {=IFERROR(INDEX(Pendencias!$A$2:$O$4333,SMALL(IF(Pendencias!$B$2:$B$4333=$F$1,ROW(Pendencias!$B$2:$B$4333)-1),ROW(A11)),7),"")} | AA11: {=IF(IFERROR(INDEX(Pendencias!$A$2:$O$4333,SMALL(IF(Pendencias!$B$2:$B$4333=$F$1,ROW(Pendencias!$B$2:$B$4333)-1),ROW(A11)),9),"")=0,"",IFERROR(INDEX(Pendencias!$A$2:$O$4333,SMALL(IF(Pendencias!$B$2:$B$4333=$F$1,ROW(Pendencias!$B$2:$B$4333)-1),ROW(A11)),9),""))}
A12: 7 | B12: Isolamento elétrico de conexões (vedação com silicone) | W12: {=IFERROR(INDEX(Pendencias!$A$2:$O$4333,SMALL(IF(Pendencias!$B$2:$B$4333=$F$1,ROW(Pendencias!$B$2:$B$4333)-1),ROW(A12)),1),"")} | X12: {=IFERROR(INDEX(Pendencias!$A$2:$O$4333,SMALL(IF(Pendencias!$B$2:$B$4333=$F$1,ROW(Pendencias!$B$2:$B$4333)-1),ROW(A12)),3),"")} | Y12: {=IFERROR(INDEX(Pendencias!$A$2:$O$4333,SMALL(IF(Pendencias!$B$2:$B$4333=$F$1,ROW(Pendencias!$B$2:$B$4333)-1),ROW(A12)),4),"")} | Z12: {=IFERROR(INDEX(Pendencias!$A$2:$O$4333,SMALL(IF(Pendencias!$B$2:$B$4333=$F$1,ROW(Pendencias!$B$2:$B$4333)-1),ROW(A12)),7),"")} | AA12: {=IF(IFERROR(INDEX(Pendencias!$A$2:$O$4333,SMALL(IF(Pendencias!$B$2:$B$4333=$F$1,ROW(Pendencias!$B$2:$B$4333)-1),ROW(A12)),9),"")=0,"",IFERROR(INDEX(Pendencias!$A$2:$O$4333,SMALL(IF(Pendencias!$B$2:$B$4333=$F$1,ROW(Pendencias!$B$2:$B$4333)-1),ROW(A12)),9),""))}
A13: 8 | B13: Vedação do casco (silicone nos prensa-cabo) | W13: {=IFERROR(INDEX(Pendencias!$A$2:$O$4333,SMALL(IF(Pendencias!$B$2:$B$4333=$F$1,ROW(Pendencias!$B$2:$B$4333)-1),ROW(A13)),1),"")} | X13: {=IFERROR(INDEX(Pendencias!$A$2:$O$4333,SMALL(IF(Pendencias!$B$2:$B$4333=$F$1,ROW(Pendencias!$B$2:$B$4333)-1),ROW(A13)),3),"")} | Y13: {=IFERROR(INDEX(Pendencias!$A$2:$O$4333,SMALL(IF(Pendencias!$B$2:$B$4333=$F$1,ROW(Pendencias!$B$2:$B$4333)-1),ROW(A13)),4),"")} | Z13: {=IFERROR(INDEX(Pendencias!$A$2:$O$4333,SMALL(IF(Pendencias!$B$2:$B$4333=$F$1,ROW(Pendencias!$B$2:$B$4333)-1),ROW(A13)),7),"")} | AA13: {=IF(IFERROR(INDEX(Pendencias!$A$2:$O$4333,SMALL(IF(Pendencias!$B$2:$B$4333=$F$1,ROW(Pendencias!$B$2:$B$4333)-1),ROW(A13)),9),"")=0,"",IFERROR(INDEX(Pendencias!$A$2:$O$4333,SMALL(IF(Pendencias!$B$2:$B$4333=$F$1,ROW(Pendencias!$B$2:$B$4333)-1),ROW(A13)),9),""))}
A14: 9 | B14: Calibração de bussolas (ADCP e Ondógrafos) | W14: {=IFERROR(INDEX(Pendencias!$A$2:$O$4333,SMALL(IF(Pendencias!$B$2:$B$4333=$F$1,ROW(Pendencias!$B$2:$B$4333)-1),ROW(A14)),1),"")} | X14: {=IFERROR(INDEX(Pendencias!$A$2:$O$4333,SMALL(IF(Pendencias!$B$2:$B$4333=$F$1,ROW(Pendencias!$B$2:$B$4333)-1),ROW(A14)),3),"")} | Y14: {=IFERROR(INDEX(Pendencias!$A$2:$O$4333,SMALL(IF(Pendencias!$B$2:$B$4333=$F$1,ROW(Pendencias!$B$2:$B$4333)-1),ROW(A14)),4),"")} | Z14: {=IFERROR(INDEX(Pendencias!$A$2:$O$4333,SMALL(IF(Pendencias!$B$2:$B$4333=$F$1,ROW(Pendencias!$B$2:$B$4333)-1),ROW(A14)),7),"")} | AA14: {=IF(IFERROR(INDEX(Pendencias!$A$2:$O$4333,SMALL(IF(Pendencias!$B$2:$B$4333=$F$1,ROW(Pendencias!$B$2:$B$4333)-1),ROW(A14)),9),"")=0,"",IFERROR(INDEX(Pendencias!$A$2:$O$4333,SMALL(IF(Pendencias!$B$2:$B$4333=$F$1,ROW(Pendencias!$B$2:$B$4333)-1),ROW(A14)),9),""))}
A15: 10 | B15: Fixar Rastreador satelital | W15: {=IFERROR(INDEX(Pendencias!$A$2:$O$4333,SMALL(IF(Pendencias!$B$2:$B$4333=$F$1,ROW(Pendencias!$B$2:$B$4333)-1),ROW(A15)),1),"")} | X15: {=IFERROR(INDEX(Pendencias!$A$2:$O$4333,SMALL(IF(Pendencias!$B$2:$B$4333=$F$1,ROW(Pendencias!$B$2:$B$4333)-1),ROW(A15)),3),"")} | Y15: {=IFERROR(INDEX(Pendencias!$A$2:$O$4333,SMALL(IF(Pendencias!$B$2:$B$4333=$F$1,ROW(Pendencias!$B$2:$B$4333)-1),ROW(A15)),4),"")} | Z15: {=IFERROR(INDEX(Pendencias!$A$2:$O$4333,SMALL(IF(Pendencias!$B$2:$B$4333=$F$1,ROW(Pendencias!$B$2:$B$4333)-1),ROW(A15)),7),"")} | AA15: {=IF(IFERROR(INDEX(Pendencias!$A$2:$O$4333,SMALL(IF(Pendencias!$B$2:$B$4333=$F$1,ROW(Pendencias!$B$2:$B$4333)-1),ROW(A15)),9),"")=0,"",IFERROR(INDEX(Pendencias!$A$2:$O$4333,SMALL(IF(Pendencias!$B$2:$B$4333=$F$1,ROW(Pendencias!$B$2:$B$4333)-1),ROW(A15)),9),""))}
A16: 11 | B16: Ajustar orientação dos anemometros e fazer marcações nos postes | W16: {=IFERROR(INDEX(Pendencias!$A$2:$O$4333,SMALL(IF(Pendencias!$B$2:$B$4333=$F$1,ROW(Pendencias!$B$2:$B$4333)-1),ROW(A16)),1),"")} | X16: {=IFERROR(INDEX(Pendencias!$A$2:$O$4333,SMALL(IF(Pendencias!$B$2:$B$4333=$F$1,ROW(Pendencias!$B$2:$B$4333)-1),ROW(A16)),3),"")} | Y16: {=IFERROR(INDEX(Pendencias!$A$2:$O$4333,SMALL(IF(Pendencias!$B$2:$B$4333=$F$1,ROW(Pendencias!$B$2:$B$4333)-1),ROW(A16)),4),"")} | Z16: {=IFERROR(INDEX(Pendencias!$A$2:$O$4333,SMALL(IF(Pendencias!$B$2:$B$4333=$F$1,ROW(Pendencias!$B$2:$B$4333)-1),ROW(A16)),7),"")} | AA16: {=IF(IFERROR(INDEX(Pendencias!$A$2:$O$4333,SMALL(IF(Pendencias!$B$2:$B$4333=$F$1,ROW(Pendencias!$B$2:$B$4333)-1),ROW(A16)),9),"")=0,"",IFERROR(INDEX(Pendencias!$A$2:$O$4333,SMALL(IF(Pendencias!$B$2:$B$4333=$F$1,ROW(Pendencias!$B$2:$B$4333)-1),ROW(A16)),9),""))}
A17: 12 | B17: Passar fita de cobre no ADCP
A18: 13 | B18: Configuração de lanterna Carmanah (protocolo marinha)
A19: 14 | B19: Checklist de parafusos arruelas e porcas necessarios para operação
A20: 15 | B20: Configurar rastreador satelital (no local de fundeio) | W20: {=IFERROR(INDEX(Pendencias!$A$2:$O$4333,SMALL(IF(Pendencias!$B$2:$B$4333=$F$1,ROW(Pendencias!$B$2:$B$4333)-1),ROW(A20)),1),"")} | X20: {=IFERROR(INDEX(Pendencias!$A$2:$O$4333,SMALL(IF(Pendencias!$B$2:$B$4333=$F$1,ROW(Pendencias!$B$2:$B$4333)-1),ROW(A20)),3),"")} | Y20: {=IFERROR(INDEX(Pendencias!$A$2:$O$4333,SMALL(IF(Pendencias!$B$2:$B$4333=$F$1,ROW(Pendencias!$B$2:$B$4333)-1),ROW(A20)),4),"")} | Z20: {=IFERROR(INDEX(Pendencias!$A$2:$O$4333,SMALL(IF(Pendencias!$B$2:$B$4333=$F$1,ROW(Pendencias!$B$2:$B$4333)-1),ROW(A20)),7),"")} | AA20: {=IF(IFERROR(INDEX(Pendencias!$A$2:$O$4333,SMALL(IF(Pendencias!$B$2:$B$4333=$F$1,ROW(Pendencias!$B$2:$B$4333)-1),ROW(A20)),9),"")=0,"",IFERROR(INDEX(Pendencias!$A$2:$O$4333,SMALL(IF(Pendencias!$B$2:$B$4333=$F$1,ROW(Pendencias!$B$2:$B$4333)-1),ROW(A20)),9),""))}
W21: {=IFERROR(INDEX(Pendencias!$A$2:$O$4333,SMALL(IF(Pendencias!$B$2:$B$4333=$F$1,ROW(Pendencias!$B$2:$B$4333)-1),ROW(A21)),1),"")} | X21: {=IFERROR(INDEX(Pendencias!$A$2:$O$4333,SMALL(IF(Pendencias!$B$2:$B$4333=$F$1,ROW(Pendencias!$B$2:$B$4333)-1),ROW(A21)),3),"")} | Y21: {=IFERROR(INDEX(Pendencias!$A$2:$O$4333,SMALL(IF(Pendencias!$B$2:$B$4333=$F$1,ROW(Pendencias!$B$2:$B$4333)-1),ROW(A21)),4),"")} | Z21: {=IFERROR(INDEX(Pendencias!$A$2:$O$4333,SMALL(IF(Pendencias!$B$2:$B$4333=$F$1,ROW(Pendencias!$B$2:$B$4333)-1),ROW(A21)),7),"")} | AA21: {=IF(IFERROR(INDEX(Pendencias!$A$2:$O$4333,SMALL(IF(Pendencias!$B$2:$B$4333=$F$1,ROW(Pendencias!$B$2:$B$4333)-1),ROW(A21)),9),"")=0,"",IFERROR(INDEX(Pendencias!$A$2:$O$4333,SMALL(IF(Pendencias!$B$2:$B$4333=$F$1,ROW(Pendencias!$B$2:$B$4333)-1),ROW(A21)),9),""))}
A22: Problemas em aberto na Estação | W22: {=IFERROR(INDEX(Pendencias!$A$2:$O$4333,SMALL(IF(Pendencias!$B$2:$B$4333=$F$1,ROW(Pendencias!$B$2:$B$4333)-1),ROW(A22)),1),"")} | X22: {=IFERROR(INDEX(Pendencias!$A$2:$O$4333,SMALL(IF(Pendencias!$B$2:$B$4333=$F$1,ROW(Pendencias!$B$2:$B$4333)-1),ROW(A22)),3),"")} | Y22: {=IFERROR(INDEX(Pendencias!$A$2:$O$4333,SMALL(IF(Pendencias!$B$2:$B$4333=$F$1,ROW(Pendencias!$B$2:$B$4333)-1),ROW(A22)),4),"")} | Z22: {=IFERROR(INDEX(Pendencias!$A$2:$O$4333,SMALL(IF(Pendencias!$B$2:$B$4333=$F$1,ROW(Pendencias!$B$2:$B$4333)-1),ROW(A22)),7),"")} | AA22: {=IF(IFERROR(INDEX(Pendencias!$A$2:$O$4333,SMALL(IF(Pendencias!$B$2:$B$4333=$F$1,ROW(Pendencias!$B$2:$B$4333)-1),ROW(A22)),9),"")=0,"",IFERROR(INDEX(Pendencias!$A$2:$O$4333,SMALL(IF(Pendencias!$B$2:$B$4333=$F$1,ROW(Pendencias!$B$2:$B$4333)-1),ROW(A22)),9),""))}
A23: KEY | B23: DATA INÍCIO | C23: PRIORIDADE | D23: PROBLEMA | G23: RESUMO DO PROBLEMA | W23: {=IFERROR(INDEX(Pendencias!$A$2:$O$4333,SMALL(IF(Pendencias!$B$2:$B$4333=$F$1,ROW(Pendencias!$B$2:$B$4333)-1),ROW(A23)),1),"")} | X23: {=IFERROR(INDEX(Pendencias!$A$2:$O$4333,SMALL(IF(Pendencias!$B$2:$B$4333=$F$1,ROW(Pendencias!$B$2:$B$4333)-1),ROW(A23)),3),"")} | Y23: {=IFERROR(INDEX(Pendencias!$A$2:$O$4333,SMALL(IF(Pendencias!$B$2:$B$4333=$F$1,ROW(Pendencias!$B$2:$B$4333)-1),ROW(A23)),4),"")} | Z23: {=IFERROR(INDEX(Pendencias!$A$2:$O$4333,SMALL(IF(Pendencias!$B$2:$B$4333=$F$1,ROW(Pendencias!$B$2:$B$4333)-1),ROW(A23)),7),"")} | AA23: {=IF(IFERROR(INDEX(Pendencias!$A$2:$O$4333,SMALL(IF(Pendencias!$B$2:$B$4333=$F$1,ROW(Pendencias!$B$2:$B$4333)-1),ROW(A23)),9),"")=0,"",IFERROR(INDEX(Pendencias!$A$2:$O$4333,SMALL(IF(Pendencias!$B$2:$B$4333=$F$1,ROW(Pendencias!$B$2:$B$4333)-1),ROW(A23)),9),""))}
W24: {=IFERROR(INDEX(Pendencias!$A$2:$O$4333,SMALL(IF(Pendencias!$B$2:$B$4333=$F$1,ROW(Pendencias!$B$2:$B$4333)-1),ROW(A24)),1),"")} | X24: {=IFERROR(INDEX(Pendencias!$A$2:$O$4333,SMALL(IF(Pendencias!$B$2:$B$4333=$F$1,ROW(Pendencias!$B$2:$B$4333)-1),ROW(A24)),3),"")} | Y24: {=IFERROR(INDEX(Pendencias!$A$2:$O$4333,SMALL(IF(Pendencias!$B$2:$B$4333=$F$1,ROW(Pendencias!$B$2:$B$4333)-1),ROW(A24)),4),"")} | Z24: {=IFERROR(INDEX(Pendencias!$A$2:$O$4333,SMALL(IF(Pendencias!$B$2:$B$4333=$F$1,ROW(Pendencias!$B$2:$B$4333)-1),ROW(A24)),7),"")} | AA24: {=IF(IFERROR(INDEX(Pendencias!$A$2:$O$4333,SMALL(IF(Pendencias!$B$2:$B$4333=$F$1,ROW(Pendencias!$B$2:$B$4333)-1),ROW(A24)),9),"")=0,"",IFERROR(INDEX(Pendencias!$A$2:$O$4333,SMALL(IF(Pendencias!$B$2:$B$4333=$F$1,ROW(Pendencias!$B$2:$B$4333)-1),ROW(A24)),9),""))}
W25: {=IFERROR(INDEX(Pendencias!$A$2:$O$4333,SMALL(IF(Pendencias!$B$2:$B$4333=$F$1,ROW(Pendencias!$B$2:$B$4333)-1),ROW(A25)),1),"")} | X25: {=IFERROR(INDEX(Pendencias!$A$2:$O$4333,SMALL(IF(Pendencias!$B$2:$B$4333=$F$1,ROW(Pendencias!$B$2:$B$4333)-1),ROW(A25)),3),"")} | Y25: {=IFERROR(INDEX(Pendencias!$A$2:$O$4333,SMALL(IF(Pendencias!$B$2:$B$4333=$F$1,ROW(Pendencias!$B$2:$B$4333)-1),ROW(A25)),4),"")} | Z25: {=IFERROR(INDEX(Pendencias!$A$2:$O$4333,SMALL(IF(Pendencias!$B$2:$B$4333=$F$1,ROW(Pendencias!$B$2:$B$4333)-1),ROW(A25)),7),"")} | AA25: {=IF(IFERROR(INDEX(Pendencias!$A$2:$O$4333,SMALL(IF(Pendencias!$B$2:$B$4333=$F$1,ROW(Pendencias!$B$2:$B$4333)-1),ROW(A25)),9),"")=0,"",IFERROR(INDEX(Pendencias!$A$2:$O$4333,SMALL(IF(Pendencias!$B$2:$B$4333=$F$1,ROW(Pendencias!$B$2:$B$4333)-1),ROW(A25)),9),""))}
W26: {=IFERROR(INDEX(Pendencias!$A$2:$O$4333,SMALL(IF(Pendencias!$B$2:$B$4333=$F$1,ROW(Pendencias!$B$2:$B$4333)-1),ROW(A26)),1),"")} | X26: {=IFERROR(INDEX(Pendencias!$A$2:$O$4333,SMALL(IF(Pendencias!$B$2:$B$4333=$F$1,ROW(Pendencias!$B$2:$B$4333)-1),ROW(A26)),3),"")} | Y26: {=IFERROR(INDEX(Pendencias!$A$2:$O$4333,SMALL(IF(Pendencias!$B$2:$B$4333=$F$1,ROW(Pendencias!$B$2:$B$4333)-1),ROW(A26)),4),"")} | Z26: {=IFERROR(INDEX(Pendencias!$A$2:$O$4333,SMALL(IF(Pendencias!$B$2:$B$4333=$F$1,ROW(Pendencias!$B$2:$B$4333)-1),ROW(A26)),7),"")} | AA26: {=IF(IFERROR(INDEX(Pendencias!$A$2:$O$4333,SMALL(IF(Pendencias!$B$2:$B$4333=$F$1,ROW(Pendencias!$B$2:$B$4333)-1),ROW(A26)),9),"")=0,"",IFERROR(INDEX(Pendencias!$A$2:$O$4333,SMALL(IF(Pendencias!$B$2:$B$4333=$F$1,ROW(Pendencias!$B$2:$B$4333)-1),ROW(A26)),9),""))}
W27: {=IFERROR(INDEX(Pendencias!$A$2:$O$4333,SMALL(IF(Pendencias!$B$2:$B$4333=$F$1,ROW(Pendencias!$B$2:$B$4333)-1),ROW(A27)),1),"")} | X27: {=IFERROR(INDEX(Pendencias!$A$2:$O$4333,SMALL(IF(Pendencias!$B$2:$B$4333=$F$1,ROW(Pendencias!$B$2:$B$4333)-1),ROW(A27)),3),"")} | Y27: {=IFERROR(INDEX(Pendencias!$A$2:$O$4333,SMALL(IF(Pendencias!$B$2:$B$4333=$F$1,ROW(Pendencias!$B$2:$B$4333)-1),ROW(A27)),4),"")} | Z27: {=IFERROR(INDEX(Pendencias!$A$2:$O$4333,SMALL(IF(Pendencias!$B$2:$B$4333=$F$1,ROW(Pendencias!$B$2:$B$4333)-1),ROW(A27)),7),"")} | AA27: {=IF(IFERROR(INDEX(Pendencias!$A$2:$O$4333,SMALL(IF(Pendencias!$B$2:$B$4333=$F$1,ROW(Pendencias!$B$2:$B$4333)-1),ROW(A27)),9),"")=0,"",IFERROR(INDEX(Pendencias!$A$2:$O$4333,SMALL(IF(Pendencias!$B$2:$B$4333=$F$1,ROW(Pendencias!$B$2:$B$4333)-1),ROW(A27)),9),""))}
W28: {=IFERROR(INDEX(Pendencias!$A$2:$O$4333,SMALL(IF(Pendencias!$B$2:$B$4333=$F$1,ROW(Pendencias!$B$2:$B$4333)-1),ROW(A28)),1),"")} | X28: {=IFERROR(INDEX(Pendencias!$A$2:$O$4333,SMALL(IF(Pendencias!$B$2:$B$4333=$F$1,ROW(Pendencias!$B$2:$B$4333)-1),ROW(A28)),3),"")} | Y28: {=IFERROR(INDEX(Pendencias!$A$2:$O$4333,SMALL(IF(Pendencias!$B$2:$B$4333=$F$1,ROW(Pendencias!$B$2:$B$4333)-1),ROW(A28)),4),"")} | Z28: {=IFERROR(INDEX(Pendencias!$A$2:$O$4333,SMALL(IF(Pendencias!$B$2:$B$4333=$F$1,ROW(Pendencias!$B$2:$B$4333)-1),ROW(A28)),7),"")} | AA28: {=IF(IFERROR(INDEX(Pendencias!$A$2:$O$4333,SMALL(IF(Pendencias!$B$2:$B$4333=$F$1,ROW(Pendencias!$B$2:$B$4333)-1),ROW(A28)),9),"")=0,"",IFERROR(INDEX(Pendencias!$A$2:$O$4333,SMALL(IF(Pendencias!$B$2:$B$4333=$F$1,ROW(Pendencias!$B$2:$B$4333)-1),ROW(A28)),9),""))}
W29: {=IFERROR(INDEX(Pendencias!$A$2:$O$4333,SMALL(IF(Pendencias!$B$2:$B$4333=$F$1,ROW(Pendencias!$B$2:$B$4333)-1),ROW(A29)),1),"")} | X29: {=IFERROR(INDEX(Pendencias!$A$2:$O$4333,SMALL(IF(Pendencias!$B$2:$B$4333=$F$1,ROW(Pendencias!$B$2:$B$4333)-1),ROW(A29)),3),"")} | Y29: {=IFERROR(INDEX(Pendencias!$A$2:$O$4333,SMALL(IF(Pendencias!$B$2:$B$4333=$F$1,ROW(Pendencias!$B$2:$B$4333)-1),ROW(A29)),4),"")} | Z29: {=IFERROR(INDEX(Pendencias!$A$2:$O$4333,SMALL(IF(Pendencias!$B$2:$B$4333=$F$1,ROW(Pendencias!$B$2:$B$4333)-1),ROW(A29)),7),"")} | AA29: {=IF(IFERROR(INDEX(Pendencias!$A$2:$O$4333,SMALL(IF(Pendencias!$B$2:$B$4333=$F$1,ROW(Pendencias!$B$2:$B$4333)-1),ROW(A29)),9),"")=0,"",IFERROR(INDEX(Pendencias!$A$2:$O$4333,SMALL(IF(Pendencias!$B$2:$B$4333=$F$1,ROW(Pendencias!$B$2:$B$4333)-1),ROW(A29)),9),""))}
W30: {=IFERROR(INDEX(Pendencias!$A$2:$O$4333,SMALL(IF(Pendencias!$B$2:$B$4333=$F$1,ROW(Pendencias!$B$2:$B$4333)-1),ROW(A30)),1),"")} | X30: {=IFERROR(INDEX(Pendencias!$A$2:$O$4333,SMALL(IF(Pendencias!$B$2:$B$4333=$F$1,ROW(Pendencias!$B$2:$B$4333)-1),ROW(A30)),3),"")} | Y30: {=IFERROR(INDEX(Pendencias!$A$2:$O$4333,SMALL(IF(Pendencias!$B$2:$B$4333=$F$1,ROW(Pendencias!$B$2:$B$4333)-1),ROW(A30)),4),"")} | Z30: {=IFERROR(INDEX(Pendencias!$A$2:$O$4333,SMALL(IF(Pendencias!$B$2:$B$4333=$F$1,ROW(Pendencias!$B$2:$B$4333)-1),ROW(A30)),7),"")} | AA30: {=IF(IFERROR(INDEX(Pendencias!$A$2:$O$4333,SMALL(IF(Pendencias!$B$2:$B$4333=$F$1,ROW(Pendencias!$B$2:$B$4333)-1),ROW(A30)),9),"")=0,"",IFERROR(INDEX(Pendencias!$A$2:$O$4333,SMALL(IF(Pendencias!$B$2:$B$4333=$F$1,ROW(Pendencias!$B$2:$B$4333)-1),ROW(A30)),9),""))}
A31: Tipo de Manobra (assinale apenas 1) | W31: {=IFERROR(INDEX(Pendencias!$A$2:$O$4333,SMALL(IF(Pendencias!$B$2:$B$4333=$F$1,ROW(Pendencias!$B$2:$B$4333)-1),ROW(A31)),1),"")} | X31: {=IFERROR(INDEX(Pendencias!$A$2:$O$4333,SMALL(IF(Pendencias!$B$2:$B$4333=$F$1,ROW(Pendencias!$B$2:$B$4333)-1),ROW(A31)),3),"")} | Y31: {=IFERROR(INDEX(Pendencias!$A$2:$O$4333,SMALL(IF(Pendencias!$B$2:$B$4333=$F$1,ROW(Pendencias!$B$2:$B$4333)-1),ROW(A31)),4),"")} | Z31: {=IFERROR(INDEX(Pendencias!$A$2:$O$4333,SMALL(IF(Pendencias!$B$2:$B$4333=$F$1,ROW(Pendencias!$B$2:$B$4333)-1),ROW(A31)),7),"")} | AA31: {=IF(IFERROR(INDEX(Pendencias!$A$2:$O$4333,SMALL(IF(Pendencias!$B$2:$B$4333=$F$1,ROW(Pendencias!$B$2:$B$4333)-1),ROW(A31)),9),"")=0,"",IFERROR(INDEX(Pendencias!$A$2:$O$4333,SMALL(IF(Pendencias!$B$2:$B$4333=$F$1,ROW(Pendencias!$B$2:$B$4333)-1),ROW(A31)),9),""))}
A32: Instalação ( ) | C32: Manutenção ( ) | E32: reinstalação( ) | G32: Desinstalação ( ) | I32: Resgate ( ) | L32: {=IFERROR(INDEX(Pendencias!$A$2:$O$209,SMALL(IF(Pendencias!$B$2:$B$209=$F$1,ROW(Pendencias!$B$2:$B$209)-1),ROW(#REF!)),1),"")} | O32: {=IFERROR(INDEX(Pendencias!$A$2:$O$209,SMALL(IF(Pendencias!$B$2:$B$209=$F$1,ROW(Pendencias!$B$2:$B$209)-1),ROW(#REF!)),7),"")} | W32: {=IFERROR(INDEX(Pendencias!$A$2:$O$4333,SMALL(IF(Pendencias!$B$2:$B$4333=$F$1,ROW(Pendencias!$B$2:$B$4333)-1),ROW(A32)),1),"")} | X32: {=IFERROR(INDEX(Pendencias!$A$2:$O$4333,SMALL(IF(Pendencias!$B$2:$B$4333=$F$1,ROW(Pendencias!$B$2:$B$4333)-1),ROW(A32)),3),"")} | Y32: {=IFERROR(INDEX(Pendencias!$A$2:$O$4333,SMALL(IF(Pendencias!$B$2:$B$4333=$F$1,ROW(Pendencias!$B$2:$B$4333)-1),ROW(A32)),4),"")} | Z32: {=IFERROR(INDEX(Pendencias!$A$2:$O$4333,SMALL(IF(Pendencias!$B$2:$B$4333=$F$1,ROW(Pendencias!$B$2:$B$4333)-1),ROW(A32)),7),"")} | AA32: {=IF(IFERROR(INDEX(Pendencias!$A$2:$O$4333,SMALL(IF(Pendencias!$B$2:$B$4333=$F$1,ROW(Pendencias!$B$2:$B$4333)-1),ROW(A32)),9),"")=0,"",IFERROR(INDEX(Pendencias!$A$2:$O$4333,SMALL(IF(Pendencias!$B$2:$B$4333=$F$1,ROW(Pendencias!$B$2:$B$4333)-1),ROW(A32)),9),""))}
L33: {=IFERROR(INDEX(Pendencias!$A$2:$O$209,SMALL(IF(Pendencias!$B$2:$B$209=$F$1,ROW(Pendencias!$B$2:$B$209)-1),ROW(A38)),1),"")} | O33: {=IFERROR(INDEX(Pendencias!$A$2:$O$209,SMALL(IF(Pendencias!$B$2:$B$209=$F$1,ROW(Pendencias!$B$2:$B$209)-1),ROW(A38)),7),"")} | W33: {=IFERROR(INDEX(Pendencias!$A$2:$O$4333,SMALL(IF(Pendencias!$B$2:$B$4333=$F$1,ROW(Pendencias!$B$2:$B$4333)-1),ROW(A33)),1),"")} | X33: {=IFERROR(INDEX(Pendencias!$A$2:$O$4333,SMALL(IF(Pendencias!$B$2:$B$4333=$F$1,ROW(Pendencias!$B$2:$B$4333)-1),ROW(A33)),3),"")} | Y33: {=IFERROR(INDEX(Pendencias!$A$2:$O$4333,SMALL(IF(Pendencias!$B$2:$B$4333=$F$1,ROW(Pendencias!$B$2:$B$4333)-1),ROW(A33)),4),"")} | Z33: {=IFERROR(INDEX(Pendencias!$A$2:$O$4333,SMALL(IF(Pendencias!$B$2:$B$4333=$F$1,ROW(Pendencias!$B$2:$B$4333)-1),ROW(A33)),7),"")} | AA33: {=IF(IFERROR(INDEX(Pendencias!$A$2:$O$4333,SMALL(IF(Pendencias!$B$2:$B$4333=$F$1,ROW(Pendencias!$B$2:$B$4333)-1),ROW(A33)),9),"")=0,"",IFERROR(INDEX(Pendencias!$A$2:$O$4333,SMALL(IF(Pendencias!$B$2:$B$4333=$F$1,ROW(Pendencias!$B$2:$B$4333)-1),ROW(A33)),9),""))}
A34: Motivo e Objetivos da Manobra | W34: {=IFERROR(INDEX(Pendencias!$A$2:$O$4333,SMALL(IF(Pendencias!$B$2:$B$4333=$F$1,ROW(Pendencias!$B$2:$B$4333)-1),ROW(A34)),1),"")} | X34: {=IFERROR(INDEX(Pendencias!$A$2:$O$4333,SMALL(IF(Pendencias!$B$2:$B$4333=$F$1,ROW(Pendencias!$B$2:$B$4333)-1),ROW(A34)),3),"")} | Y34: {=IFERROR(INDEX(Pendencias!$A$2:$O$4333,SMALL(IF(Pendencias!$B$2:$B$4333=$F$1,ROW(Pendencias!$B$2:$B$4333)-1),ROW(A34)),4),"")} | Z34: {=IFERROR(INDEX(Pendencias!$A$2:$O$4333,SMALL(IF(Pendencias!$B$2:$B$4333=$F$1,ROW(Pendencias!$B$2:$B$4333)-1),ROW(A34)),7),"")} | AA34: {=IF(IFERROR(INDEX(Pendencias!$A$2:$O$4333,SMALL(IF(Pendencias!$B$2:$B$4333=$F$1,ROW(Pendencias!$B$2:$B$4333)-1),ROW(A34)),9),"")=0,"",IFERROR(INDEX(Pendencias!$A$2:$O$4333,SMALL(IF(Pendencias!$B$2:$B$4333=$F$1,ROW(Pendencias!$B$2:$B$4333)-1),ROW(A34)),9),""))}
A37: Observações: | W37: {=IFERROR(INDEX(Pendencias!$A$2:$O$4333,SMALL(IF(Pendencias!$B$2:$B$4333=$F$1,ROW(Pendencias!$B$2:$B$4333)-1),ROW(A37)),1),"")} | X37: {=IFERROR(INDEX(Pendencias!$A$2:$O$4333,SMALL(IF(Pendencias!$B$2:$B$4333=$F$1,ROW(Pendencias!$B$2:$B$4333)-1),ROW(A37)),3),"")} | Y37: {=IFERROR(INDEX(Pendencias!$A$2:$O$4333,SMALL(IF(Pendencias!$B$2:$B$4333=$F$1,ROW(Pendencias!$B$2:$B$4333)-1),ROW(A37)),4),"")} | Z37: {=IFERROR(INDEX(Pendencias!$A$2:$O$4333,SMALL(IF(Pendencias!$B$2:$B$4333=$F$1,ROW(Pendencias!$B$2:$B$4333)-1),ROW(A37)),7),"")} | AA37: {=IF(IFERROR(INDEX(Pendencias!$A$2:$O$4333,SMALL(IF(Pendencias!$B$2:$B$4333=$F$1,ROW(Pendencias!$B$2:$B$4333)-1),ROW(A37)),9),"")=0,"",IFERROR(INDEX(Pendencias!$A$2:$O$4333,SMALL(IF(Pendencias!$B$2:$B$4333=$F$1,ROW(Pendencias!$B$2:$B$4333)-1),ROW(A37)),9),""))}
A38: Orientação do anemômetro ultrassonico: Marcação do sensor oposta ao leme ou Sul da boia (BMO) Orientação do anemômetro analógico: Face da caixa de passagem alinhada ao leme ou Sul da boia (BMO) Orientação do Ondógrafo Triaxys: Marcação do sensor alinhada com o leme ou Sul da boia (BMO) Orientação do Ondógrafo SBG: Marcação do sensor alinhada com o leme ou Sul da boia (BMO) Verificar a presença de dummy plug na porta de comunicação numero 1 (ADCP) Inserir sachê de sílica em todas as caixas da boia
W40: {=IFERROR(INDEX(Pendencias!$A$2:$O$4333,SMALL(IF(Pendencias!$B$2:$B$4333=$F$1,ROW(Pendencias!$B$2:$B$4333)-1),ROW(A38)),1),"")} | X40: {=IFERROR(INDEX(Pendencias!$A$2:$O$4333,SMALL(IF(Pendencias!$B$2:$B$4333=$F$1,ROW(Pendencias!$B$2:$B$4333)-1),ROW(A38)),3),"")} | Y40: {=IFERROR(INDEX(Pendencias!$A$2:$O$4333,SMALL(IF(Pendencias!$B$2:$B$4333=$F$1,ROW(Pendencias!$B$2:$B$4333)-1),ROW(A38)),4),"")} | Z40: {=IFERROR(INDEX(Pendencias!$A$2:$O$4333,SMALL(IF(Pendencias!$B$2:$B$4333=$F$1,ROW(Pendencias!$B$2:$B$4333)-1),ROW(A38)),7),"")} | AA40: {=IF(IFERROR(INDEX(Pendencias!$A$2:$O$4333,SMALL(IF(Pendencias!$B$2:$B$4333=$F$1,ROW(Pendencias!$B$2:$B$4333)-1),ROW(A38)),9),"")=0,"",IFERROR(INDEX(Pendencias!$A$2:$O$4333,SMALL(IF(Pendencias!$B$2:$B$4333=$F$1,ROW(Pendencias!$B$2:$B$4333)-1),ROW(A38)),9),""))}
A41: Boas Práticas
A42: Lubrificar O-ring dos conectores com lubrificante apropriado Lubrificar conectores com graxa apropriada Utilizar alcool isopropilico para limpeza de conectores emborrachados Utilizar limpa contatos para limpeza de conectores metalicos Preencher Conectores BullGin com Silicone Vedar prensas cabo com silicone Passar LockTite 277nos parafusos de estruturas
W45: {=IFERROR(INDEX(Pendencias!$A$2:$O$209,SMALL(IF(Pendencias!$B$2:$B$209=$F$1,ROW(Pendencias!$B$2:$B$209)-1),ROW(A49)),1),"")} | X45: {=IFERROR(INDEX(Pendencias!$A$2:$O$209,SMALL(IF(Pendencias!$B$2:$B$209=$F$1,ROW(Pendencias!$B$2:$B$209)-1),ROW(A49)),3),"")} | Y45: {=IFERROR(INDEX(Pendencias!$A$2:$O$209,SMALL(IF(Pendencias!$B$2:$B$209=$F$1,ROW(Pendencias!$B$2:$B$209)-1),ROW(A49)),4),"")} | Z45: {=IFERROR(INDEX(Pendencias!$A$2:$O$209,SMALL(IF(Pendencias!$B$2:$B$209=$F$1,ROW(Pendencias!$B$2:$B$209)-1),ROW(A49)),7),"")} | AA45: {=IF(IFERROR(INDEX(Pendencias!$A$2:$O$209,SMALL(IF(Pendencias!$B$2:$B$209=$F$1,ROW(Pendencias!$B$2:$B$209)-1),ROW(A49)),9),"")=0,"",IFERROR(INDEX(Pendencias!$A$2:$O$209,SMALL(IF(Pendencias!$B$2:$B$209=$F$1,ROW(Pendencias!$B$2:$B$209)-1),ROW(A49)),9),""))}
A46: Horário de Início da navegação | F46: Horário Término da navegação | W46: {=IFERROR(INDEX(Pendencias!$A$2:$O$209,SMALL(IF(Pendencias!$B$2:$B$209=$F$1,ROW(Pendencias!$B$2:$B$209)-1),ROW(A50)),1),"")} | X46: {=IFERROR(INDEX(Pendencias!$A$2:$O$209,SMALL(IF(Pendencias!$B$2:$B$209=$F$1,ROW(Pendencias!$B$2:$B$209)-1),ROW(A50)),3),"")} | Y46: {=IFERROR(INDEX(Pendencias!$A$2:$O$209,SMALL(IF(Pendencias!$B$2:$B$209=$F$1,ROW(Pendencias!$B$2:$B$209)-1),ROW(A50)),4),"")} | Z46: {=IFERROR(INDEX(Pendencias!$A$2:$O$209,SMALL(IF(Pendencias!$B$2:$B$209=$F$1,ROW(Pendencias!$B$2:$B$209)-1),ROW(A50)),7),"")} | AA46: {=IF(IFERROR(INDEX(Pendencias!$A$2:$O$209,SMALL(IF(Pendencias!$B$2:$B$209=$F$1,ROW(Pendencias!$B$2:$B$209)-1),ROW(A50)),9),"")=0,"",IFERROR(INDEX(Pendencias!$A$2:$O$209,SMALL(IF(Pendencias!$B$2:$B$209=$F$1,ROW(Pendencias!$B$2:$B$209)-1),ROW(A50)),9),""))}
A47: Horário de Início da Manobra | F47: Horário Término da Manobra | W47: {=IFERROR(INDEX(Pendencias!$A$2:$O$209,SMALL(IF(Pendencias!$B$2:$B$209=$F$1,ROW(Pendencias!$B$2:$B$209)-1),ROW(A51)),1),"")} | X47: {=IFERROR(INDEX(Pendencias!$A$2:$O$209,SMALL(IF(Pendencias!$B$2:$B$209=$F$1,ROW(Pendencias!$B$2:$B$209)-1),ROW(A51)),3),"")} | Y47: {=IFERROR(INDEX(Pendencias!$A$2:$O$209,SMALL(IF(Pendencias!$B$2:$B$209=$F$1,ROW(Pendencias!$B$2:$B$209)-1),ROW(A51)),4),"")} | Z47: {=IFERROR(INDEX(Pendencias!$A$2:$O$209,SMALL(IF(Pendencias!$B$2:$B$209=$F$1,ROW(Pendencias!$B$2:$B$209)-1),ROW(A51)),7),"")} | AA47: {=IF(IFERROR(INDEX(Pendencias!$A$2:$O$209,SMALL(IF(Pendencias!$B$2:$B$209=$F$1,ROW(Pendencias!$B$2:$B$209)-1),ROW(A51)),9),"")=0,"",IFERROR(INDEX(Pendencias!$A$2:$O$209,SMALL(IF(Pendencias!$B$2:$B$209=$F$1,ROW(Pendencias!$B$2:$B$209)-1),ROW(A51)),9),""))}
W48: {=IFERROR(INDEX(Pendencias!$A$2:$O$209,SMALL(IF(Pendencias!$B$2:$B$209=$F$1,ROW(Pendencias!$B$2:$B$209)-1),ROW(A51)),1),"")} | X48: {=IFERROR(INDEX(Pendencias!$A$2:$O$209,SMALL(IF(Pendencias!$B$2:$B$209=$F$1,ROW(Pendencias!$B$2:$B$209)-1),ROW(A51)),3),"")} | Y48: {=IFERROR(INDEX(Pendencias!$A$2:$O$209,SMALL(IF(Pendencias!$B$2:$B$209=$F$1,ROW(Pendencias!$B$2:$B$209)-1),ROW(A51)),4),"")} | Z48: {=IFERROR(INDEX(Pendencias!$A$2:$O$209,SMALL(IF(Pendencias!$B$2:$B$209=$F$1,ROW(Pendencias!$B$2:$B$209)-1),ROW(A51)),7),"")} | AA48: {=IF(IFERROR(INDEX(Pendencias!$A$2:$O$209,SMALL(IF(Pendencias!$B$2:$B$209=$F$1,ROW(Pendencias!$B$2:$B$209)-1),ROW(A51)),9),"")=0,"",IFERROR(INDEX(Pendencias!$A$2:$O$209,SMALL(IF(Pendencias!$B$2:$B$209=$F$1,ROW(Pendencias!$B$2:$B$209)-1),ROW(A51)),9),""))}
A49: Condições ambientais no ínicio da manobra | C49: Sem Chuva ( ) | F49: Chuva Fraca ( ) | I49: Chuva Forte ( ) | W49: {=IFERROR(INDEX(Pendencias!$A$2:$O$209,SMALL(IF(Pendencias!$B$2:$B$209=$F$1,ROW(Pendencias!$B$2:$B$209)-1),ROW(A52)),1),"")} | X49: {=IFERROR(INDEX(Pendencias!$A$2:$O$209,SMALL(IF(Pendencias!$B$2:$B$209=$F$1,ROW(Pendencias!$B$2:$B$209)-1),ROW(A52)),3),"")} | Y49: {=IFERROR(INDEX(Pendencias!$A$2:$O$209,SMALL(IF(Pendencias!$B$2:$B$209=$F$1,ROW(Pendencias!$B$2:$B$209)-1),ROW(A52)),4),"")} | Z49: {=IFERROR(INDEX(Pendencias!$A$2:$O$209,SMALL(IF(Pendencias!$B$2:$B$209=$F$1,ROW(Pendencias!$B$2:$B$209)-1),ROW(A52)),7),"")} | AA49: {=IF(IFERROR(INDEX(Pendencias!$A$2:$O$209,SMALL(IF(Pendencias!$B$2:$B$209=$F$1,ROW(Pendencias!$B$2:$B$209)-1),ROW(A52)),9),"")=0,"",IFERROR(INDEX(Pendencias!$A$2:$O$209,SMALL(IF(Pendencias!$B$2:$B$209=$F$1,ROW(Pendencias!$B$2:$B$209)-1),ROW(A52)),9),""))}
C50: Ventos Fracos ( ) | F50: Vento Moderado ( ) | I50: Ventos Fortes ( ) | W50: {=IFERROR(INDEX(Pendencias!$A$2:$O$209,SMALL(IF(Pendencias!$B$2:$B$209=$F$1,ROW(Pendencias!$B$2:$B$209)-1),ROW(A53)),1),"")} | X50: {=IFERROR(INDEX(Pendencias!$A$2:$O$209,SMALL(IF(Pendencias!$B$2:$B$209=$F$1,ROW(Pendencias!$B$2:$B$209)-1),ROW(A53)),3),"")} | Y50: {=IFERROR(INDEX(Pendencias!$A$2:$O$209,SMALL(IF(Pendencias!$B$2:$B$209=$F$1,ROW(Pendencias!$B$2:$B$209)-1),ROW(A53)),4),"")} | Z50: {=IFERROR(INDEX(Pendencias!$A$2:$O$209,SMALL(IF(Pendencias!$B$2:$B$209=$F$1,ROW(Pendencias!$B$2:$B$209)-1),ROW(A53)),7),"")} | AA50: {=IF(IFERROR(INDEX(Pendencias!$A$2:$O$209,SMALL(IF(Pendencias!$B$2:$B$209=$F$1,ROW(Pendencias!$B$2:$B$209)-1),ROW(A53)),9),"")=0,"",IFERROR(INDEX(Pendencias!$A$2:$O$209,SMALL(IF(Pendencias!$B$2:$B$209=$F$1,ROW(Pendencias!$B$2:$B$209)-1),ROW(A53)),9),""))}
C51: Mar Calmo ( ) | F51: Ondas Moderadas ( ) | I51: Ondas Altas ( ) | W51: {=IFERROR(INDEX(Pendencias!$A$2:$O$209,SMALL(IF(Pendencias!$B$2:$B$209=$F$1,ROW(Pendencias!$B$2:$B$209)-1),ROW(A54)),1),"")} | X51: {=IFERROR(INDEX(Pendencias!$A$2:$O$209,SMALL(IF(Pendencias!$B$2:$B$209=$F$1,ROW(Pendencias!$B$2:$B$209)-1),ROW(A54)),3),"")} | Y51: {=IFERROR(INDEX(Pendencias!$A$2:$O$209,SMALL(IF(Pendencias!$B$2:$B$209=$F$1,ROW(Pendencias!$B$2:$B$209)-1),ROW(A54)),4),"")} | Z51: {=IFERROR(INDEX(Pendencias!$A$2:$O$209,SMALL(IF(Pendencias!$B$2:$B$209=$F$1,ROW(Pendencias!$B$2:$B$209)-1),ROW(A54)),7),"")} | AA51: {=IF(IFERROR(INDEX(Pendencias!$A$2:$O$209,SMALL(IF(Pendencias!$B$2:$B$209=$F$1,ROW(Pendencias!$B$2:$B$209)-1),ROW(A54)),9),"")=0,"",IFERROR(INDEX(Pendencias!$A$2:$O$209,SMALL(IF(Pendencias!$B$2:$B$209=$F$1,ROW(Pendencias!$B$2:$B$209)-1),ROW(A54)),9),""))}
C52: Correntes Fracas ( ) | F52: Correntes Moderadas ( ) | I52: Correntes Fortes ( ) | W52: {=IFERROR(INDEX(Pendencias!$A$2:$O$209,SMALL(IF(Pendencias!$B$2:$B$209=$F$1,ROW(Pendencias!$B$2:$B$209)-1),ROW(A55)),1),"")} | X52: {=IFERROR(INDEX(Pendencias!$A$2:$O$209,SMALL(IF(Pendencias!$B$2:$B$209=$F$1,ROW(Pendencias!$B$2:$B$209)-1),ROW(A55)),3),"")} | Y52: {=IFERROR(INDEX(Pendencias!$A$2:$O$209,SMALL(IF(Pendencias!$B$2:$B$209=$F$1,ROW(Pendencias!$B$2:$B$209)-1),ROW(A55)),4),"")} | Z52: {=IFERROR(INDEX(Pendencias!$A$2:$O$209,SMALL(IF(Pendencias!$B$2:$B$209=$F$1,ROW(Pendencias!$B$2:$B$209)-1),ROW(A55)),7),"")} | AA52: {=IF(IFERROR(INDEX(Pendencias!$A$2:$O$209,SMALL(IF(Pendencias!$B$2:$B$209=$F$1,ROW(Pendencias!$B$2:$B$209)-1),ROW(A55)),9),"")=0,"",IFERROR(INDEX(Pendencias!$A$2:$O$209,SMALL(IF(Pendencias!$B$2:$B$209=$F$1,ROW(Pendencias!$B$2:$B$209)-1),ROW(A55)),9),""))}
W53: {=IFERROR(INDEX(Pendencias!$A$2:$O$209,SMALL(IF(Pendencias!$B$2:$B$209=$F$1,ROW(Pendencias!$B$2:$B$209)-1),ROW(A56)),1),"")} | X53: {=IFERROR(INDEX(Pendencias!$A$2:$O$209,SMALL(IF(Pendencias!$B$2:$B$209=$F$1,ROW(Pendencias!$B$2:$B$209)-1),ROW(A56)),3),"")} | Y53: {=IFERROR(INDEX(Pendencias!$A$2:$O$209,SMALL(IF(Pendencias!$B$2:$B$209=$F$1,ROW(Pendencias!$B$2:$B$209)-1),ROW(A56)),4),"")} | Z53: {=IFERROR(INDEX(Pendencias!$A$2:$O$209,SMALL(IF(Pendencias!$B$2:$B$209=$F$1,ROW(Pendencias!$B$2:$B$209)-1),ROW(A56)),7),"")} | AA53: {=IF(IFERROR(INDEX(Pendencias!$A$2:$O$209,SMALL(IF(Pendencias!$B$2:$B$209=$F$1,ROW(Pendencias!$B$2:$B$209)-1),ROW(A56)),9),"")=0,"",IFERROR(INDEX(Pendencias!$A$2:$O$209,SMALL(IF(Pendencias!$B$2:$B$209=$F$1,ROW(Pendencias!$B$2:$B$209)-1),ROW(A56)),9),""))}
A54: Informações sobre embarcação, tripulação e mergulho | W54: {=IFERROR(INDEX(Pendencias!$A$2:$O$209,SMALL(IF(Pendencias!$B$2:$B$209=$F$1,ROW(Pendencias!$B$2:$B$209)-1),ROW(A57)),1),"")} | X54: {=IFERROR(INDEX(Pendencias!$A$2:$O$209,SMALL(IF(Pendencias!$B$2:$B$209=$F$1,ROW(Pendencias!$B$2:$B$209)-1),ROW(A57)),3),"")} | Y54: {=IFERROR(INDEX(Pendencias!$A$2:$O$209,SMALL(IF(Pendencias!$B$2:$B$209=$F$1,ROW(Pendencias!$B$2:$B$209)-1),ROW(A57)),4),"")} | Z54: {=IFERROR(INDEX(Pendencias!$A$2:$O$209,SMALL(IF(Pendencias!$B$2:$B$209=$F$1,ROW(Pendencias!$B$2:$B$209)-1),ROW(A57)),7),"")} | AA54: {=IF(IFERROR(INDEX(Pendencias!$A$2:$O$209,SMALL(IF(Pendencias!$B$2:$B$209=$F$1,ROW(Pendencias!$B$2:$B$209)-1),ROW(A57)),9),"")=0,"",IFERROR(INDEX(Pendencias!$A$2:$O$209,SMALL(IF(Pendencias!$B$2:$B$209=$F$1,ROW(Pendencias!$B$2:$B$209)-1),ROW(A57)),9),""))}
A55: Embarcação : | F55: Embarcação de apoio: | W55: {=IFERROR(INDEX(Pendencias!$A$2:$O$209,SMALL(IF(Pendencias!$B$2:$B$209=$F$1,ROW(Pendencias!$B$2:$B$209)-1),ROW(#REF!)),1),"")} | X55: {=IFERROR(INDEX(Pendencias!$A$2:$O$209,SMALL(IF(Pendencias!$B$2:$B$209=$F$1,ROW(Pendencias!$B$2:$B$209)-1),ROW(#REF!)),3),"")} | Y55: {=IFERROR(INDEX(Pendencias!$A$2:$O$209,SMALL(IF(Pendencias!$B$2:$B$209=$F$1,ROW(Pendencias!$B$2:$B$209)-1),ROW(#REF!)),4),"")} | Z55: {=IFERROR(INDEX(Pendencias!$A$2:$O$209,SMALL(IF(Pendencias!$B$2:$B$209=$F$1,ROW(Pendencias!$B$2:$B$209)-1),ROW(#REF!)),7),"")} | AA55: {=IF(IFERROR(INDEX(Pendencias!$A$2:$O$209,SMALL(IF(Pendencias!$B$2:$B$209=$F$1,ROW(Pendencias!$B$2:$B$209)-1),ROW(#REF!)),9),"")=0,"",IFERROR(INDEX(Pendencias!$A$2:$O$209,SMALL(IF(Pendencias!$B$2:$B$209=$F$1,ROW(Pendencias!$B$2:$B$209)-1),ROW(#REF!)),9),""))}
A56: Comt. Embarcação: | F56: Imediato Emb. : | W56: {=IFERROR(INDEX(Pendencias!$A$2:$O$209,SMALL(IF(Pendencias!$B$2:$B$209=$F$1,ROW(Pendencias!$B$2:$B$209)-1),ROW(A58)),1),"")} | X56: {=IFERROR(INDEX(Pendencias!$A$2:$O$209,SMALL(IF(Pendencias!$B$2:$B$209=$F$1,ROW(Pendencias!$B$2:$B$209)-1),ROW(A58)),3),"")} | Y56: {=IFERROR(INDEX(Pendencias!$A$2:$O$209,SMALL(IF(Pendencias!$B$2:$B$209=$F$1,ROW(Pendencias!$B$2:$B$209)-1),ROW(A58)),4),"")} | Z56: {=IFERROR(INDEX(Pendencias!$A$2:$O$209,SMALL(IF(Pendencias!$B$2:$B$209=$F$1,ROW(Pendencias!$B$2:$B$209)-1),ROW(A58)),7),"")} | AA56: {=IF(IFERROR(INDEX(Pendencias!$A$2:$O$209,SMALL(IF(Pendencias!$B$2:$B$209=$F$1,ROW(Pendencias!$B$2:$B$209)-1),ROW(A58)),9),"")=0,"",IFERROR(INDEX(Pendencias!$A$2:$O$209,SMALL(IF(Pendencias!$B$2:$B$209=$F$1,ROW(Pendencias!$B$2:$B$209)-1),ROW(A58)),9),""))}
A57: Chefe de operações: | F57: Responsável: | W57: {=IFERROR(INDEX(Pendencias!$A$2:$O$209,SMALL(IF(Pendencias!$B$2:$B$209=$F$1,ROW(Pendencias!$B$2:$B$209)-1),ROW(A59)),1),"")} | X57: {=IFERROR(INDEX(Pendencias!$A$2:$O$209,SMALL(IF(Pendencias!$B$2:$B$209=$F$1,ROW(Pendencias!$B$2:$B$209)-1),ROW(A59)),3),"")} | Y57: {=IFERROR(INDEX(Pendencias!$A$2:$O$209,SMALL(IF(Pendencias!$B$2:$B$209=$F$1,ROW(Pendencias!$B$2:$B$209)-1),ROW(A59)),4),"")} | Z57: {=IFERROR(INDEX(Pendencias!$A$2:$O$209,SMALL(IF(Pendencias!$B$2:$B$209=$F$1,ROW(Pendencias!$B$2:$B$209)-1),ROW(A59)),7),"")} | AA57: {=IF(IFERROR(INDEX(Pendencias!$A$2:$O$209,SMALL(IF(Pendencias!$B$2:$B$209=$F$1,ROW(Pendencias!$B$2:$B$209)-1),ROW(A59)),9),"")=0,"",IFERROR(INDEX(Pendencias!$A$2:$O$209,SMALL(IF(Pendencias!$B$2:$B$209=$F$1,ROW(Pendencias!$B$2:$B$209)-1),ROW(A59)),9),""))}
A58: Mergulhadores: | W58: {=IFERROR(INDEX(Pendencias!$A$2:$O$209,SMALL(IF(Pendencias!$B$2:$B$209=$F$1,ROW(Pendencias!$B$2:$B$209)-1),ROW(A61)),1),"")} | X58: {=IFERROR(INDEX(Pendencias!$A$2:$O$209,SMALL(IF(Pendencias!$B$2:$B$209=$F$1,ROW(Pendencias!$B$2:$B$209)-1),ROW(A61)),3),"")} | Y58: {=IFERROR(INDEX(Pendencias!$A$2:$O$209,SMALL(IF(Pendencias!$B$2:$B$209=$F$1,ROW(Pendencias!$B$2:$B$209)-1),ROW(A61)),4),"")} | Z58: {=IFERROR(INDEX(Pendencias!$A$2:$O$209,SMALL(IF(Pendencias!$B$2:$B$209=$F$1,ROW(Pendencias!$B$2:$B$209)-1),ROW(A61)),7),"")} | AA58: {=IF(IFERROR(INDEX(Pendencias!$A$2:$O$209,SMALL(IF(Pendencias!$B$2:$B$209=$F$1,ROW(Pendencias!$B$2:$B$209)-1),ROW(A61)),9),"")=0,"",IFERROR(INDEX(Pendencias!$A$2:$O$209,SMALL(IF(Pendencias!$B$2:$B$209=$F$1,ROW(Pendencias!$B$2:$B$209)-1),ROW(A61)),9),""))}
A59: Equipe PNBOIA: | W59: {=IFERROR(INDEX(Pendencias!$A$2:$O$209,SMALL(IF(Pendencias!$B$2:$B$209=$F$1,ROW(Pendencias!$B$2:$B$209)-1),ROW(A62)),1),"")} | X59: {=IFERROR(INDEX(Pendencias!$A$2:$O$209,SMALL(IF(Pendencias!$B$2:$B$209=$F$1,ROW(Pendencias!$B$2:$B$209)-1),ROW(A62)),3),"")} | Y59: {=IFERROR(INDEX(Pendencias!$A$2:$O$209,SMALL(IF(Pendencias!$B$2:$B$209=$F$1,ROW(Pendencias!$B$2:$B$209)-1),ROW(A62)),4),"")} | Z59: {=IFERROR(INDEX(Pendencias!$A$2:$O$209,SMALL(IF(Pendencias!$B$2:$B$209=$F$1,ROW(Pendencias!$B$2:$B$209)-1),ROW(A62)),7),"")} | AA59: {=IF(IFERROR(INDEX(Pendencias!$A$2:$O$209,SMALL(IF(Pendencias!$B$2:$B$209=$F$1,ROW(Pendencias!$B$2:$B$209)-1),ROW(A62)),9),"")=0,"",IFERROR(INDEX(Pendencias!$A$2:$O$209,SMALL(IF(Pendencias!$B$2:$B$209=$F$1,ROW(Pendencias!$B$2:$B$209)-1),ROW(A62)),9),""))}
A60: Terceiros (nomes e empresa): | W60: {=IFERROR(INDEX(Pendencias!$A$2:$O$209,SMALL(IF(Pendencias!$B$2:$B$209=$F$1,ROW(Pendencias!$B$2:$B$209)-1),ROW(A68)),1),"")} | X60: {=IFERROR(INDEX(Pendencias!$A$2:$O$209,SMALL(IF(Pendencias!$B$2:$B$209=$F$1,ROW(Pendencias!$B$2:$B$209)-1),ROW(A68)),3),"")} | Y60: {=IFERROR(INDEX(Pendencias!$A$2:$O$209,SMALL(IF(Pendencias!$B$2:$B$209=$F$1,ROW(Pendencias!$B$2:$B$209)-1),ROW(A68)),4),"")} | Z60: {=IFERROR(INDEX(Pendencias!$A$2:$O$209,SMALL(IF(Pendencias!$B$2:$B$209=$F$1,ROW(Pendencias!$B$2:$B$209)-1),ROW(A68)),7),"")} | AA60: {=IF(IFERROR(INDEX(Pendencias!$A$2:$O$209,SMALL(IF(Pendencias!$B$2:$B$209=$F$1,ROW(Pendencias!$B$2:$B$209)-1),ROW(A68)),9),"")=0,"",IFERROR(INDEX(Pendencias!$A$2:$O$209,SMALL(IF(Pendencias!$B$2:$B$209=$F$1,ROW(Pendencias!$B$2:$B$209)-1),ROW(A68)),9),""))}
A61: CheckList Procedimentos e Ficha de Campo | G61: =F1 -> AXYS039 | W61: {=IFERROR(INDEX(Pendencias!$A$2:$O$209,SMALL(IF(Pendencias!$B$2:$B$209=$F$1,ROW(Pendencias!$B$2:$B$209)-1),ROW(#REF!)),1),"")} | X61: {=IFERROR(INDEX(Pendencias!$A$2:$O$209,SMALL(IF(Pendencias!$B$2:$B$209=$F$1,ROW(Pendencias!$B$2:$B$209)-1),ROW(#REF!)),3),"")} | Y61: {=IFERROR(INDEX(Pendencias!$A$2:$O$209,SMALL(IF(Pendencias!$B$2:$B$209=$F$1,ROW(Pendencias!$B$2:$B$209)-1),ROW(#REF!)),4),"")} | Z61: {=IFERROR(INDEX(Pendencias!$A$2:$O$209,SMALL(IF(Pendencias!$B$2:$B$209=$F$1,ROW(Pendencias!$B$2:$B$209)-1),ROW(#REF!)),7),"")} | AA61: {=IF(IFERROR(INDEX(Pendencias!$A$2:$O$209,SMALL(IF(Pendencias!$B$2:$B$209=$F$1,ROW(Pendencias!$B$2:$B$209)-1),ROW(#REF!)),9),"")=0,"",IFERROR(INDEX(Pendencias!$A$2:$O$209,SMALL(IF(Pendencias!$B$2:$B$209=$F$1,ROW(Pendencias!$B$2:$B$209)-1),ROW(#REF!)),9),""))}
W62: {=IFERROR(INDEX(Pendencias!$A$2:$O$209,SMALL(IF(Pendencias!$B$2:$B$209=$F$1,ROW(Pendencias!$B$2:$B$209)-1),ROW(A69)),1),"")} | X62: {=IFERROR(INDEX(Pendencias!$A$2:$O$209,SMALL(IF(Pendencias!$B$2:$B$209=$F$1,ROW(Pendencias!$B$2:$B$209)-1),ROW(A69)),3),"")} | Y62: {=IFERROR(INDEX(Pendencias!$A$2:$O$209,SMALL(IF(Pendencias!$B$2:$B$209=$F$1,ROW(Pendencias!$B$2:$B$209)-1),ROW(A69)),4),"")} | Z62: {=IFERROR(INDEX(Pendencias!$A$2:$O$209,SMALL(IF(Pendencias!$B$2:$B$209=$F$1,ROW(Pendencias!$B$2:$B$209)-1),ROW(A69)),7),"")} | AA62: {=IF(IFERROR(INDEX(Pendencias!$A$2:$O$209,SMALL(IF(Pendencias!$B$2:$B$209=$F$1,ROW(Pendencias!$B$2:$B$209)-1),ROW(A69)),9),"")=0,"",IFERROR(INDEX(Pendencias!$A$2:$O$209,SMALL(IF(Pendencias!$B$2:$B$209=$F$1,ROW(Pendencias!$B$2:$B$209)-1),ROW(A69)),9),""))}
A63: Checklist de Fotografias Obrigatórias (Após manobra de movimentação de carga) | W63: {=IFERROR(INDEX(Pendencias!$A$2:$O$209,SMALL(IF(Pendencias!$B$2:$B$209=$F$1,ROW(Pendencias!$B$2:$B$209)-1),ROW(A66)),1),"")} | X63: {=IFERROR(INDEX(Pendencias!$A$2:$O$209,SMALL(IF(Pendencias!$B$2:$B$209=$F$1,ROW(Pendencias!$B$2:$B$209)-1),ROW(A66)),3),"")} | Y63: {=IFERROR(INDEX(Pendencias!$A$2:$O$209,SMALL(IF(Pendencias!$B$2:$B$209=$F$1,ROW(Pendencias!$B$2:$B$209)-1),ROW(A66)),4),"")} | Z63: {=IFERROR(INDEX(Pendencias!$A$2:$O$209,SMALL(IF(Pendencias!$B$2:$B$209=$F$1,ROW(Pendencias!$B$2:$B$209)-1),ROW(A66)),7),"")} | AA63: {=IF(IFERROR(INDEX(Pendencias!$A$2:$O$209,SMALL(IF(Pendencias!$B$2:$B$209=$F$1,ROW(Pendencias!$B$2:$B$209)-1),ROW(A66)),9),"")=0,"",IFERROR(INDEX(Pendencias!$A$2:$O$209,SMALL(IF(Pendencias!$B$2:$B$209=$F$1,ROW(Pendencias!$B$2:$B$209)-1),ROW(A66)),9),""))}
A64: Casco da boia | D64: Tripé | G64: Orientação anemômetros | W64: {=IFERROR(INDEX(Pendencias!$A$2:$O$209,SMALL(IF(Pendencias!$B$2:$B$209=$F$1,ROW(Pendencias!$B$2:$B$209)-1),ROW(A67)),1),"")} | X64: {=IFERROR(INDEX(Pendencias!$A$2:$O$209,SMALL(IF(Pendencias!$B$2:$B$209=$F$1,ROW(Pendencias!$B$2:$B$209)-1),ROW(A67)),3),"")} | Y64: {=IFERROR(INDEX(Pendencias!$A$2:$O$209,SMALL(IF(Pendencias!$B$2:$B$209=$F$1,ROW(Pendencias!$B$2:$B$209)-1),ROW(A67)),4),"")} | Z64: {=IFERROR(INDEX(Pendencias!$A$2:$O$209,SMALL(IF(Pendencias!$B$2:$B$209=$F$1,ROW(Pendencias!$B$2:$B$209)-1),ROW(A67)),7),"")} | AA64: {=IF(IFERROR(INDEX(Pendencias!$A$2:$O$209,SMALL(IF(Pendencias!$B$2:$B$209=$F$1,ROW(Pendencias!$B$2:$B$209)-1),ROW(A67)),9),"")=0,"",IFERROR(INDEX(Pendencias!$A$2:$O$209,SMALL(IF(Pendencias!$B$2:$B$209=$F$1,ROW(Pendencias!$B$2:$B$209)-1),ROW(A67)),9),""))}
A65: Cabos dos sensores | D65: Linha de fundeio | G65: Orientação ondógrafos | W65: {=IFERROR(INDEX(Pendencias!$A$2:$O$209,SMALL(IF(Pendencias!$B$2:$B$209=$F$1,ROW(Pendencias!$B$2:$B$209)-1),ROW(A68)),1),"")} | X65: {=IFERROR(INDEX(Pendencias!$A$2:$O$209,SMALL(IF(Pendencias!$B$2:$B$209=$F$1,ROW(Pendencias!$B$2:$B$209)-1),ROW(A68)),3),"")} | Y65: {=IFERROR(INDEX(Pendencias!$A$2:$O$209,SMALL(IF(Pendencias!$B$2:$B$209=$F$1,ROW(Pendencias!$B$2:$B$209)-1),ROW(A68)),4),"")} | Z65: {=IFERROR(INDEX(Pendencias!$A$2:$O$209,SMALL(IF(Pendencias!$B$2:$B$209=$F$1,ROW(Pendencias!$B$2:$B$209)-1),ROW(A68)),7),"")} | AA65: {=IF(IFERROR(INDEX(Pendencias!$A$2:$O$209,SMALL(IF(Pendencias!$B$2:$B$209=$F$1,ROW(Pendencias!$B$2:$B$209)-1),ROW(A68)),9),"")=0,"",IFERROR(INDEX(Pendencias!$A$2:$O$209,SMALL(IF(Pendencias!$B$2:$B$209=$F$1,ROW(Pendencias!$B$2:$B$209)-1),ROW(A68)),9),""))}
A66: Sensores | D66: Estruturas e suportes | G66: Charuto | I66: Poita | W66: {=IFERROR(INDEX(Pendencias!$A$2:$O$209,SMALL(IF(Pendencias!$B$2:$B$209=$F$1,ROW(Pendencias!$B$2:$B$209)-1),ROW(#REF!)),1),"")} | X66: {=IFERROR(INDEX(Pendencias!$A$2:$O$209,SMALL(IF(Pendencias!$B$2:$B$209=$F$1,ROW(Pendencias!$B$2:$B$209)-1),ROW(#REF!)),3),"")} | Y66: {=IFERROR(INDEX(Pendencias!$A$2:$O$209,SMALL(IF(Pendencias!$B$2:$B$209=$F$1,ROW(Pendencias!$B$2:$B$209)-1),ROW(#REF!)),4),"")} | Z66: {=IFERROR(INDEX(Pendencias!$A$2:$O$209,SMALL(IF(Pendencias!$B$2:$B$209=$F$1,ROW(Pendencias!$B$2:$B$209)-1),ROW(#REF!)),7),"")} | AA66: {=IF(IFERROR(INDEX(Pendencias!$A$2:$O$209,SMALL(IF(Pendencias!$B$2:$B$209=$F$1,ROW(Pendencias!$B$2:$B$209)-1),ROW(#REF!)),9),"")=0,"",IFERROR(INDEX(Pendencias!$A$2:$O$209,SMALL(IF(Pendencias!$B$2:$B$209=$F$1,ROW(Pendencias!$B$2:$B$209)-1),ROW(#REF!)),9),""))}
A67: Comprimento linha de fundeio: | C67: =I3+(I3*0.33) -> 0 | D67: Painel Solar | G67: Prensas cabo | W67: {=IFERROR(INDEX(Pendencias!$A$2:$O$209,SMALL(IF(Pendencias!$B$2:$B$209=$F$1,ROW(Pendencias!$B$2:$B$209)-1),ROW(A69)),1),"")} | X67: {=IFERROR(INDEX(Pendencias!$A$2:$O$209,SMALL(IF(Pendencias!$B$2:$B$209=$F$1,ROW(Pendencias!$B$2:$B$209)-1),ROW(A69)),3),"")} | Y67: {=IFERROR(INDEX(Pendencias!$A$2:$O$209,SMALL(IF(Pendencias!$B$2:$B$209=$F$1,ROW(Pendencias!$B$2:$B$209)-1),ROW(A69)),4),"")} | Z67: {=IFERROR(INDEX(Pendencias!$A$2:$O$209,SMALL(IF(Pendencias!$B$2:$B$209=$F$1,ROW(Pendencias!$B$2:$B$209)-1),ROW(A69)),7),"")} | AA67: {=IF(IFERROR(INDEX(Pendencias!$A$2:$O$209,SMALL(IF(Pendencias!$B$2:$B$209=$F$1,ROW(Pendencias!$B$2:$B$209)-1),ROW(A69)),9),"")=0,"",IFERROR(INDEX(Pendencias!$A$2:$O$209,SMALL(IF(Pendencias!$B$2:$B$209=$F$1,ROW(Pendencias!$B$2:$B$209)-1),ROW(A69)),9),""))}
W68: {=IFERROR(INDEX(Pendencias!$A$2:$O$209,SMALL(IF(Pendencias!$B$2:$B$209=$F$1,ROW(Pendencias!$B$2:$B$209)-1),ROW(A70)),1),"")} | X68: {=IFERROR(INDEX(Pendencias!$A$2:$O$209,SMALL(IF(Pendencias!$B$2:$B$209=$F$1,ROW(Pendencias!$B$2:$B$209)-1),ROW(A70)),3),"")} | Y68: {=IFERROR(INDEX(Pendencias!$A$2:$O$209,SMALL(IF(Pendencias!$B$2:$B$209=$F$1,ROW(Pendencias!$B$2:$B$209)-1),ROW(A70)),4),"")} | Z68: {=IFERROR(INDEX(Pendencias!$A$2:$O$209,SMALL(IF(Pendencias!$B$2:$B$209=$F$1,ROW(Pendencias!$B$2:$B$209)-1),ROW(A70)),7),"")} | AA68: {=IF(IFERROR(INDEX(Pendencias!$A$2:$O$209,SMALL(IF(Pendencias!$B$2:$B$209=$F$1,ROW(Pendencias!$B$2:$B$209)-1),ROW(A70)),9),"")=0,"",IFERROR(INDEX(Pendencias!$A$2:$O$209,SMALL(IF(Pendencias!$B$2:$B$209=$F$1,ROW(Pendencias!$B$2:$B$209)-1),ROW(A70)),9),""))}
A69: Checklist de Fotografias Obrigatórias (Durante a comissão) | W69: {=IFERROR(INDEX(Pendencias!$A$2:$O$209,SMALL(IF(Pendencias!$B$2:$B$209=$F$1,ROW(Pendencias!$B$2:$B$209)-1),ROW(A72)),1),"")} | X69: {=IFERROR(INDEX(Pendencias!$A$2:$O$209,SMALL(IF(Pendencias!$B$2:$B$209=$F$1,ROW(Pendencias!$B$2:$B$209)-1),ROW(A72)),3),"")} | Y69: {=IFERROR(INDEX(Pendencias!$A$2:$O$209,SMALL(IF(Pendencias!$B$2:$B$209=$F$1,ROW(Pendencias!$B$2:$B$209)-1),ROW(A72)),4),"")} | Z69: {=IFERROR(INDEX(Pendencias!$A$2:$O$209,SMALL(IF(Pendencias!$B$2:$B$209=$F$1,ROW(Pendencias!$B$2:$B$209)-1),ROW(A72)),7),"")} | AA69: {=IF(IFERROR(INDEX(Pendencias!$A$2:$O$209,SMALL(IF(Pendencias!$B$2:$B$209=$F$1,ROW(Pendencias!$B$2:$B$209)-1),ROW(A72)),9),"")=0,"",IFERROR(INDEX(Pendencias!$A$2:$O$209,SMALL(IF(Pendencias!$B$2:$B$209=$F$1,ROW(Pendencias!$B$2:$B$209)-1),ROW(A72)),9),""))}
A70: Embarcação | D70: Material Embarcado | G70: Chegando / Saindo da Estação | W70: {=IFERROR(INDEX(Pendencias!$A$2:$O$209,SMALL(IF(Pendencias!$B$2:$B$209=$F$1,ROW(Pendencias!$B$2:$B$209)-1),ROW(A73)),1),"")} | X70: {=IFERROR(INDEX(Pendencias!$A$2:$O$209,SMALL(IF(Pendencias!$B$2:$B$209=$F$1,ROW(Pendencias!$B$2:$B$209)-1),ROW(A73)),3),"")} | Y70: {=IFERROR(INDEX(Pendencias!$A$2:$O$209,SMALL(IF(Pendencias!$B$2:$B$209=$F$1,ROW(Pendencias!$B$2:$B$209)-1),ROW(A73)),4),"")} | Z70: {=IFERROR(INDEX(Pendencias!$A$2:$O$209,SMALL(IF(Pendencias!$B$2:$B$209=$F$1,ROW(Pendencias!$B$2:$B$209)-1),ROW(A73)),7),"")} | AA70: {=IF(IFERROR(INDEX(Pendencias!$A$2:$O$209,SMALL(IF(Pendencias!$B$2:$B$209=$F$1,ROW(Pendencias!$B$2:$B$209)-1),ROW(A73)),9),"")=0,"",IFERROR(INDEX(Pendencias!$A$2:$O$209,SMALL(IF(Pendencias!$B$2:$B$209=$F$1,ROW(Pendencias!$B$2:$B$209)-1),ROW(A73)),9),""))}
A71: Caixa dentro / fora | D71: Mergulhador | G71: Anemômetros | W71: {=IFERROR(INDEX(Pendencias!$A$2:$O$209,SMALL(IF(Pendencias!$B$2:$B$209=$F$1,ROW(Pendencias!$B$2:$B$209)-1),ROW(A74)),1),"")} | X71: {=IFERROR(INDEX(Pendencias!$A$2:$O$209,SMALL(IF(Pendencias!$B$2:$B$209=$F$1,ROW(Pendencias!$B$2:$B$209)-1),ROW(A74)),3),"")} | Y71: {=IFERROR(INDEX(Pendencias!$A$2:$O$209,SMALL(IF(Pendencias!$B$2:$B$209=$F$1,ROW(Pendencias!$B$2:$B$209)-1),ROW(A74)),4),"")} | Z71: {=IFERROR(INDEX(Pendencias!$A$2:$O$209,SMALL(IF(Pendencias!$B$2:$B$209=$F$1,ROW(Pendencias!$B$2:$B$209)-1),ROW(A74)),7),"")} | AA71: {=IF(IFERROR(INDEX(Pendencias!$A$2:$O$209,SMALL(IF(Pendencias!$B$2:$B$209=$F$1,ROW(Pendencias!$B$2:$B$209)-1),ROW(A74)),9),"")=0,"",IFERROR(INDEX(Pendencias!$A$2:$O$209,SMALL(IF(Pendencias!$B$2:$B$209=$F$1,ROW(Pendencias!$B$2:$B$209)-1),ROW(A74)),9),""))}
A72: Conector ADCP | D72: Estruturas e suportes | G72: Rastreador | I72: Boia | W72: {=IFERROR(INDEX(Pendencias!$A$2:$O$209,SMALL(IF(Pendencias!$B$2:$B$209=$F$1,ROW(Pendencias!$B$2:$B$209)-1),ROW(A75)),1),"")} | X72: {=IFERROR(INDEX(Pendencias!$A$2:$O$209,SMALL(IF(Pendencias!$B$2:$B$209=$F$1,ROW(Pendencias!$B$2:$B$209)-1),ROW(A75)),3),"")} | Y72: {=IFERROR(INDEX(Pendencias!$A$2:$O$209,SMALL(IF(Pendencias!$B$2:$B$209=$F$1,ROW(Pendencias!$B$2:$B$209)-1),ROW(A75)),4),"")} | Z72: {=IFERROR(INDEX(Pendencias!$A$2:$O$209,SMALL(IF(Pendencias!$B$2:$B$209=$F$1,ROW(Pendencias!$B$2:$B$209)-1),ROW(A75)),7),"")} | AA72: {=IF(IFERROR(INDEX(Pendencias!$A$2:$O$209,SMALL(IF(Pendencias!$B$2:$B$209=$F$1,ROW(Pendencias!$B$2:$B$209)-1),ROW(A75)),9),"")=0,"",IFERROR(INDEX(Pendencias!$A$2:$O$209,SMALL(IF(Pendencias!$B$2:$B$209=$F$1,ROW(Pendencias!$B$2:$B$209)-1),ROW(A75)),9),""))}
A73: Est. Meteorológica | D73: Painel Solar | G73: Fotos para Marketing | W73: {=IFERROR(INDEX(Pendencias!$A$2:$O$209,SMALL(IF(Pendencias!$B$2:$B$209=$F$1,ROW(Pendencias!$B$2:$B$209)-1),ROW(A76)),1),"")} | X73: {=IFERROR(INDEX(Pendencias!$A$2:$O$209,SMALL(IF(Pendencias!$B$2:$B$209=$F$1,ROW(Pendencias!$B$2:$B$209)-1),ROW(A76)),3),"")} | Y73: {=IFERROR(INDEX(Pendencias!$A$2:$O$209,SMALL(IF(Pendencias!$B$2:$B$209=$F$1,ROW(Pendencias!$B$2:$B$209)-1),ROW(A76)),4),"")} | Z73: {=IFERROR(INDEX(Pendencias!$A$2:$O$209,SMALL(IF(Pendencias!$B$2:$B$209=$F$1,ROW(Pendencias!$B$2:$B$209)-1),ROW(A76)),7),"")} | AA73: {=IF(IFERROR(INDEX(Pendencias!$A$2:$O$209,SMALL(IF(Pendencias!$B$2:$B$209=$F$1,ROW(Pendencias!$B$2:$B$209)-1),ROW(A76)),9),"")=0,"",IFERROR(INDEX(Pendencias!$A$2:$O$209,SMALL(IF(Pendencias!$B$2:$B$209=$F$1,ROW(Pendencias!$B$2:$B$209)-1),ROW(A76)),9),""))}
W74: {=IFERROR(INDEX(Pendencias!$A$2:$O$209,SMALL(IF(Pendencias!$B$2:$B$209=$F$1,ROW(Pendencias!$B$2:$B$209)-1),ROW(A77)),1),"")} | X74: {=IFERROR(INDEX(Pendencias!$A$2:$O$209,SMALL(IF(Pendencias!$B$2:$B$209=$F$1,ROW(Pendencias!$B$2:$B$209)-1),ROW(A77)),3),"")} | Y74: {=IFERROR(INDEX(Pendencias!$A$2:$O$209,SMALL(IF(Pendencias!$B$2:$B$209=$F$1,ROW(Pendencias!$B$2:$B$209)-1),ROW(A77)),4),"")} | Z74: {=IFERROR(INDEX(Pendencias!$A$2:$O$209,SMALL(IF(Pendencias!$B$2:$B$209=$F$1,ROW(Pendencias!$B$2:$B$209)-1),ROW(A77)),7),"")} | AA74: {=IF(IFERROR(INDEX(Pendencias!$A$2:$O$209,SMALL(IF(Pendencias!$B$2:$B$209=$F$1,ROW(Pendencias!$B$2:$B$209)-1),ROW(A77)),9),"")=0,"",IFERROR(INDEX(Pendencias!$A$2:$O$209,SMALL(IF(Pendencias!$B$2:$B$209=$F$1,ROW(Pendencias!$B$2:$B$209)-1),ROW(A77)),9),""))}
A75: Conservação das Estruturas (OK = ótimo estado; Observação = foi observada alguma anomalia/observação; Foi Subst = foi substituído). Descrever as observações/anomalias abaixo. | W75: {=IFERROR(INDEX(Pendencias!$A$2:$O$209,SMALL(IF(Pendencias!$B$2:$B$209=$F$1,ROW(Pendencias!$B$2:$B$209)-1),ROW(A78)),1),"")} | X75: {=IFERROR(INDEX(Pendencias!$A$2:$O$209,SMALL(IF(Pendencias!$B$2:$B$209=$F$1,ROW(Pendencias!$B$2:$B$209)-1),ROW(A78)),3),"")} | Y75: {=IFERROR(INDEX(Pendencias!$A$2:$O$209,SMALL(IF(Pendencias!$B$2:$B$209=$F$1,ROW(Pendencias!$B$2:$B$209)-1),ROW(A78)),4),"")} | Z75: {=IFERROR(INDEX(Pendencias!$A$2:$O$209,SMALL(IF(Pendencias!$B$2:$B$209=$F$1,ROW(Pendencias!$B$2:$B$209)-1),ROW(A78)),7),"")} | AA75: {=IF(IFERROR(INDEX(Pendencias!$A$2:$O$209,SMALL(IF(Pendencias!$B$2:$B$209=$F$1,ROW(Pendencias!$B$2:$B$209)-1),ROW(A78)),9),"")=0,"",IFERROR(INDEX(Pendencias!$A$2:$O$209,SMALL(IF(Pendencias!$B$2:$B$209=$F$1,ROW(Pendencias!$B$2:$B$209)-1),ROW(A78)),9),""))}
